Workbook
Name ConxBase: OFFSET(CONEXIONES!$C$10,0,0,MAX(1,COUNT(CONEXIONES!$A$10:$A$40)),1)
Name ConxDesc: OFFSET(CONEXIONES!$Y$10,0,0,MAX(1,COUNT(CONEXIONES!$A$10:$A$40)),1)
Name ConxDia: OFFSET(CONEXIONES!$B$10,0,0,MAX(1,COUNT(CONEXIONES!$A$10:$A$40)),1)
Name ConxMax: OFFSET(CONEXIONES!$D$10,0,0,MAX(1,COUNT(CONEXIONES!$A$10:$A$40)),1)
Name ConxNuevas: OFFSET(CONEXIONES!$E$10,0,0,MAX(1,COUNT(CONEXIONES!$A$10:$A$40)),1)
Name ConxPPK: OFFSET(CONEXIONES!$G$10,0,0,MAX(1,COUNT(CONEXIONES!$A$10:$A$40)),1)
Name ConxTotal: OFFSET(CONEXIONES!$H$10,0,0,MAX(1,COUNT(CONEXIONES!$A$10:$A$40)),1)
Name GrafCosto: OFFSET('VISTA MES'!$O$10,0,0,MAX(1,COUNT('VISTA MES'!$A$10:$A$39)),1)
Name GrafNaves: OFFSET('VISTA MES'!$E$10,0,0,MAX(1,COUNT('VISTA MES'!$A$10:$A$39)),1)
Name GrafVenta: OFFSET('VISTA MES'!$J$10,0,0,MAX(1,COUNT('VISTA MES'!$A$10:$A$39)),1)

Sheet RESUMEN
A1: REPORTE REEFER — COSTOS REALES 2026
A2: Costos reales PPK y SITRANS en CLP. Combustible total mensual en USD, sin distribución por nave.
A3: ="ÚLTIMO MES CON COSTOS REALES: "&UPPER(INDEX($A$9:$A$20,COUNT($B$9:$B$20)))&" 2026" -> ÚLTIMO MES CON COSTOS REALES: SEPTIEMBRE 2026
A4: REEFERS | C4: PPK ÚNICOS | E4: DÍAS-PPK | G4: PPK + SITRANS CLP | I4: COMBUSTIBLE USD | K4: ESTADO EDP | M4: COSTO TOTAL CLP/REEFER
A5: =INDEX($B$9:$B$20,COUNT($B$9:$B$20)) -> 1151 | C5: =INDEX($C$9:$C$20,COUNT($B$9:$B$20)) -> 9 | E5: =INDEX($D$9:$D$20,COUNT($B$9:$B$20)) -> 90 | G5: =INDEX($G$9:$G$20,COUNT($B$9:$B$20)) -> 39938519 | I5: =INDEX($J$9:$J$20,COUNT($B$9:$B$20)) -> 79706.23 | K5: =INDEX($L$9:$L$20,COUNT($B$9:$B$20)) -> Disponible incompleto | M5: =INDEX($O$9:$O$20,COUNT($B$9:$B$20)) -> 97369.815
A8: Mes | B8: Reefers | C8: PPK únicos | D8: Días-PPK | E8: SITRANS CLP | F8: PPK CLP | G8: Total CLP | H8: CLP/reefer | I8: Combustible L | J8: Combustible USD | K8: Estadía prom. días | L8: Estado EDP | M8: TC CLP/USD | N8: Costo total CLP | O8: Costo total CLP/reefer | P8: % SITRANS | Q8: % PPK | R8: % Combustible | S8: Var. reefers % | T8: Var. costo total % | U8: US$ combustible/reefer-día | V8: Venta real USD | W8: Costo real USD | X8: Margen real USD | Y8: Margen real %
A9: Enero | B9: =IF(ACTUALIZAR!B7="","",ACTUALIZAR!B7) -> 88 | C9: =IF(PPK!B7="","",PPK!B7) -> 2 | D9: =IF(PPK!C7="","",PPK!C7) -> 31 | E9: =IF(ACTUALIZAR!C7="","",ACTUALIZAR!C7) -> 12918273 | F9: =IF(PPK!F7="","",PPK!F7) -> 9514784 | G9: =IF(AND(E9="",F9=""),"",SUM(E9:F9)) -> 22433057 | H9: =IFERROR(N9/B9,"") -> 348759.94 | I9: =IF(ACTUALIZAR!E7="","",ACTUALIZAR!E7) -> 13228.63 | J9: =IF(ACTUALIZAR!F7="","",ACTUALIZAR!F7) -> 9124.66 | K9: =IFERROR(SUMPRODUCT((NAVES!$A$7:$A$200=A9)*NAVES!$F$7:$F$200*NAVES!$G$7:$G$200)/SUMIF(NAVES!$A$7:$A$200,A9,NAVES!$F$7:$F$200),"") -> 6.1794074 | L9: =ACTUALIZAR!G7 -> Disponible | M9: =IF(ACTUALIZAR!I7="","",ACTUALIZAR!I7) -> 905 | N9: =IF(OR(G9="",J9="",M9=""),"",G9+J9*M9) -> 30690874 | O9: =IFERROR(N9/B9,"") -> 348759.94 | P9: =IFERROR(E9/N9,"") -> 0.42091577 | Q9: =IFERROR(F9/N9,"") -> 0.31001997 | R9: =IFERROR((J9*M9)/N9,"") -> 0.26906426 | S9: ="" | T9: ="" | U9: =IFERROR((J9/B9)/K9,"") -> 16.779816 | V9: 71088.33 | W9: =IFERROR(N9/M9,"") -> 33912.568 | X9: =IFERROR(V9-W9,"") -> 37175.762 | Y9: =IFERROR(X9/V9,"") -> 0.52295168
A10: Febrero | B10: =IF(ACTUALIZAR!B8="","",ACTUALIZAR!B8) -> 54 | C10: =IF(PPK!B8="","",PPK!B8) -> 2 | D10: =IF(PPK!C8="","",PPK!C8) -> 34 | E10: =IF(ACTUALIZAR!C8="","",ACTUALIZAR!C8) -> 12918273 | F10: =IF(PPK!F8="","",PPK!F8) -> 10336991 | G10: =IF(AND(E10="",F10=""),"",SUM(E10:F10)) -> 23255264 | H10: =IFERROR(N10/B10,"") -> 595963.52 | I10: =IF(ACTUALIZAR!E8="","",ACTUALIZAR!E8) -> 13525.31 | J10: =IF(ACTUALIZAR!F8="","",ACTUALIZAR!F8) -> 9863.83 | K10: =IFERROR(SUMPRODUCT((NAVES!$A$7:$A$200=A10)*NAVES!$F$7:$F$200*NAVES!$G$7:$G$200)/SUMIF(NAVES!$A$7:$A$200,A10,NAVES!$F$7:$F$200),"") -> 14.934472 | L10: =ACTUALIZAR!G8 -> Disponible incompleto | M10: =IF(ACTUALIZAR!I8="","",ACTUALIZAR!I8) -> 905 | N10: =IF(OR(G10="",J10="",M10=""),"",G10+J10*M10) -> 32182030 | O10: =IFERROR(N10/B10,"") -> 595963.52 | P10: =IFERROR(E10/N10,"") -> 0.40141262 | Q10: =IFERROR(F10/N10,"") -> 0.32120382 | R10: =IFERROR((J10*M10)/N10,"") -> 0.27738356 | S10: =IFERROR(B10/B9-1,"") -> -0.38636364 | T10: =IFERROR(N10/N9-1,"") -> 0.048586294 | U10: =IFERROR((J10/B10)/K10,"") -> 12.230999 | V10: 53916.57 | W10: =IFERROR(N10/M10,"") -> 35560.254 | X10: =IFERROR(V10-W10,"") -> 18356.316 | Y10: =IFERROR(X10/V10,"") -> 0.34045778
A11: Marzo | B11: =IF(ACTUALIZAR!B9="","",ACTUALIZAR!B9) -> 72 | C11: =IF(PPK!B9="","",PPK!B9) -> 2 | D11: =IF(PPK!C9="","",PPK!C9) -> 31 | E11: =IF(ACTUALIZAR!C9="","",ACTUALIZAR!C9) -> 12918273 | F11: =IF(PPK!F9="","",PPK!F9) -> 9514784 | G11: =IF(AND(E11="",F11=""),"",SUM(E11:F11)) -> 22433057 | H11: =IFERROR(N11/B11,"") -> 423642.67 | I11: =IF(ACTUALIZAR!E9="","",ACTUALIZAR!E9) -> 7812.79 | J11: =IF(ACTUALIZAR!F9="","",ACTUALIZAR!F9) -> 8916.26 | K11: =IFERROR(SUMPRODUCT((NAVES!$A$7:$A$200=A11)*NAVES!$F$7:$F$200*NAVES!$G$7:$G$200)/SUMIF(NAVES!$A$7:$A$200,A11,NAVES!$F$7:$F$200),"") -> 8.1315297 | L11: =ACTUALIZAR!G9 -> Disponible | M11: =IF(ACTUALIZAR!I9="","",ACTUALIZAR!I9) -> 905 | N11: =IF(OR(G11="",J11="",M11=""),"",G11+J11*M11) -> 30502272 | O11: =IFERROR(N11/B11,"") -> 423642.67 | P11: =IFERROR(E11/N11,"") -> 0.42351838 | Q11: =IFERROR(F11/N11,"") -> 0.31193689 | R11: =IFERROR((J11*M11)/N11,"") -> 0.26454473 | S11: =IFERROR(B11/B10-1,"") -> 0.33333333 | T11: =IFERROR(N11/N10-1,"") -> -0.052195522 | U11: =IFERROR((J11/B11)/K11,"") -> 15.229231 | V11: 71738.1 | W11: =IFERROR(N11/M11,"") -> 33704.168 | X11: =IFERROR(V11-W11,"") -> 38033.932 | Y11: =IFERROR(X11/V11,"") -> 0.53017757
A12: Abril | B12: =IF(ACTUALIZAR!B10="","",ACTUALIZAR!B10) -> 23 | C12: =IF(PPK!B10="","",PPK!B10) -> 1 | D12: =IF(PPK!C10="","",PPK!C10) -> 30 | E12: =IF(ACTUALIZAR!C10="","",ACTUALIZAR!C10) -> 12918273 | F12: =IF(PPK!F10="","",PPK!F10) -> 9240715 | G12: =IF(AND(E12="",F12=""),"",SUM(E12:F12)) -> 22158988 | H12: =IFERROR(N12/B12,"") -> 1004353.6 | I12: =IF(ACTUALIZAR!E10="","",ACTUALIZAR!E10) -> 804.81 | J12: =IF(ACTUALIZAR!F10="","",ACTUALIZAR!F10) -> 1039.94 | K12: =IFERROR(SUMPRODUCT((NAVES!$A$7:$A$200=A12)*NAVES!$F$7:$F$200*NAVES!$G$7:$G$200)/SUMIF(NAVES!$A$7:$A$200,A12,NAVES!$F$7:$F$200),"") -> 6.2434179 | L12: =ACTUALIZAR!G10 -> Disponible | M12: =IF(ACTUALIZAR!I10="","",ACTUALIZAR!I10) -> 905 | N12: =IF(OR(G12="",J12="",M12=""),"",G12+J12*M12) -> 23100134 | O12: =IFERROR(N12/B12,"") -> 1004353.6 | P12: =IFERROR(E12/N12,"") -> 0.55922936 | Q12: =IFERROR(F12/N12,"") -> 0.40002864 | R12: =IFERROR((J12*M12)/N12,"") -> 0.040742002 | S12: =IFERROR(B12/B11-1,"") -> -0.68055556 | T12: =IFERROR(N12/N11-1,"") -> -0.24267499 | U12: =IFERROR((J12/B12)/K12,"") -> 7.241992 | V12: 19736 | W12: =IFERROR(N12/M12,"") -> 25525.01 | X12: =IFERROR(V12-W12,"") -> -5789.0096 | Y12: =IFERROR(X12/V12,"") -> -0.29332234
A13: Mayo | B13: =IF(ACTUALIZAR!B11="","",ACTUALIZAR!B11) -> 47 | C13: =IF(PPK!B11="","",PPK!B11) -> 2 | D13: =IF(PPK!C11="","",PPK!C11) -> 31 | E13: =IF(ACTUALIZAR!C11="","",ACTUALIZAR!C11) -> 12918273 | F13: =IF(PPK!F11="","",PPK!F11) -> 9514784 | G13: =IF(AND(E13="",F13=""),"",SUM(E13:F13)) -> 22433057 | H13: =IFERROR(N13/B13,"") -> 700396.32 | I13: =IF(ACTUALIZAR!E11="","",ACTUALIZAR!E11) -> 8444.64 | J13: =IF(ACTUALIZAR!F11="","",ACTUALIZAR!F11) -> 11586.265 | K13: =IFERROR(SUMPRODUCT((NAVES!$A$7:$A$200=A13)*NAVES!$F$7:$F$200*NAVES!$G$7:$G$200)/SUMIF(NAVES!$A$7:$A$200,A13,NAVES!$F$7:$F$200),"") -> 6.4853086 | L13: =ACTUALIZAR!G11 -> Disponible incompleto | M13: =IF(ACTUALIZAR!I11="","",ACTUALIZAR!I11) -> 905 | N13: =IF(OR(G13="",J13="",M13=""),"",G13+J13*M13) -> 32918627 | O13: =IFERROR(N13/B13,"") -> 700396.32 | P13: =IFERROR(E13/N13,"") -> 0.39243049 | Q13: =IFERROR(F13/N13,"") -> 0.28903952 | R13: =IFERROR((J13*M13)/N13,"") -> 0.31852999 | S13: =IFERROR(B13/B12-1,"") -> 1.0434783 | T13: =IFERROR(N13/N12-1,"") -> 0.42504053 | U13: =IFERROR((J13/B13)/K13,"") -> 38.011495 | V13: 41288 | W13: =IFERROR(N13/M13,"") -> 36374.173 | X13: =IFERROR(V13-W13,"") -> 4913.8267 | Y13: =IFERROR(X13/V13,"") -> 0.11901343
A14: Junio | B14: =IF(ACTUALIZAR!B12="","",ACTUALIZAR!B12) -> 213 | C14: =IF(PPK!B12="","",PPK!B12) -> 3 | D14: =IF(PPK!C12="","",PPK!C12) -> 32 | E14: =IF(ACTUALIZAR!C12="","",ACTUALIZAR!C12) -> 12918273 | F14: =IF(PPK!F12="","",PPK!F12) -> 9788853 | G14: =IF(AND(E14="",F14=""),"",SUM(E14:F14)) -> 22707126 | H14: =IFERROR(N14/B14,"") -> 137879.03 | I14: =IF(ACTUALIZAR!E12="","",ACTUALIZAR!E12) -> 7391.7 | J14: =IF(ACTUALIZAR!F12="","",ACTUALIZAR!F12) -> 7360.34 | K14: =IFERROR(SUMPRODUCT((NAVES!$A$7:$A$200=A14)*NAVES!$F$7:$F$200*NAVES!$G$7:$G$200)/SUMIF(NAVES!$A$7:$A$200,A14,NAVES!$F$7:$F$200),"") -> 1.7942195 | L14: =ACTUALIZAR!G12 -> Disponible | M14: =IF(ACTUALIZAR!I12="","",ACTUALIZAR!I12) -> 905 | N14: =IF(OR(G14="",J14="",M14=""),"",G14+J14*M14) -> 29368234 | O14: =IFERROR(N14/B14,"") -> 137879.03 | P14: =IFERROR(E14/N14,"") -> 0.43987232 | Q14: =IFERROR(F14/N14,"") -> 0.33331433 | R14: =IFERROR((J14*M14)/N14,"") -> 0.22681336 | S14: =IFERROR(B14/B13-1,"") -> 3.5319149 | T14: =IFERROR(N14/N13-1,"") -> -0.10785362 | U14: =IFERROR((J14/B14)/K14,"") -> 19.259398 | V14: 54592 | W14: =IFERROR(N14/M14,"") -> 32451.087 | X14: =IFERROR(V14-W14,"") -> 22140.913 | Y14: =IFERROR(X14/V14,"") -> 0.40557065
A15: Julio | B15: =IF(ACTUALIZAR!B13="","",ACTUALIZAR!B13) -> 547 | C15: =IF(PPK!B13="","",PPK!B13) -> 4 | D15: =IF(PPK!C13="","",PPK!C13) -> 35 | E15: =IF(ACTUALIZAR!C13="","",ACTUALIZAR!C13) -> 13585968 | F15: =IF(PPK!F13="","",PPK!F13) -> 10611062 | G15: =IF(AND(E15="",F15=""),"",SUM(E15:F15)) -> 24197030 | H15: =IFERROR(N15/B15,"") -> 80687.65 | I15: =IF(ACTUALIZAR!E13="","",ACTUALIZAR!E13) -> 19860.92 | J15: =IF(ACTUALIZAR!F13="","",ACTUALIZAR!F13) -> 22032.17 | K15: =IFERROR(SUMPRODUCT((NAVES!$A$7:$A$200=A15)*NAVES!$F$7:$F$200*NAVES!$G$7:$G$200)/SUMIF(NAVES!$A$7:$A$200,A15,NAVES!$F$7:$F$200),"") -> 2.3124476 | L15: =ACTUALIZAR!G13 -> Disponible incompleto | M15: =IF(ACTUALIZAR!I13="","",ACTUALIZAR!I13) -> 905 | N15: =IF(OR(G15="",J15="",M15=""),"",G15+J15*M15) -> 44136144 | O15: =IFERROR(N15/B15,"") -> 80687.65 | P15: =IFERROR(E15/N15,"") -> 0.30781956 | Q15: =IFERROR(F15/N15,"") -> 0.24041661 | R15: =IFERROR((J15*M15)/N15,"") -> 0.45176384 | S15: =IFERROR(B15/B14-1,"") -> 1.5680751 | T15: =IFERROR(N15/N14-1,"") -> 0.50285321 | U15: =IFERROR((J15/B15)/K15,"") -> 17.417991 | V15: 198088 | W15: =IFERROR(N15/M15,"") -> 48769.22 | X15: =IFERROR(V15-W15,"") -> 149318.78 | Y15: =IFERROR(X15/V15,"") -> 0.75380023
A16: Agosto | B16: =IF(ACTUALIZAR!B14="","",ACTUALIZAR!B14) -> 751 | C16: =IF(PPK!B14="","",PPK!B14) -> 9 | D16: =IF(PPK!C14="","",PPK!C14) -> 74 | E16: =IF(ACTUALIZAR!C14="","",ACTUALIZAR!C14) -> 13919815 | F16: =IF(PPK!F14="","",PPK!F14) -> 21299751 | G16: =IF(AND(E16="",F16=""),"",SUM(E16:F16)) -> 35219566 | H16: =IFERROR(N16/B16,"") -> 104647.34 | I16: =IF(ACTUALIZAR!E14="","",ACTUALIZAR!E14) -> 39428.23 | J16: =IF(ACTUALIZAR!F14="","",ACTUALIZAR!F14) -> 47923.3 | K16: =IFERROR(SUMPRODUCT((NAVES!$A$7:$A$200=A16)*NAVES!$F$7:$F$200*NAVES!$G$7:$G$200)/SUMIF(NAVES!$A$7:$A$200,A16,NAVES!$F$7:$F$200),"") -> 2.9878828 | L16: =ACTUALIZAR!G14 -> Disponible | M16: =IF(ACTUALIZAR!I14="","",ACTUALIZAR!I14) -> 905 | N16: =IF(OR(G16="",J16="",M16=""),"",G16+J16*M16) -> 78590153 | O16: =IFERROR(N16/B16,"") -> 104647.34 | P16: =IFERROR(E16/N16,"") -> 0.17711907 | Q16: =IFERROR(F16/N16,"") -> 0.27102315 | R16: =IFERROR((J16*M16)/N16,"") -> 0.55185777 | S16: =IFERROR(B16/B15-1,"") -> 0.37294333 | T16: =IFERROR(N16/N15-1,"") -> 0.78063023 | U16: =IFERROR((J16/B16)/K16,"") -> 21.357146 | V16: 305408 | W16: =IFERROR(N16/M16,"") -> 86839.948 | X16: =IFERROR(V16-W16,"") -> 218568.05 | Y16: =IFERROR(X16/V16,"") -> 0.71565922
A17: Septiembre | B17: =IF(ACTUALIZAR!B15="","",ACTUALIZAR!B15) -> 1151 | C17: =IF(PPK!B15="","",PPK!B15) -> 9 | D17: =IF(PPK!C15="","",PPK!C15) -> 90 | E17: =IF(ACTUALIZAR!C15="","",ACTUALIZAR!C15) -> 14253664 | F17: =IF(PPK!F15="","",PPK!F15) -> 25684855 | G17: =IF(AND(E17="",F17=""),"",SUM(E17:F17)) -> 39938519 | H17: =IFERROR(N17/B17,"") -> 97369.815 | I17: =IF(ACTUALIZAR!E15="","",ACTUALIZAR!E15) -> 58941.29 | J17: =IF(ACTUALIZAR!F15="","",ACTUALIZAR!F15) -> 79706.23 | K17: =IFERROR(SUMPRODUCT((NAVES!$A$7:$A$200=A17)*NAVES!$F$7:$F$200*NAVES!$G$7:$G$200)/SUMIF(NAVES!$A$7:$A$200,A17,NAVES!$F$7:$F$200),"") -> 2.8327074 | L17: =ACTUALIZAR!G15 -> Disponible incompleto | M17: =IF(ACTUALIZAR!I15="","",ACTUALIZAR!I15) -> 905 | N17: =IF(OR(G17="",J17="",M17=""),"",G17+J17*M17) -> 1.1207266e+08 | O17: =IFERROR(N17/B17,"") -> 97369.815 | P17: =IFERROR(E17/N17,"") -> 0.12718235 | Q17: =IFERROR(F17/N17,"") -> 0.22918039 | R17: =IFERROR((J17*M17)/N17,"") -> 0.64363726 | S17: =IFERROR(B17/B16-1,"") -> 0.53262317 | T17: =IFERROR(N17/N16-1,"") -> 0.42603944 | U17: =IFERROR((J17/B17)/K17,"") -> 24.446417 | V17: 630824 | W17: =IFERROR(N17/M17,"") -> 123837.19 | X17: =IFERROR(V17-W17,"") -> 506986.81 | Y17: =IFERROR(X17/V17,"") -> 0.80368979
A18: Octubre | B18: =IF(ACTUALIZAR!B16="","",ACTUALIZAR!B16) | C18: =IF(PPK!B16="","",PPK!B16) | D18: =IF(PPK!C16="","",PPK!C16) | E18: =IF(ACTUALIZAR!C16="","",ACTUALIZAR!C16) | F18: =IF(PPK!F16="","",PPK!F16) | G18: =IF(AND(E18="",F18=""),"",SUM(E18:F18)) | H18: =IFERROR(N18/B18,"") | I18: =IF(ACTUALIZAR!E16="","",ACTUALIZAR!E16) | J18: =IF(ACTUALIZAR!F16="","",ACTUALIZAR!F16) | K18: =IFERROR(SUMPRODUCT((NAVES!$A$7:$A$200=A18)*NAVES!$F$7:$F$200*NAVES!$G$7:$G$200)/SUMIF(NAVES!$A$7:$A$200,A18,NAVES!$F$7:$F$200),"") | L18: =ACTUALIZAR!G16 -> Pendiente | M18: =IF(ACTUALIZAR!I16="","",ACTUALIZAR!I16) | N18: =IF(OR(G18="",J18="",M18=""),"",G18+J18*M18) | O18: =IFERROR(N18/B18,"") | P18: =IFERROR(E18/N18,"") | Q18: =IFERROR(F18/N18,"") | R18: =IFERROR((J18*M18)/N18,"") | S18: =IFERROR(B18/B17-1,"") | T18: =IFERROR(N18/N17-1,"") | U18: =IFERROR((J18/B18)/K18,"") | W18: =IFERROR(N18/M18,"") | X18: =IFERROR(V18-W18,"") | Y18: =IFERROR(X18/V18,"")
A19: Noviembre | B19: =IF(ACTUALIZAR!B17="","",ACTUALIZAR!B17) | C19: =IF(PPK!B17="","",PPK!B17) | D19: =IF(PPK!C17="","",PPK!C17) | E19: =IF(ACTUALIZAR!C17="","",ACTUALIZAR!C17) | F19: =IF(PPK!F17="","",PPK!F17) | G19: =IF(AND(E19="",F19=""),"",SUM(E19:F19)) | H19: =IFERROR(N19/B19,"") | I19: =IF(ACTUALIZAR!E17="","",ACTUALIZAR!E17) | J19: =IF(ACTUALIZAR!F17="","",ACTUALIZAR!F17) | K19: =IFERROR(SUMPRODUCT((NAVES!$A$7:$A$200=A19)*NAVES!$F$7:$F$200*NAVES!$G$7:$G$200)/SUMIF(NAVES!$A$7:$A$200,A19,NAVES!$F$7:$F$200),"") | L19: =ACTUALIZAR!G17 -> Pendiente | M19: =IF(ACTUALIZAR!I17="","",ACTUALIZAR!I17) | N19: =IF(OR(G19="",J19="",M19=""),"",G19+J19*M19) | O19: =IFERROR(N19/B19,"") | P19: =IFERROR(E19/N19,"") | Q19: =IFERROR(F19/N19,"") | R19: =IFERROR((J19*M19)/N19,"") | S19: =IFERROR(B19/B18-1,"") | T19: =IFERROR(N19/N18-1,"") | U19: =IFERROR((J19/B19)/K19,"") | W19: =IFERROR(N19/M19,"") | X19: =IFERROR(V19-W19,"") | Y19: =IFERROR(X19/V19,"")
A20: Diciembre | B20: =IF(ACTUALIZAR!B18="","",ACTUALIZAR!B18) | C20: =IF(PPK!B18="","",PPK!B18) | D20: =IF(PPK!C18="","",PPK!C18) | E20: =IF(ACTUALIZAR!C18="","",ACTUALIZAR!C18) | F20: =IF(PPK!F18="","",PPK!F18) | G20: =IF(AND(E20="",F20=""),"",SUM(E20:F20)) | H20: =IFERROR(N20/B20,"") | I20: =IF(ACTUALIZAR!E18="","",ACTUALIZAR!E18) | J20: =IF(ACTUALIZAR!F18="","",ACTUALIZAR!F18) | K20: =IFERROR(SUMPRODUCT((NAVES!$A$7:$A$200=A20)*NAVES!$F$7:$F$200*NAVES!$G$7:$G$200)/SUMIF(NAVES!$A$7:$A$200,A20,NAVES!$F$7:$F$200),"") | L20: =ACTUALIZAR!G18 -> Pendiente | M20: =IF(ACTUALIZAR!I18="","",ACTUALIZAR!I18) | N20: =IF(OR(G20="",J20="",M20=""),"",G20+J20*M20) | O20: =IFERROR(N20/B20,"") | P20: =IFERROR(E20/N20,"") | Q20: =IFERROR(F20/N20,"") | R20: =IFERROR((J20*M20)/N20,"") | S20: =IFERROR(B20/B19-1,"") | T20: =IFERROR(N20/N19-1,"") | U20: =IFERROR((J20/B20)/K20,"") | W20: =IFERROR(N20/M20,"") | X20: =IFERROR(V20-W20,"") | Y20: =IFERROR(X20/V20,"")
A21: TOTAL ENE–SEP | B21: =SUM(B9:B20) -> 2946 | D21: =SUM(D9:D20) -> 388 | E21: =SUM(E9:E20) -> 1.1926909e+08 | F21: =SUM(F9:F20) -> 115506579 | G21: =SUM(G9:G20) -> 2.3477566e+08 | H21: =IFERROR(G21/B21,"") -> 79693.029 | I21: =SUM(I9:I20) -> 169438.32 | J21: =SUM(J9:J20) -> 197553 | K21: =IFERROR(SUMPRODUCT(NAVES!$F$7:$F$200,NAVES!$G$7:$G$200)/SUM(NAVES!$F$7:$F$200),"") -> 3.2074956 | L21: Ene–Sep con EDP | N21: =IF(COUNT(N9:N20)=0,"",SUM(N9:N20)) -> 4.1356112e+08 | O21: =IFERROR(N21/B21,"") -> 140380.56 | P21: =IFERROR(E21/N21,"") -> 0.2883953 | Q21: =IFERROR(F21/N21,"") -> 0.27929748 | R21: =IFERROR((SUM(J9:J20)*905)/N21,"") -> 0.43230722 | V21: =IF(COUNT(V9:V20)=0,"",SUM(V9:V20)) -> 1446679 | W21: =IF(COUNT(W9:W20)=0,"",SUM(W9:W20)) -> 456973.62 | X21: =IFERROR(V21-W21,"") -> 989705.38 | Y21: =IFERROR(X21/V21,"") -> 0.68412231

Sheet VISTA MES
A1: VISTA POR MES — NAVES, VENTA Y MARGEN REEFER 2026
A2: Elige el mes en la celda amarilla. Reefers = OC SITRANS. Venta por nave: Naves por Servicios (Servicio Reefer). SITRANS y PPK se asignan por reefers; el combustible del mes se prorratea por reefers.
A4: MES | B4: Septiembre | D4: TC CLP/USD | E4: =IFERROR(INDEX(RESUMEN!$M$9:$M$20,MATCH($B$4,RESUMEN!$A$9:$A$20,0)),"") -> 905 | G4: Combustible mes USD | I4: =IFERROR(INDEX(RESUMEN!$J$9:$J$20,MATCH($B$4,RESUMEN!$A$9:$A$20,0)),"") -> 79706.23 | K4: Estado EDP | L4: =IFERROR(INDEX(ACTUALIZAR!$G$7:$G$18,MATCH($B$4,ACTUALIZAR!$A$7:$A$18,0)),"") -> Disponible incompleto | N4: Control venta vs RESUMEN | P4: =IFERROR(J40-INDEX(RESUMEN!$V$9:$V$20,MATCH($B$4,RESUMEN!$A$9:$A$20,0)),"") -> 0
A6: NAVES | C6: REEFERS OC | E6: VENTA USD | G6: COSTO USD | I6: MARGEN USD | K6: MARGEN % | M6: VENTA/REEFER | O6: COSTO/REEFER | Q6: ESTADÍA PROM.
A7: =IFERROR(MAX(NAVES!$P$7:$P$200),"") -> 18 | C7: =IFERROR(F40,"") -> 1151 | E7: =IFERROR(J40,"") -> 630824 | G7: =IFERROR(O40,"") -> 123837.19 | I7: =IFERROR(P40,"") -> 506986.81 | K7: =IFERROR(Q40,"") -> 0.80368979 | M7: =IFERROR(R40,"") -> 548.06603 | O7: =IFERROR(S40,"") -> 107.59096 | Q7: =IFERROR(H40,"") -> 2.8327074
A9: # | B9: CI | C9: Correlativo | D9: Línea | E9: Nave | F9: Reefers OC | G9: EDP válidos | H9: Estadía prom. días | I9: Estado EDP | J9: Venta USD | K9: SITRANS CLP | L9: PPK CLP | M9: Combustible CLP | N9: Costo total CLP | O9: Costo total USD | P9: Margen USD | Q9: Margen % | R9: Venta/reefer USD | S9: Costo/reefer USD
A10: =IF($U10="","",1) -> 1 | B10: =IF($U10="","",INDEX(NAVES!$B$7:$B$200,$U10)) -> 8426 | C10: =IF($U10="","",IF(INDEX(NAVES!$M$7:$M$200,$U10)="","",INDEX(NAVES!$M$7:$M$200,$U10))) -> 2026-182 | D10: =IF($U10="","",INDEX(NAVES!$C$7:$C$200,$U10)) -> Por confirmar | E10: =IF($U10="","",INDEX(NAVES!$D$7:$D$200,$U10)) -> ALIOTH 1 | F10: =IF($U10="","",INDEX(NAVES!$E$7:$E$200,$U10)) -> 1 | G10: =IF($U10="","",IF(INDEX(NAVES!$F$7:$F$200,$U10)="","",INDEX(NAVES!$F$7:$F$200,$U10))) -> 1 | H10: =IF($U10="","",IF(INDEX(NAVES!$G$7:$G$200,$U10)="","",INDEX(NAVES!$G$7:$G$200,$U10))) -> 6.04 | I10: =IF($U10="","",INDEX(NAVES!$H$7:$H$200,$U10)) -> Disponible | J10: =IF($U10="","",N(INDEX(NAVES!$N$7:$N$200,$U10))) -> 656 | K10: =IF($U10="","",N(INDEX(NAVES!$I$7:$I$200,$U10))) -> 12383.722 | L10: =IF($U10="","",N(INDEX(NAVES!$J$7:$J$200,$U10))) -> 22315.252 | M10: =IF($U10="","",IFERROR(F10/SUMIF(NAVES!$A$7:$A$200,$B$4,NAVES!$E$7:$E$200)*$I$4*$E$4,0)) -> 62670.841 | N10: =IF($U10="","",K10+L10+M10) -> 97369.815 | O10: =IF($U10="","",IFERROR(N10/$E$4,"")) -> 107.59096 | P10: =IF($U10="","",IFERROR(J10-O10,"")) -> 548.40904 | Q10: =IF($U10="","",IFERROR(P10/J10,"")) -> 0.8359894 | R10: =IF($U10="","",IFERROR(J10/F10,"")) -> 656 | S10: =IF($U10="","",IFERROR(O10/F10,"")) -> 107.59096 | U10: =IFERROR(MATCH(1,NAVES!$P$7:$P$200,0),"") -> 76
A11: =IF($U11="","",2) -> 2 | B11: =IF($U11="","",INDEX(NAVES!$B$7:$B$200,$U11)) -> 8427 | C11: =IF($U11="","",IF(INDEX(NAVES!$M$7:$M$200,$U11)="","",INDEX(NAVES!$M$7:$M$200,$U11))) -> 2026-181 | D11: =IF($U11="","",INDEX(NAVES!$C$7:$C$200,$U11)) -> MSC | E11: =IF($U11="","",INDEX(NAVES!$D$7:$D$200,$U11)) -> MSC ABUJA VI | F11: =IF($U11="","",INDEX(NAVES!$E$7:$E$200,$U11)) -> 4 | G11: =IF($U11="","",IF(INDEX(NAVES!$F$7:$F$200,$U11)="","",INDEX(NAVES!$F$7:$F$200,$U11))) -> 4 | H11: =IF($U11="","",IF(INDEX(NAVES!$G$7:$G$200,$U11)="","",INDEX(NAVES!$G$7:$G$200,$U11))) -> 5.44 | I11: =IF($U11="","",INDEX(NAVES!$H$7:$H$200,$U11)) -> Disponible | J11: =IF($U11="","",N(INDEX(NAVES!$N$7:$N$200,$U11))) -> 3200 | K11: =IF($U11="","",N(INDEX(NAVES!$I$7:$I$200,$U11))) -> 49534.887 | L11: =IF($U11="","",N(INDEX(NAVES!$J$7:$J$200,$U11))) -> 89261.008 | M11: =IF($U11="","",IFERROR(F11/SUMIF(NAVES!$A$7:$A$200,$B$4,NAVES!$E$7:$E$200)*$I$4*$E$4,0)) -> 250683.36 | N11: =IF($U11="","",K11+L11+M11) -> 389479.26 | O11: =IF($U11="","",IFERROR(N11/$E$4,"")) -> 430.36382 | P11: =IF($U11="","",IFERROR(J11-O11,"")) -> 2769.6362 | Q11: =IF($U11="","",IFERROR(P11/J11,"")) -> 0.86551131 | R11: =IF($U11="","",IFERROR(J11/F11,"")) -> 800 | S11: =IF($U11="","",IFERROR(O11/F11,"")) -> 107.59096 | U11: =IFERROR(MATCH(2,NAVES!$P$7:$P$200,0),"") -> 77
A12: =IF($U12="","",3) -> 3 | B12: =IF($U12="","",INDEX(NAVES!$B$7:$B$200,$U12)) -> 8428 | C12: =IF($U12="","",IF(INDEX(NAVES!$M$7:$M$200,$U12)="","",INDEX(NAVES!$M$7:$M$200,$U12))) -> 2026-185 | D12: =IF($U12="","",INDEX(NAVES!$C$7:$C$200,$U12)) -> Por confirmar | E12: =IF($U12="","",INDEX(NAVES!$D$7:$D$200,$U12)) -> CAPE BRUNO 1 | F12: =IF($U12="","",INDEX(NAVES!$E$7:$E$200,$U12)) -> 2 | G12: =IF($U12="","",IF(INDEX(NAVES!$F$7:$F$200,$U12)="","",INDEX(NAVES!$F$7:$F$200,$U12))) -> 2 | H12: =IF($U12="","",IF(INDEX(NAVES!$G$7:$G$200,$U12)="","",INDEX(NAVES!$G$7:$G$200,$U12))) -> 4.6 | I12: =IF($U12="","",INDEX(NAVES!$H$7:$H$200,$U12)) -> Disponible | J12: =IF($U12="","",N(INDEX(NAVES!$N$7:$N$200,$U12))) -> 512 | K12: =IF($U12="","",N(INDEX(NAVES!$I$7:$I$200,$U12))) -> 24767.444 | L12: =IF($U12="","",N(INDEX(NAVES!$J$7:$J$200,$U12))) -> 44630.504 | M12: =IF($U12="","",IFERROR(F12/SUMIF(NAVES!$A$7:$A$200,$B$4,NAVES!$E$7:$E$200)*$I$4*$E$4,0)) -> 125341.68 | N12: =IF($U12="","",K12+L12+M12) -> 194739.63 | O12: =IF($U12="","",IFERROR(N12/$E$4,"")) -> 215.18191 | P12: =IF($U12="","",IFERROR(J12-O12,"")) -> 296.81809 | Q12: =IF($U12="","",IFERROR(P12/J12,"")) -> 0.57972283 | R12: =IF($U12="","",IFERROR(J12/F12,"")) -> 256 | S12: =IF($U12="","",IFERROR(O12/F12,"")) -> 107.59096 | U12: =IFERROR(MATCH(3,NAVES!$P$7:$P$200,0),"") -> 78
A13: =IF($U13="","",4) -> 4 | B13: =IF($U13="","",INDEX(NAVES!$B$7:$B$200,$U13)) -> 8429 | C13: =IF($U13="","",IF(INDEX(NAVES!$M$7:$M$200,$U13)="","",INDEX(NAVES!$M$7:$M$200,$U13))) | D13: =IF($U13="","",INDEX(NAVES!$C$7:$C$200,$U13)) -> Por confirmar | E13: =IF($U13="","",INDEX(NAVES!$D$7:$D$200,$U13)) -> LITTLE ATHINA | F13: =IF($U13="","",INDEX(NAVES!$E$7:$E$200,$U13)) -> 1 | G13: =IF($U13="","",IF(INDEX(NAVES!$F$7:$F$200,$U13)="","",INDEX(NAVES!$F$7:$F$200,$U13))) -> 0 | H13: =IF($U13="","",IF(INDEX(NAVES!$G$7:$G$200,$U13)="","",INDEX(NAVES!$G$7:$G$200,$U13))) | I13: =IF($U13="","",INDEX(NAVES!$H$7:$H$200,$U13)) -> Parcial | J13: =IF($U13="","",N(INDEX(NAVES!$N$7:$N$200,$U13))) -> 0 | K13: =IF($U13="","",N(INDEX(NAVES!$I$7:$I$200,$U13))) -> 12383.722 | L13: =IF($U13="","",N(INDEX(NAVES!$J$7:$J$200,$U13))) -> 22315.252 | M13: =IF($U13="","",IFERROR(F13/SUMIF(NAVES!$A$7:$A$200,$B$4,NAVES!$E$7:$E$200)*$I$4*$E$4,0)) -> 62670.841 | N13: =IF($U13="","",K13+L13+M13) -> 97369.815 | O13: =IF($U13="","",IFERROR(N13/$E$4,"")) -> 107.59096 | P13: =IF($U13="","",IFERROR(J13-O13,"")) -> -107.59096 | Q13: =IF($U13="","",IFERROR(P13/J13,"")) | R13: =IF($U13="","",IFERROR(J13/F13,"")) -> 0 | S13: =IF($U13="","",IFERROR(O13/F13,"")) -> 107.59096 | U13: =IFERROR(MATCH(4,NAVES!$P$7:$P$200,0),"") -> 79
A14: =IF($U14="","",5) -> 5 | B14: =IF($U14="","",INDEX(NAVES!$B$7:$B$200,$U14)) -> 8430 | C14: =IF($U14="","",IF(INDEX(NAVES!$M$7:$M$200,$U14)="","",INDEX(NAVES!$M$7:$M$200,$U14))) -> 2026-186 | D14: =IF($U14="","",INDEX(NAVES!$C$7:$C$200,$U14)) -> MAERSK | E14: =IF($U14="","",INDEX(NAVES!$D$7:$D$200,$U14)) -> POLAR CHILE | F14: =IF($U14="","",INDEX(NAVES!$E$7:$E$200,$U14)) -> 268 | G14: =IF($U14="","",IF(INDEX(NAVES!$F$7:$F$200,$U14)="","",INDEX(NAVES!$F$7:$F$200,$U14))) -> 267 | H14: =IF($U14="","",IF(INDEX(NAVES!$G$7:$G$200,$U14)="","",INDEX(NAVES!$G$7:$G$200,$U14))) -> 2.69 | I14: =IF($U14="","",INDEX(NAVES!$H$7:$H$200,$U14)) -> Parcial | J14: =IF($U14="","",N(INDEX(NAVES!$N$7:$N$200,$U14))) -> 145144 | K14: =IF($U14="","",N(INDEX(NAVES!$I$7:$I$200,$U14))) -> 3318837.5 | L14: =IF($U14="","",N(INDEX(NAVES!$J$7:$J$200,$U14))) -> 5980487.5 | M14: =IF($U14="","",IFERROR(F14/SUMIF(NAVES!$A$7:$A$200,$B$4,NAVES!$E$7:$E$200)*$I$4*$E$4,0)) -> 16795785 | N14: =IF($U14="","",K14+L14+M14) -> 26095110 | O14: =IF($U14="","",IFERROR(N14/$E$4,"")) -> 28834.376 | P14: =IF($U14="","",IFERROR(J14-O14,"")) -> 116309.62 | Q14: =IF($U14="","",IFERROR(P14/J14,"")) -> 0.80133952 | R14: =IF($U14="","",IFERROR(J14/F14,"")) -> 541.58209 | S14: =IF($U14="","",IFERROR(O14/F14,"")) -> 107.59096 | U14: =IFERROR(MATCH(5,NAVES!$P$7:$P$200,0),"") -> 80
A15: =IF($U15="","",6) -> 6 | B15: =IF($U15="","",INDEX(NAVES!$B$7:$B$200,$U15)) -> 8431 | C15: =IF($U15="","",IF(INDEX(NAVES!$M$7:$M$200,$U15)="","",INDEX(NAVES!$M$7:$M$200,$U15))) -> 2026-177 | D15: =IF($U15="","",INDEX(NAVES!$C$7:$C$200,$U15)) -> HAPAG LLOYD / ON | E15: =IF($U15="","",INDEX(NAVES!$D$7:$D$200,$U15)) -> HUMBOLDT EXPRESS | F15: =IF($U15="","",INDEX(NAVES!$E$7:$E$200,$U15)) -> 17 | G15: =IF($U15="","",IF(INDEX(NAVES!$F$7:$F$200,$U15)="","",INDEX(NAVES!$F$7:$F$200,$U15))) -> 17 | H15: =IF($U15="","",IF(INDEX(NAVES!$G$7:$G$200,$U15)="","",INDEX(NAVES!$G$7:$G$200,$U15))) -> 8.62 | I15: =IF($U15="","",INDEX(NAVES!$H$7:$H$200,$U15)) -> Disponible | J15: =IF($U15="","",N(INDEX(NAVES!$N$7:$N$200,$U15))) -> 16440 | K15: =IF($U15="","",N(INDEX(NAVES!$I$7:$I$200,$U15))) -> 210523.27 | L15: =IF($U15="","",N(INDEX(NAVES!$J$7:$J$200,$U15))) -> 379359.28 | M15: =IF($U15="","",IFERROR(F15/SUMIF(NAVES!$A$7:$A$200,$B$4,NAVES!$E$7:$E$200)*$I$4*$E$4,0)) -> 1065404.3 | N15: =IF($U15="","",K15+L15+M15) -> 1655286.9 | O15: =IF($U15="","",IFERROR(N15/$E$4,"")) -> 1829.0462 | P15: =IF($U15="","",IFERROR(J15-O15,"")) -> 14610.954 | Q15: =IF($U15="","",IFERROR(P15/J15,"")) -> 0.88874415 | R15: =IF($U15="","",IFERROR(J15/F15,"")) -> 967.05882 | S15: =IF($U15="","",IFERROR(O15/F15,"")) -> 107.59096 | U15: =IFERROR(MATCH(6,NAVES!$P$7:$P$200,0),"") -> 81
A16: =IF($U16="","",7) -> 7 | B16: =IF($U16="","",INDEX(NAVES!$B$7:$B$200,$U16)) -> 8432 | C16: =IF($U16="","",IF(INDEX(NAVES!$M$7:$M$200,$U16)="","",INDEX(NAVES!$M$7:$M$200,$U16))) -> 2026-192 | D16: =IF($U16="","",INDEX(NAVES!$C$7:$C$200,$U16)) -> SEABOARD | E16: =IF($U16="","",INDEX(NAVES!$D$7:$D$200,$U16)) -> MOLLY SCHULTE 1 | F16: =IF($U16="","",INDEX(NAVES!$E$7:$E$200,$U16)) -> 9 | G16: =IF($U16="","",IF(INDEX(NAVES!$F$7:$F$200,$U16)="","",INDEX(NAVES!$F$7:$F$200,$U16))) -> 9 | H16: =IF($U16="","",IF(INDEX(NAVES!$G$7:$G$200,$U16)="","",INDEX(NAVES!$G$7:$G$200,$U16))) -> 9.29 | I16: =IF($U16="","",INDEX(NAVES!$H$7:$H$200,$U16)) -> Disponible | J16: =IF($U16="","",N(INDEX(NAVES!$N$7:$N$200,$U16))) -> 7560 | K16: =IF($U16="","",N(INDEX(NAVES!$I$7:$I$200,$U16))) -> 111453.5 | L16: =IF($U16="","",N(INDEX(NAVES!$J$7:$J$200,$U16))) -> 200837.27 | M16: =IF($U16="","",IFERROR(F16/SUMIF(NAVES!$A$7:$A$200,$B$4,NAVES!$E$7:$E$200)*$I$4*$E$4,0)) -> 564037.57 | N16: =IF($U16="","",K16+L16+M16) -> 876328.33 | O16: =IF($U16="","",IFERROR(N16/$E$4,"")) -> 968.3186 | P16: =IF($U16="","",IFERROR(J16-O16,"")) -> 6591.6814 | Q16: =IF($U16="","",IFERROR(P16/J16,"")) -> 0.87191553 | R16: =IF($U16="","",IFERROR(J16/F16,"")) -> 840 | S16: =IF($U16="","",IFERROR(O16/F16,"")) -> 107.59096 | U16: =IFERROR(MATCH(7,NAVES!$P$7:$P$200,0),"") -> 82
A17: =IF($U17="","",8) -> 8 | B17: =IF($U17="","",INDEX(NAVES!$B$7:$B$200,$U17)) -> 8433 | C17: =IF($U17="","",IF(INDEX(NAVES!$M$7:$M$200,$U17)="","",INDEX(NAVES!$M$7:$M$200,$U17))) -> 2026-188 | D17: =IF($U17="","",INDEX(NAVES!$C$7:$C$200,$U17)) -> MSC | E17: =IF($U17="","",INDEX(NAVES!$D$7:$D$200,$U17)) -> MSC YOKOHAMA | F17: =IF($U17="","",INDEX(NAVES!$E$7:$E$200,$U17)) -> 12 | G17: =IF($U17="","",IF(INDEX(NAVES!$F$7:$F$200,$U17)="","",INDEX(NAVES!$F$7:$F$200,$U17))) -> 12 | H17: =IF($U17="","",IF(INDEX(NAVES!$G$7:$G$200,$U17)="","",INDEX(NAVES!$G$7:$G$200,$U17))) -> 6.06 | I17: =IF($U17="","",INDEX(NAVES!$H$7:$H$200,$U17)) -> Disponible | J17: =IF($U17="","",N(INDEX(NAVES!$N$7:$N$200,$U17))) -> 12000 | K17: =IF($U17="","",N(INDEX(NAVES!$I$7:$I$200,$U17))) -> 148604.66 | L17: =IF($U17="","",N(INDEX(NAVES!$J$7:$J$200,$U17))) -> 267783.02 | M17: =IF($U17="","",IFERROR(F17/SUMIF(NAVES!$A$7:$A$200,$B$4,NAVES!$E$7:$E$200)*$I$4*$E$4,0)) -> 752050.09 | N17: =IF($U17="","",K17+L17+M17) -> 1168437.8 | O17: =IF($U17="","",IFERROR(N17/$E$4,"")) -> 1291.0915 | P17: =IF($U17="","",IFERROR(J17-O17,"")) -> 10708.909 | Q17: =IF($U17="","",IFERROR(P17/J17,"")) -> 0.89240904 | R17: =IF($U17="","",IFERROR(J17/F17,"")) -> 1000 | S17: =IF($U17="","",IFERROR(O17/F17,"")) -> 107.59096 | U17: =IFERROR(MATCH(8,NAVES!$P$7:$P$200,0),"") -> 83
A18: =IF($U18="","",9) -> 9 | B18: =IF($U18="","",INDEX(NAVES!$B$7:$B$200,$U18)) -> 8434 | C18: =IF($U18="","",IF(INDEX(NAVES!$M$7:$M$200,$U18)="","",INDEX(NAVES!$M$7:$M$200,$U18))) -> 2026-187 | D18: =IF($U18="","",INDEX(NAVES!$C$7:$C$200,$U18)) -> MAERSK | E18: =IF($U18="","",INDEX(NAVES!$D$7:$D$200,$U18)) -> POLAR ARGENTINA | F18: =IF($U18="","",INDEX(NAVES!$E$7:$E$200,$U18)) -> 210 | G18: =IF($U18="","",IF(INDEX(NAVES!$F$7:$F$200,$U18)="","",INDEX(NAVES!$F$7:$F$200,$U18))) -> 210 | H18: =IF($U18="","",IF(INDEX(NAVES!$G$7:$G$200,$U18)="","",INDEX(NAVES!$G$7:$G$200,$U18))) -> 2.91 | I18: =IF($U18="","",INDEX(NAVES!$H$7:$H$200,$U18)) -> Disponible | J18: =IF($U18="","",N(INDEX(NAVES!$N$7:$N$200,$U18))) -> 147896 | K18: =IF($U18="","",N(INDEX(NAVES!$I$7:$I$200,$U18))) -> 2600581.6 | L18: =IF($U18="","",N(INDEX(NAVES!$J$7:$J$200,$U18))) -> 4686202.9 | M18: =IF($U18="","",IFERROR(F18/SUMIF(NAVES!$A$7:$A$200,$B$4,NAVES!$E$7:$E$200)*$I$4*$E$4,0)) -> 13160877 | N18: =IF($U18="","",K18+L18+M18) -> 20447661 | O18: =IF($U18="","",IFERROR(N18/$E$4,"")) -> 22594.101 | P18: =IF($U18="","",IFERROR(J18-O18,"")) -> 125301.9 | Q18: =IF($U18="","",IFERROR(P18/J18,"")) -> 0.84722981 | R18: =IF($U18="","",IFERROR(J18/F18,"")) -> 704.26667 | S18: =IF($U18="","",IFERROR(O18/F18,"")) -> 107.59096 | U18: =IFERROR(MATCH(9,NAVES!$P$7:$P$200,0),"") -> 84
A19: =IF($U19="","",10) -> 10 | B19: =IF($U19="","",INDEX(NAVES!$B$7:$B$200,$U19)) -> 8436 | C19: =IF($U19="","",IF(INDEX(NAVES!$M$7:$M$200,$U19)="","",INDEX(NAVES!$M$7:$M$200,$U19))) -> 2026-196 | D19: =IF($U19="","",INDEX(NAVES!$C$7:$C$200,$U19)) -> Por confirmar | E19: =IF($U19="","",INDEX(NAVES!$D$7:$D$200,$U19)) -> ALIOTH 2 | F19: =IF($U19="","",INDEX(NAVES!$E$7:$E$200,$U19)) -> 1 | G19: =IF($U19="","",IF(INDEX(NAVES!$F$7:$F$200,$U19)="","",INDEX(NAVES!$F$7:$F$200,$U19))) -> 1 | H19: =IF($U19="","",IF(INDEX(NAVES!$G$7:$G$200,$U19)="","",INDEX(NAVES!$G$7:$G$200,$U19))) -> 6.52 | I19: =IF($U19="","",INDEX(NAVES!$H$7:$H$200,$U19)) -> Disponible | J19: =IF($U19="","",N(INDEX(NAVES!$N$7:$N$200,$U19))) -> 616 | K19: =IF($U19="","",N(INDEX(NAVES!$I$7:$I$200,$U19))) -> 12383.722 | L19: =IF($U19="","",N(INDEX(NAVES!$J$7:$J$200,$U19))) -> 22315.252 | M19: =IF($U19="","",IFERROR(F19/SUMIF(NAVES!$A$7:$A$200,$B$4,NAVES!$E$7:$E$200)*$I$4*$E$4,0)) -> 62670.841 | N19: =IF($U19="","",K19+L19+M19) -> 97369.815 | O19: =IF($U19="","",IFERROR(N19/$E$4,"")) -> 107.59096 | P19: =IF($U19="","",IFERROR(J19-O19,"")) -> 508.40904 | Q19: =IF($U19="","",IFERROR(P19/J19,"")) -> 0.82533936 | R19: =IF($U19="","",IFERROR(J19/F19,"")) -> 616 | S19: =IF($U19="","",IFERROR(O19/F19,"")) -> 107.59096 | U19: =IFERROR(MATCH(10,NAVES!$P$7:$P$200,0),"") -> 85
A20: =IF($U20="","",11) -> 11 | B20: =IF($U20="","",INDEX(NAVES!$B$7:$B$200,$U20)) -> 8437 | C20: =IF($U20="","",IF(INDEX(NAVES!$M$7:$M$200,$U20)="","",INDEX(NAVES!$M$7:$M$200,$U20))) | D20: =IF($U20="","",INDEX(NAVES!$C$7:$C$200,$U20)) -> Por confirmar | E20: =IF($U20="","",INDEX(NAVES!$D$7:$D$200,$U20)) -> CAPE BRUNO 2 | F20: =IF($U20="","",INDEX(NAVES!$E$7:$E$200,$U20)) -> 1 | G20: =IF($U20="","",IF(INDEX(NAVES!$F$7:$F$200,$U20)="","",INDEX(NAVES!$F$7:$F$200,$U20))) -> 1 | H20: =IF($U20="","",IF(INDEX(NAVES!$G$7:$G$200,$U20)="","",INDEX(NAVES!$G$7:$G$200,$U20))) -> 2.34 | I20: =IF($U20="","",INDEX(NAVES!$H$7:$H$200,$U20)) -> Disponible | J20: =IF($U20="","",N(INDEX(NAVES!$N$7:$N$200,$U20))) -> 0 | K20: =IF($U20="","",N(INDEX(NAVES!$I$7:$I$200,$U20))) -> 12383.722 | L20: =IF($U20="","",N(INDEX(NAVES!$J$7:$J$200,$U20))) -> 22315.252 | M20: =IF($U20="","",IFERROR(F20/SUMIF(NAVES!$A$7:$A$200,$B$4,NAVES!$E$7:$E$200)*$I$4*$E$4,0)) -> 62670.841 | N20: =IF($U20="","",K20+L20+M20) -> 97369.815 | O20: =IF($U20="","",IFERROR(N20/$E$4,"")) -> 107.59096 | P20: =IF($U20="","",IFERROR(J20-O20,"")) -> -107.59096 | Q20: =IF($U20="","",IFERROR(P20/J20,"")) | R20: =IF($U20="","",IFERROR(J20/F20,"")) -> 0 | S20: =IF($U20="","",IFERROR(O20/F20,"")) -> 107.59096 | U20: =IFERROR(MATCH(11,NAVES!$P$7:$P$200,0),"") -> 86
A21: =IF($U21="","",12) -> 12 | B21: =IF($U21="","",INDEX(NAVES!$B$7:$B$200,$U21)) -> 8438 | C21: =IF($U21="","",IF(INDEX(NAVES!$M$7:$M$200,$U21)="","",INDEX(NAVES!$M$7:$M$200,$U21))) -> 2026-190 | D21: =IF($U21="","",INDEX(NAVES!$C$7:$C$200,$U21)) -> HAPAG LLOYD / ON | E21: =IF($U21="","",INDEX(NAVES!$D$7:$D$200,$U21)) -> ONE SINCERITY | F21: =IF($U21="","",INDEX(NAVES!$E$7:$E$200,$U21)) -> 37 | G21: =IF($U21="","",IF(INDEX(NAVES!$F$7:$F$200,$U21)="","",INDEX(NAVES!$F$7:$F$200,$U21))) -> 37 | H21: =IF($U21="","",IF(INDEX(NAVES!$G$7:$G$200,$U21)="","",INDEX(NAVES!$G$7:$G$200,$U21))) -> 7.17 | I21: =IF($U21="","",INDEX(NAVES!$H$7:$H$200,$U21)) -> Disponible | J21: =IF($U21="","",N(INDEX(NAVES!$N$7:$N$200,$U21))) -> 27608 | K21: =IF($U21="","",N(INDEX(NAVES!$I$7:$I$200,$U21))) -> 458197.71 | L21: =IF($U21="","",N(INDEX(NAVES!$J$7:$J$200,$U21))) -> 825664.32 | M21: =IF($U21="","",IFERROR(F21/SUMIF(NAVES!$A$7:$A$200,$B$4,NAVES!$E$7:$E$200)*$I$4*$E$4,0)) -> 2318821.1 | N21: =IF($U21="","",K21+L21+M21) -> 3602683.2 | O21: =IF($U21="","",IFERROR(N21/$E$4,"")) -> 3980.8654 | P21: =IF($U21="","",IFERROR(J21-O21,"")) -> 23627.135 | Q21: =IF($U21="","",IFERROR(P21/J21,"")) -> 0.85580754 | R21: =IF($U21="","",IFERROR(J21/F21,"")) -> 746.16216 | S21: =IF($U21="","",IFERROR(O21/F21,"")) -> 107.59096 | U21: =IFERROR(MATCH(12,NAVES!$P$7:$P$200,0),"") -> 87
A22: =IF($U22="","",13) -> 13 | B22: =IF($U22="","",INDEX(NAVES!$B$7:$B$200,$U22)) -> 8439 | C22: =IF($U22="","",IF(INDEX(NAVES!$M$7:$M$200,$U22)="","",INDEX(NAVES!$M$7:$M$200,$U22))) -> 2026-200 | D22: =IF($U22="","",INDEX(NAVES!$C$7:$C$200,$U22)) -> MAERSK | E22: =IF($U22="","",INDEX(NAVES!$D$7:$D$200,$U22)) -> POLAR PERU | F22: =IF($U22="","",INDEX(NAVES!$E$7:$E$200,$U22)) -> 166 | G22: =IF($U22="","",IF(INDEX(NAVES!$F$7:$F$200,$U22)="","",INDEX(NAVES!$F$7:$F$200,$U22))) -> 166 | H22: =IF($U22="","",IF(INDEX(NAVES!$G$7:$G$200,$U22)="","",INDEX(NAVES!$G$7:$G$200,$U22))) -> 2 | I22: =IF($U22="","",INDEX(NAVES!$H$7:$H$200,$U22)) -> Disponible | J22: =IF($U22="","",N(INDEX(NAVES!$N$7:$N$200,$U22))) -> 69784 | K22: =IF($U22="","",N(INDEX(NAVES!$I$7:$I$200,$U22))) -> 2055697.8 | L22: =IF($U22="","",N(INDEX(NAVES!$J$7:$J$200,$U22))) -> 3704331.8 | M22: =IF($U22="","",IFERROR(F22/SUMIF(NAVES!$A$7:$A$200,$B$4,NAVES!$E$7:$E$200)*$I$4*$E$4,0)) -> 10403360 | N22: =IF($U22="","",K22+L22+M22) -> 16163389 | O22: =IF($U22="","",IFERROR(N22/$E$4,"")) -> 17860.099 | P22: =IF($U22="","",IFERROR(J22-O22,"")) -> 51923.901 | Q22: =IF($U22="","",IFERROR(P22/J22,"")) -> 0.74406599 | R22: =IF($U22="","",IFERROR(J22/F22,"")) -> 420.38554 | S22: =IF($U22="","",IFERROR(O22/F22,"")) -> 107.59096 | U22: =IFERROR(MATCH(13,NAVES!$P$7:$P$200,0),"") -> 88
A23: =IF($U23="","",14) -> 14 | B23: =IF($U23="","",INDEX(NAVES!$B$7:$B$200,$U23)) -> 8440 | C23: =IF($U23="","",IF(INDEX(NAVES!$M$7:$M$200,$U23)="","",INDEX(NAVES!$M$7:$M$200,$U23))) -> 2026-199 | D23: =IF($U23="","",INDEX(NAVES!$C$7:$C$200,$U23)) -> MSC | E23: =IF($U23="","",INDEX(NAVES!$D$7:$D$200,$U23)) -> MSC FLORIANA VI | F23: =IF($U23="","",INDEX(NAVES!$E$7:$E$200,$U23)) -> 2 | G23: =IF($U23="","",IF(INDEX(NAVES!$F$7:$F$200,$U23)="","",INDEX(NAVES!$F$7:$F$200,$U23))) -> 2 | H23: =IF($U23="","",IF(INDEX(NAVES!$G$7:$G$200,$U23)="","",INDEX(NAVES!$G$7:$G$200,$U23))) -> 12.09 | I23: =IF($U23="","",INDEX(NAVES!$H$7:$H$200,$U23)) -> Disponible | J23: =IF($U23="","",N(INDEX(NAVES!$N$7:$N$200,$U23))) -> 4704 | K23: =IF($U23="","",N(INDEX(NAVES!$I$7:$I$200,$U23))) -> 24767.444 | L23: =IF($U23="","",N(INDEX(NAVES!$J$7:$J$200,$U23))) -> 44630.504 | M23: =IF($U23="","",IFERROR(F23/SUMIF(NAVES!$A$7:$A$200,$B$4,NAVES!$E$7:$E$200)*$I$4*$E$4,0)) -> 125341.68 | N23: =IF($U23="","",K23+L23+M23) -> 194739.63 | O23: =IF($U23="","",IFERROR(N23/$E$4,"")) -> 215.18191 | P23: =IF($U23="","",IFERROR(J23-O23,"")) -> 4488.8181 | Q23: =IF($U23="","",IFERROR(P23/J23,"")) -> 0.95425555 | R23: =IF($U23="","",IFERROR(J23/F23,"")) -> 2352 | S23: =IF($U23="","",IFERROR(O23/F23,"")) -> 107.59096 | U23: =IFERROR(MATCH(14,NAVES!$P$7:$P$200,0),"") -> 89
A24: =IF($U24="","",15) -> 15 | B24: =IF($U24="","",INDEX(NAVES!$B$7:$B$200,$U24)) -> 8442 | C24: =IF($U24="","",IF(INDEX(NAVES!$M$7:$M$200,$U24)="","",INDEX(NAVES!$M$7:$M$200,$U24))) -> 2026-191 | D24: =IF($U24="","",INDEX(NAVES!$C$7:$C$200,$U24)) -> HAPAG LLOYD / ON | E24: =IF($U24="","",INDEX(NAVES!$D$7:$D$200,$U24)) -> ONE SAPHIRE | F24: =IF($U24="","",INDEX(NAVES!$E$7:$E$200,$U24)) -> 29 | G24: =IF($U24="","",IF(INDEX(NAVES!$F$7:$F$200,$U24)="","",INDEX(NAVES!$F$7:$F$200,$U24))) -> 29 | H24: =IF($U24="","",IF(INDEX(NAVES!$G$7:$G$200,$U24)="","",INDEX(NAVES!$G$7:$G$200,$U24))) -> 5.51 | I24: =IF($U24="","",INDEX(NAVES!$H$7:$H$200,$U24)) -> Disponible | J24: =IF($U24="","",N(INDEX(NAVES!$N$7:$N$200,$U24))) -> 26856 | K24: =IF($U24="","",N(INDEX(NAVES!$I$7:$I$200,$U24))) -> 359127.93 | L24: =IF($U24="","",N(INDEX(NAVES!$J$7:$J$200,$U24))) -> 647142.31 | M24: =IF($U24="","",IFERROR(F24/SUMIF(NAVES!$A$7:$A$200,$B$4,NAVES!$E$7:$E$200)*$I$4*$E$4,0)) -> 1817454.4 | N24: =IF($U24="","",K24+L24+M24) -> 2823724.6 | O24: =IF($U24="","",IFERROR(N24/$E$4,"")) -> 3120.1377 | P24: =IF($U24="","",IFERROR(J24-O24,"")) -> 23735.862 | Q24: =IF($U24="","",IFERROR(P24/J24,"")) -> 0.88381972 | R24: =IF($U24="","",IFERROR(J24/F24,"")) -> 926.06897 | S24: =IF($U24="","",IFERROR(O24/F24,"")) -> 107.59096 | U24: =IFERROR(MATCH(15,NAVES!$P$7:$P$200,0),"") -> 90
A25: =IF($U25="","",16) -> 16 | B25: =IF($U25="","",INDEX(NAVES!$B$7:$B$200,$U25)) -> 8443 | C25: =IF($U25="","",IF(INDEX(NAVES!$M$7:$M$200,$U25)="","",INDEX(NAVES!$M$7:$M$200,$U25))) -> 2026-204 | D25: =IF($U25="","",INDEX(NAVES!$C$7:$C$200,$U25)) -> MAERSK | E25: =IF($U25="","",INDEX(NAVES!$D$7:$D$200,$U25)) -> POLAR COLOMBIA | F25: =IF($U25="","",INDEX(NAVES!$E$7:$E$200,$U25)) -> 387 | G25: =IF($U25="","",IF(INDEX(NAVES!$F$7:$F$200,$U25)="","",INDEX(NAVES!$F$7:$F$200,$U25))) -> 385 | H25: =IF($U25="","",IF(INDEX(NAVES!$G$7:$G$200,$U25)="","",INDEX(NAVES!$G$7:$G$200,$U25))) -> 2.02 | I25: =IF($U25="","",INDEX(NAVES!$H$7:$H$200,$U25)) -> Parcial | J25: =IF($U25="","",N(INDEX(NAVES!$N$7:$N$200,$U25))) -> 166640 | K25: =IF($U25="","",N(INDEX(NAVES!$I$7:$I$200,$U25))) -> 4792500.4 | L25: =IF($U25="","",N(INDEX(NAVES!$J$7:$J$200,$U25))) -> 8636002.5 | M25: =IF($U25="","",IFERROR(F25/SUMIF(NAVES!$A$7:$A$200,$B$4,NAVES!$E$7:$E$200)*$I$4*$E$4,0)) -> 24253616 | N25: =IF($U25="","",K25+L25+M25) -> 37682118 | O25: =IF($U25="","",IFERROR(N25/$E$4,"")) -> 41637.7 | P25: =IF($U25="","",IFERROR(J25-O25,"")) -> 125002.3 | Q25: =IF($U25="","",IFERROR(P25/J25,"")) -> 0.75013382 | R25: =IF($U25="","",IFERROR(J25/F25,"")) -> 430.59432 | S25: =IF($U25="","",IFERROR(O25/F25,"")) -> 107.59096 | U25: =IFERROR(MATCH(16,NAVES!$P$7:$P$200,0),"") -> 91
A26: =IF($U26="","",17) -> 17 | B26: =IF($U26="","",INDEX(NAVES!$B$7:$B$200,$U26)) -> 8444 | C26: =IF($U26="","",IF(INDEX(NAVES!$M$7:$M$200,$U26)="","",INDEX(NAVES!$M$7:$M$200,$U26))) -> 2026-198 | D26: =IF($U26="","",INDEX(NAVES!$C$7:$C$200,$U26)) -> Por confirmar | E26: =IF($U26="","",INDEX(NAVES!$D$7:$D$200,$U26)) -> ALIOTH 3 | F26: =IF($U26="","",INDEX(NAVES!$E$7:$E$200,$U26)) -> 1 | G26: =IF($U26="","",IF(INDEX(NAVES!$F$7:$F$200,$U26)="","",INDEX(NAVES!$F$7:$F$200,$U26))) -> 1 | H26: =IF($U26="","",IF(INDEX(NAVES!$G$7:$G$200,$U26)="","",INDEX(NAVES!$G$7:$G$200,$U26))) -> 4.01 | I26: =IF($U26="","",INDEX(NAVES!$H$7:$H$200,$U26)) -> Disponible | J26: =IF($U26="","",N(INDEX(NAVES!$N$7:$N$200,$U26))) -> 656 | K26: =IF($U26="","",N(INDEX(NAVES!$I$7:$I$200,$U26))) -> 12383.722 | L26: =IF($U26="","",N(INDEX(NAVES!$J$7:$J$200,$U26))) -> 22315.252 | M26: =IF($U26="","",IFERROR(F26/SUMIF(NAVES!$A$7:$A$200,$B$4,NAVES!$E$7:$E$200)*$I$4*$E$4,0)) -> 62670.841 | N26: =IF($U26="","",K26+L26+M26) -> 97369.815 | O26: =IF($U26="","",IFERROR(N26/$E$4,"")) -> 107.59096 | P26: =IF($U26="","",IFERROR(J26-O26,"")) -> 548.40904 | Q26: =IF($U26="","",IFERROR(P26/J26,"")) -> 0.8359894 | R26: =IF($U26="","",IFERROR(J26/F26,"")) -> 656 | S26: =IF($U26="","",IFERROR(O26/F26,"")) -> 107.59096 | U26: =IFERROR(MATCH(17,NAVES!$P$7:$P$200,0),"") -> 92
A27: =IF($U27="","",18) -> 18 | B27: =IF($U27="","",INDEX(NAVES!$B$7:$B$200,$U27)) -> 8445 | C27: =IF($U27="","",IF(INDEX(NAVES!$M$7:$M$200,$U27)="","",INDEX(NAVES!$M$7:$M$200,$U27))) -> 2026-202 | D27: =IF($U27="","",INDEX(NAVES!$C$7:$C$200,$U27)) -> Por confirmar | E27: =IF($U27="","",INDEX(NAVES!$D$7:$D$200,$U27)) -> CAPE BRUNO 3 | F27: =IF($U27="","",INDEX(NAVES!$E$7:$E$200,$U27)) -> 3 | G27: =IF($U27="","",IF(INDEX(NAVES!$F$7:$F$200,$U27)="","",INDEX(NAVES!$F$7:$F$200,$U27))) -> 1 | H27: =IF($U27="","",IF(INDEX(NAVES!$G$7:$G$200,$U27)="","",INDEX(NAVES!$G$7:$G$200,$U27))) -> 2.42 | I27: =IF($U27="","",INDEX(NAVES!$H$7:$H$200,$U27)) -> Parcial | J27: =IF($U27="","",N(INDEX(NAVES!$N$7:$N$200,$U27))) -> 552 | K27: =IF($U27="","",N(INDEX(NAVES!$I$7:$I$200,$U27))) -> 37151.166 | L27: =IF($U27="","",N(INDEX(NAVES!$J$7:$J$200,$U27))) -> 66945.756 | M27: =IF($U27="","",IFERROR(F27/SUMIF(NAVES!$A$7:$A$200,$B$4,NAVES!$E$7:$E$200)*$I$4*$E$4,0)) -> 188012.52 | N27: =IF($U27="","",K27+L27+M27) -> 292109.44 | O27: =IF($U27="","",IFERROR(N27/$E$4,"")) -> 322.77287 | P27: =IF($U27="","",IFERROR(J27-O27,"")) -> 229.22713 | Q27: =IF($U27="","",IFERROR(P27/J27,"")) -> 0.41526654 | R27: =IF($U27="","",IFERROR(J27/F27,"")) -> 184 | S27: =IF($U27="","",IFERROR(O27/F27,"")) -> 107.59096 | U27: =IFERROR(MATCH(18,NAVES!$P$7:$P$200,0),"") -> 93
A28: =IF($U28="","",19) | B28: =IF($U28="","",INDEX(NAVES!$B$7:$B$200,$U28)) | C28: =IF($U28="","",IF(INDEX(NAVES!$M$7:$M$200,$U28)="","",INDEX(NAVES!$M$7:$M$200,$U28))) | D28: =IF($U28="","",INDEX(NAVES!$C$7:$C$200,$U28)) | E28: =IF($U28="","",INDEX(NAVES!$D$7:$D$200,$U28)) | F28: =IF($U28="","",INDEX(NAVES!$E$7:$E$200,$U28)) | G28: =IF($U28="","",IF(INDEX(NAVES!$F$7:$F$200,$U28)="","",INDEX(NAVES!$F$7:$F$200,$U28))) | H28: =IF($U28="","",IF(INDEX(NAVES!$G$7:$G$200,$U28)="","",INDEX(NAVES!$G$7:$G$200,$U28))) | I28: =IF($U28="","",INDEX(NAVES!$H$7:$H$200,$U28)) | J28: =IF($U28="","",N(INDEX(NAVES!$N$7:$N$200,$U28))) | K28: =IF($U28="","",N(INDEX(NAVES!$I$7:$I$200,$U28))) | L28: =IF($U28="","",N(INDEX(NAVES!$J$7:$J$200,$U28))) | M28: =IF($U28="","",IFERROR(F28/SUMIF(NAVES!$A$7:$A$200,$B$4,NAVES!$E$7:$E$200)*$I$4*$E$4,0)) | N28: =IF($U28="","",K28+L28+M28) | O28: =IF($U28="","",IFERROR(N28/$E$4,"")) | P28: =IF($U28="","",IFERROR(J28-O28,"")) | Q28: =IF($U28="","",IFERROR(P28/J28,"")) | R28: =IF($U28="","",IFERROR(J28/F28,"")) | S28: =IF($U28="","",IFERROR(O28/F28,"")) | U28: =IFERROR(MATCH(19,NAVES!$P$7:$P$200,0),"")
A29: =IF($U29="","",20) | B29: =IF($U29="","",INDEX(NAVES!$B$7:$B$200,$U29)) | C29: =IF($U29="","",IF(INDEX(NAVES!$M$7:$M$200,$U29)="","",INDEX(NAVES!$M$7:$M$200,$U29))) | D29: =IF($U29="","",INDEX(NAVES!$C$7:$C$200,$U29)) | E29: =IF($U29="","",INDEX(NAVES!$D$7:$D$200,$U29)) | F29: =IF($U29="","",INDEX(NAVES!$E$7:$E$200,$U29)) | G29: =IF($U29="","",IF(INDEX(NAVES!$F$7:$F$200,$U29)="","",INDEX(NAVES!$F$7:$F$200,$U29))) | H29: =IF($U29="","",IF(INDEX(NAVES!$G$7:$G$200,$U29)="","",INDEX(NAVES!$G$7:$G$200,$U29))) | I29: =IF($U29="","",INDEX(NAVES!$H$7:$H$200,$U29)) | J29: =IF($U29="","",N(INDEX(NAVES!$N$7:$N$200,$U29))) | K29: =IF($U29="","",N(INDEX(NAVES!$I$7:$I$200,$U29))) | L29: =IF($U29="","",N(INDEX(NAVES!$J$7:$J$200,$U29))) | M29: =IF($U29="","",IFERROR(F29/SUMIF(NAVES!$A$7:$A$200,$B$4,NAVES!$E$7:$E$200)*$I$4*$E$4,0)) | N29: =IF($U29="","",K29+L29+M29) | O29: =IF($U29="","",IFERROR(N29/$E$4,"")) | P29: =IF($U29="","",IFERROR(J29-O29,"")) | Q29: =IF($U29="","",IFERROR(P29/J29,"")) | R29: =IF($U29="","",IFERROR(J29/F29,"")) | S29: =IF($U29="","",IFERROR(O29/F29,"")) | U29: =IFERROR(MATCH(20,NAVES!$P$7:$P$200,0),"")
A30: =IF($U30="","",21) | B30: =IF($U30="","",INDEX(NAVES!$B$7:$B$200,$U30)) | C30: =IF($U30="","",IF(INDEX(NAVES!$M$7:$M$200,$U30)="","",INDEX(NAVES!$M$7:$M$200,$U30))) | D30: =IF($U30="","",INDEX(NAVES!$C$7:$C$200,$U30)) | E30: =IF($U30="","",INDEX(NAVES!$D$7:$D$200,$U30)) | F30: =IF($U30="","",INDEX(NAVES!$E$7:$E$200,$U30)) | G30: =IF($U30="","",IF(INDEX(NAVES!$F$7:$F$200,$U30)="","",INDEX(NAVES!$F$7:$F$200,$U30))) | H30: =IF($U30="","",IF(INDEX(NAVES!$G$7:$G$200,$U30)="","",INDEX(NAVES!$G$7:$G$200,$U30))) | I30: =IF($U30="","",INDEX(NAVES!$H$7:$H$200,$U30)) | J30: =IF($U30="","",N(INDEX(NAVES!$N$7:$N$200,$U30))) | K30: =IF($U30="","",N(INDEX(NAVES!$I$7:$I$200,$U30))) | L30: =IF($U30="","",N(INDEX(NAVES!$J$7:$J$200,$U30))) | M30: =IF($U30="","",IFERROR(F30/SUMIF(NAVES!$A$7:$A$200,$B$4,NAVES!$E$7:$E$200)*$I$4*$E$4,0)) | N30: =IF($U30="","",K30+L30+M30) | O30: =IF($U30="","",IFERROR(N30/$E$4,"")) | P30: =IF($U30="","",IFERROR(J30-O30,"")) | Q30: =IF($U30="","",IFERROR(P30/J30,"")) | R30: =IF($U30="","",IFERROR(J30/F30,"")) | S30: =IF($U30="","",IFERROR(O30/F30,"")) | U30: =IFERROR(MATCH(21,NAVES!$P$7:$P$200,0),"")
A31: =IF($U31="","",22) | B31: =IF($U31="","",INDEX(NAVES!$B$7:$B$200,$U31)) | C31: =IF($U31="","",IF(INDEX(NAVES!$M$7:$M$200,$U31)="","",INDEX(NAVES!$M$7:$M$200,$U31))) | D31: =IF($U31="","",INDEX(NAVES!$C$7:$C$200,$U31)) | E31: =IF($U31="","",INDEX(NAVES!$D$7:$D$200,$U31)) | F31: =IF($U31="","",INDEX(NAVES!$E$7:$E$200,$U31)) | G31: =IF($U31="","",IF(INDEX(NAVES!$F$7:$F$200,$U31)="","",INDEX(NAVES!$F$7:$F$200,$U31))) | H31: =IF($U31="","",IF(INDEX(NAVES!$G$7:$G$200,$U31)="","",INDEX(NAVES!$G$7:$G$200,$U31))) | I31: =IF($U31="","",INDEX(NAVES!$H$7:$H$200,$U31)) | J31: =IF($U31="","",N(INDEX(NAVES!$N$7:$N$200,$U31))) | K31: =IF($U31="","",N(INDEX(NAVES!$I$7:$I$200,$U31))) | L31: =IF($U31="","",N(INDEX(NAVES!$J$7:$J$200,$U31))) | M31: =IF($U31="","",IFERROR(F31/SUMIF(NAVES!$A$7:$A$200,$B$4,NAVES!$E$7:$E$200)*$I$4*$E$4,0)) | N31: =IF($U31="","",K31+L31+M31) | O31: =IF($U31="","",IFERROR(N31/$E$4,"")) | P31: =IF($U31="","",IFERROR(J31-O31,"")) | Q31: =IF($U31="","",IFERROR(P31/J31,"")) | R31: =IF($U31="","",IFERROR(J31/F31,"")) | S31: =IF($U31="","",IFERROR(O31/F31,"")) | U31: =IFERROR(MATCH(22,NAVES!$P$7:$P$200,0),"")
A32: =IF($U32="","",23) | B32: =IF($U32="","",INDEX(NAVES!$B$7:$B$200,$U32)) | C32: =IF($U32="","",IF(INDEX(NAVES!$M$7:$M$200,$U32)="","",INDEX(NAVES!$M$7:$M$200,$U32))) | D32: =IF($U32="","",INDEX(NAVES!$C$7:$C$200,$U32)) | E32: =IF($U32="","",INDEX(NAVES!$D$7:$D$200,$U32)) | F32: =IF($U32="","",INDEX(NAVES!$E$7:$E$200,$U32)) | G32: =IF($U32="","",IF(INDEX(NAVES!$F$7:$F$200,$U32)="","",INDEX(NAVES!$F$7:$F$200,$U32))) | H32: =IF($U32="","",IF(INDEX(NAVES!$G$7:$G$200,$U32)="","",INDEX(NAVES!$G$7:$G$200,$U32))) | I32: =IF($U32="","",INDEX(NAVES!$H$7:$H$200,$U32)) | J32: =IF($U32="","",N(INDEX(NAVES!$N$7:$N$200,$U32))) | K32: =IF($U32="","",N(INDEX(NAVES!$I$7:$I$200,$U32))) | L32: =IF($U32="","",N(INDEX(NAVES!$J$7:$J$200,$U32))) | M32: =IF($U32="","",IFERROR(F32/SUMIF(NAVES!$A$7:$A$200,$B$4,NAVES!$E$7:$E$200)*$I$4*$E$4,0)) | N32: =IF($U32="","",K32+L32+M32) | O32: =IF($U32="","",IFERROR(N32/$E$4,"")) | P32: =IF($U32="","",IFERROR(J32-O32,"")) | Q32: =IF($U32="","",IFERROR(P32/J32,"")) | R32: =IF($U32="","",IFERROR(J32/F32,"")) | S32: =IF($U32="","",IFERROR(O32/F32,"")) | U32: =IFERROR(MATCH(23,NAVES!$P$7:$P$200,0),"")
A33: =IF($U33="","",24) | B33: =IF($U33="","",INDEX(NAVES!$B$7:$B$200,$U33)) | C33: =IF($U33="","",IF(INDEX(NAVES!$M$7:$M$200,$U33)="","",INDEX(NAVES!$M$7:$M$200,$U33))) | D33: =IF($U33="","",INDEX(NAVES!$C$7:$C$200,$U33)) | E33: =IF($U33="","",INDEX(NAVES!$D$7:$D$200,$U33)) | F33: =IF($U33="","",INDEX(NAVES!$E$7:$E$200,$U33)) | G33: =IF($U33="","",IF(INDEX(NAVES!$F$7:$F$200,$U33)="","",INDEX(NAVES!$F$7:$F$200,$U33))) | H33: =IF($U33="","",IF(INDEX(NAVES!$G$7:$G$200,$U33)="","",INDEX(NAVES!$G$7:$G$200,$U33))) | I33: =IF($U33="","",INDEX(NAVES!$H$7:$H$200,$U33)) | J33: =IF($U33="","",N(INDEX(NAVES!$N$7:$N$200,$U33))) | K33: =IF($U33="","",N(INDEX(NAVES!$I$7:$I$200,$U33))) | L33: =IF($U33="","",N(INDEX(NAVES!$J$7:$J$200,$U33))) | M33: =IF($U33="","",IFERROR(F33/SUMIF(NAVES!$A$7:$A$200,$B$4,NAVES!$E$7:$E$200)*$I$4*$E$4,0)) | N33: =IF($U33="","",K33+L33+M33) | O33: =IF($U33="","",IFERROR(N33/$E$4,"")) | P33: =IF($U33="","",IFERROR(J33-O33,"")) | Q33: =IF($U33="","",IFERROR(P33/J33,"")) | R33: =IF($U33="","",IFERROR(J33/F33,"")) | S33: =IF($U33="","",IFERROR(O33/F33,"")) | U33: =IFERROR(MATCH(24,NAVES!$P$7:$P$200,0),"")
A34: =IF($U34="","",25) | B34: =IF($U34="","",INDEX(NAVES!$B$7:$B$200,$U34)) | C34: =IF($U34="","",IF(INDEX(NAVES!$M$7:$M$200,$U34)="","",INDEX(NAVES!$M$7:$M$200,$U34))) | D34: =IF($U34="","",INDEX(NAVES!$C$7:$C$200,$U34)) | E34: =IF($U34="","",INDEX(NAVES!$D$7:$D$200,$U34)) | F34: =IF($U34="","",INDEX(NAVES!$E$7:$E$200,$U34)) | G34: =IF($U34="","",IF(INDEX(NAVES!$F$7:$F$200,$U34)="","",INDEX(NAVES!$F$7:$F$200,$U34))) | H34: =IF($U34="","",IF(INDEX(NAVES!$G$7:$G$200,$U34)="","",INDEX(NAVES!$G$7:$G$200,$U34))) | I34: =IF($U34="","",INDEX(NAVES!$H$7:$H$200,$U34)) | J34: =IF($U34="","",N(INDEX(NAVES!$N$7:$N$200,$U34))) | K34: =IF($U34="","",N(INDEX(NAVES!$I$7:$I$200,$U34))) | L34: =IF($U34="","",N(INDEX(NAVES!$J$7:$J$200,$U34))) | M34: =IF($U34="","",IFERROR(F34/SUMIF(NAVES!$A$7:$A$200,$B$4,NAVES!$E$7:$E$200)*$I$4*$E$4,0)) | N34: =IF($U34="","",K34+L34+M34) | O34: =IF($U34="","",IFERROR(N34/$E$4,"")) | P34: =IF($U34="","",IFERROR(J34-O34,"")) | Q34: =IF($U34="","",IFERROR(P34/J34,"")) | R34: =IF($U34="","",IFERROR(J34/F34,"")) | S34: =IF($U34="","",IFERROR(O34/F34,"")) | U34: =IFERROR(MATCH(25,NAVES!$P$7:$P$200,0),"")
A35: =IF($U35="","",26) | B35: =IF($U35="","",INDEX(NAVES!$B$7:$B$200,$U35)) | C35: =IF($U35="","",IF(INDEX(NAVES!$M$7:$M$200,$U35)="","",INDEX(NAVES!$M$7:$M$200,$U35))) | D35: =IF($U35="","",INDEX(NAVES!$C$7:$C$200,$U35)) | E35: =IF($U35="","",INDEX(NAVES!$D$7:$D$200,$U35)) | F35: =IF($U35="","",INDEX(NAVES!$E$7:$E$200,$U35)) | G35: =IF($U35="","",IF(INDEX(NAVES!$F$7:$F$200,$U35)="","",INDEX(NAVES!$F$7:$F$200,$U35))) | H35: =IF($U35="","",IF(INDEX(NAVES!$G$7:$G$200,$U35)="","",INDEX(NAVES!$G$7:$G$200,$U35))) | I35: =IF($U35="","",INDEX(NAVES!$H$7:$H$200,$U35)) | J35: =IF($U35="","",N(INDEX(NAVES!$N$7:$N$200,$U35))) | K35: =IF($U35="","",N(INDEX(NAVES!$I$7:$I$200,$U35))) | L35: =IF($U35="","",N(INDEX(NAVES!$J$7:$J$200,$U35))) | M35: =IF($U35="","",IFERROR(F35/SUMIF(NAVES!$A$7:$A$200,$B$4,NAVES!$E$7:$E$200)*$I$4*$E$4,0)) | N35: =IF($U35="","",K35+L35+M35) | O35: =IF($U35="","",IFERROR(N35/$E$4,"")) | P35: =IF($U35="","",IFERROR(J35-O35,"")) | Q35: =IF($U35="","",IFERROR(P35/J35,"")) | R35: =IF($U35="","",IFERROR(J35/F35,"")) | S35: =IF($U35="","",IFERROR(O35/F35,"")) | U35: =IFERROR(MATCH(26,NAVES!$P$7:$P$200,0),"")
A36: =IF($U36="","",27) | B36: =IF($U36="","",INDEX(NAVES!$B$7:$B$200,$U36)) | C36: =IF($U36="","",IF(INDEX(NAVES!$M$7:$M$200,$U36)="","",INDEX(NAVES!$M$7:$M$200,$U36))) | D36: =IF($U36="","",INDEX(NAVES!$C$7:$C$200,$U36)) | E36: =IF($U36="","",INDEX(NAVES!$D$7:$D$200,$U36)) | F36: =IF($U36="","",INDEX(NAVES!$E$7:$E$200,$U36)) | G36: =IF($U36="","",IF(INDEX(NAVES!$F$7:$F$200,$U36)="","",INDEX(NAVES!$F$7:$F$200,$U36))) | H36: =IF($U36="","",IF(INDEX(NAVES!$G$7:$G$200,$U36)="","",INDEX(NAVES!$G$7:$G$200,$U36))) | I36: =IF($U36="","",INDEX(NAVES!$H$7:$H$200,$U36)) | J36: =IF($U36="","",N(INDEX(NAVES!$N$7:$N$200,$U36))) | K36: =IF($U36="","",N(INDEX(NAVES!$I$7:$I$200,$U36))) | L36: =IF($U36="","",N(INDEX(NAVES!$J$7:$J$200,$U36))) | M36: =IF($U36="","",IFERROR(F36/SUMIF(NAVES!$A$7:$A$200,$B$4,NAVES!$E$7:$E$200)*$I$4*$E$4,0)) | N36: =IF($U36="","",K36+L36+M36) | O36: =IF($U36="","",IFERROR(N36/$E$4,"")) | P36: =IF($U36="","",IFERROR(J36-O36,"")) | Q36: =IF($U36="","",IFERROR(P36/J36,"")) | R36: =IF($U36="","",IFERROR(J36/F36,"")) | S36: =IF($U36="","",IFERROR(O36/F36,"")) | U36: =IFERROR(MATCH(27,NAVES!$P$7:$P$200,0),"")
A37: =IF($U37="","",28) | B37: =IF($U37="","",INDEX(NAVES!$B$7:$B$200,$U37)) | C37: =IF($U37="","",IF(INDEX(NAVES!$M$7:$M$200,$U37)="","",INDEX(NAVES!$M$7:$M$200,$U37))) | D37: =IF($U37="","",INDEX(NAVES!$C$7:$C$200,$U37)) | E37: =IF($U37="","",INDEX(NAVES!$D$7:$D$200,$U37)) | F37: =IF($U37="","",INDEX(NAVES!$E$7:$E$200,$U37)) | G37: =IF($U37="","",IF(INDEX(NAVES!$F$7:$F$200,$U37)="","",INDEX(NAVES!$F$7:$F$200,$U37))) | H37: =IF($U37="","",IF(INDEX(NAVES!$G$7:$G$200,$U37)="","",INDEX(NAVES!$G$7:$G$200,$U37))) | I37: =IF($U37="","",INDEX(NAVES!$H$7:$H$200,$U37)) | J37: =IF($U37="","",N(INDEX(NAVES!$N$7:$N$200,$U37))) | K37: =IF($U37="","",N(INDEX(NAVES!$I$7:$I$200,$U37))) | L37: =IF($U37="","",N(INDEX(NAVES!$J$7:$J$200,$U37))) | M37: =IF($U37="","",IFERROR(F37/SUMIF(NAVES!$A$7:$A$200,$B$4,NAVES!$E$7:$E$200)*$I$4*$E$4,0)) | N37: =IF($U37="","",K37+L37+M37) | O37: =IF($U37="","",IFERROR(N37/$E$4,"")) | P37: =IF($U37="","",IFERROR(J37-O37,"")) | Q37: =IF($U37="","",IFERROR(P37/J37,"")) | R37: =IF($U37="","",IFERROR(J37/F37,"")) | S37: =IF($U37="","",IFERROR(O37/F37,"")) | U37: =IFERROR(MATCH(28,NAVES!$P$7:$P$200,0),"")
A38: =IF($U38="","",29) | B38: =IF($U38="","",INDEX(NAVES!$B$7:$B$200,$U38)) | C38: =IF($U38="","",IF(INDEX(NAVES!$M$7:$M$200,$U38)="","",INDEX(NAVES!$M$7:$M$200,$U38))) | D38: =IF($U38="","",INDEX(NAVES!$C$7:$C$200,$U38)) | E38: =IF($U38="","",INDEX(NAVES!$D$7:$D$200,$U38)) | F38: =IF($U38="","",INDEX(NAVES!$E$7:$E$200,$U38)) | G38: =IF($U38="","",IF(INDEX(NAVES!$F$7:$F$200,$U38)="","",INDEX(NAVES!$F$7:$F$200,$U38))) | H38: =IF($U38="","",IF(INDEX(NAVES!$G$7:$G$200,$U38)="","",INDEX(NAVES!$G$7:$G$200,$U38))) | I38: =IF($U38="","",INDEX(NAVES!$H$7:$H$200,$U38)) | J38: =IF($U38="","",N(INDEX(NAVES!$N$7:$N$200,$U38))) | K38: =IF($U38="","",N(INDEX(NAVES!$I$7:$I$200,$U38))) | L38: =IF($U38="","",N(INDEX(NAVES!$J$7:$J$200,$U38))) | M38: =IF($U38="","",IFERROR(F38/SUMIF(NAVES!$A$7:$A$200,$B$4,NAVES!$E$7:$E$200)*$I$4*$E$4,0)) | N38: =IF($U38="","",K38+L38+M38) | O38: =IF($U38="","",IFERROR(N38/$E$4,"")) | P38: =IF($U38="","",IFERROR(J38-O38,"")) | Q38: =IF($U38="","",IFERROR(P38/J38,"")) | R38: =IF($U38="","",IFERROR(J38/F38,"")) | S38: =IF($U38="","",IFERROR(O38/F38,"")) | U38: =IFERROR(MATCH(29,NAVES!$P$7:$P$200,0),"")
A39: =IF($U39="","",30) | B39: =IF($U39="","",INDEX(NAVES!$B$7:$B$200,$U39)) | C39: =IF($U39="","",IF(INDEX(NAVES!$M$7:$M$200,$U39)="","",INDEX(NAVES!$M$7:$M$200,$U39))) | D39: =IF($U39="","",INDEX(NAVES!$C$7:$C$200,$U39)) | E39: =IF($U39="","",INDEX(NAVES!$D$7:$D$200,$U39)) | F39: =IF($U39="","",INDEX(NAVES!$E$7:$E$200,$U39)) | G39: =IF($U39="","",IF(INDEX(NAVES!$F$7:$F$200,$U39)="","",INDEX(NAVES!$F$7:$F$200,$U39))) | H39: =IF($U39="","",IF(INDEX(NAVES!$G$7:$G$200,$U39)="","",INDEX(NAVES!$G$7:$G$200,$U39))) | I39: =IF($U39="","",INDEX(NAVES!$H$7:$H$200,$U39)) | J39: =IF($U39="","",N(INDEX(NAVES!$N$7:$N$200,$U39))) | K39: =IF($U39="","",N(INDEX(NAVES!$I$7:$I$200,$U39))) | L39: =IF($U39="","",N(INDEX(NAVES!$J$7:$J$200,$U39))) | M39: =IF($U39="","",IFERROR(F39/SUMIF(NAVES!$A$7:$A$200,$B$4,NAVES!$E$7:$E$200)*$I$4*$E$4,0)) | N39: =IF($U39="","",K39+L39+M39) | O39: =IF($U39="","",IFERROR(N39/$E$4,"")) | P39: =IF($U39="","",IFERROR(J39-O39,"")) | Q39: =IF($U39="","",IFERROR(P39/J39,"")) | R39: =IF($U39="","",IFERROR(J39/F39,"")) | S39: =IF($U39="","",IFERROR(O39/F39,"")) | U39: =IFERROR(MATCH(30,NAVES!$P$7:$P$200,0),"")
A40: TOTAL MES | F40: =SUM(F10:F39) -> 1151 | G40: =SUM(G10:G39) -> 1145 | H40: =IFERROR(SUMPRODUCT((NAVES!$A$7:$A$200=$B$4)*NAVES!$F$7:$F$200*NAVES!$G$7:$G$200)/SUMIF(NAVES!$A$7:$A$200,$B$4,NAVES!$F$7:$F$200),"") -> 2.8327074 | J40: =SUM(J10:J39) -> 630824 | K40: =SUM(K10:K39) -> 14253664 | L40: =SUM(L10:L39) -> 25684855 | M40: =SUM(M10:M39) -> 72134138 | N40: =SUM(N10:N39) -> 1.1207266e+08 | O40: =SUM(O10:O39) -> 123837.19 | P40: =SUM(P10:P39) -> 506986.81 | Q40: =IFERROR(P40/J40,"") -> 0.80368979 | R40: =IFERROR(J40/F40,"") -> 548.06603 | S40: =IFERROR(O40/F40,"") -> 107.59096
A42: Notas: venta por nave según "Servicio Reefer" de Naves por Servicios (cuadra con RESUMEN; ver control en P4). Naves sin venta (descargas, EDP pendiente) muestran margen negativo por el costo asignado. Columna U: auxiliar.
A44: ="VENTA vs COSTO POR NAVE — "&UPPER($B$4)&" 2026" -> VENTA vs COSTO POR NAVE — SEPTIEMBRE 2026

Sheet CONEXIONES
A1: CONEXIONES SIMULTÁNEAS REEFER 2026 — POR DÍA Y POR MES
A2: Elige el mes en la celda amarilla. Máx. simultáneo = mayor cantidad de reefers conectados al mismo tiempo en el día (al minuto), según el detalle de los EDP (pestaña DATOS_CONEX). PPK = equipos arrendados ese día según pestaña PPK.
A4: MES | B4: Septiembre | E4: Umbral peak | F4: 200 | H4: EDP del mes | I4: =IF(COUNTIF(DATOS_CONEX!$B$7:$B$4000,$B$4)=0,"Falta EDP","Cargado ("&COUNTIFS(DATOS_CONEX!$B$7:$B$4000,$B$4,DATOS_CONEX!$I$7:$I$4000,"Sí")&" válidos)") -> Cargado (1146 válidos) | M4: Excluidos del EDP | O4: =COUNTIFS(DATOS_CONEX!$B$7:$B$4000,$B$4,DATOS_CONEX!$I$7:$I$4000,"No") -> 8 | Z4: =MATCH($B$4,{"Enero","Febrero","Marzo","Abril","Mayo","Junio","Julio","Agosto","Septiembre","Octubre","Noviembre","Diciembre"},0) -> 9
A6: MÁX. SIMULTÁNEO | C6: FECHA / HORA DEL MÁX. | E6: NAVE AL MÁX. | G6: PROMEDIO EN PARALELO | I6: DÍAS ≥ UMBRAL | K6: MÁX. PPK EN UN DÍA | M6: PROM. MÁX. DIARIO | O6: REEFER-DÍAS DEL MES
A7: =IFERROR(MAX(D10:D40),"") -> 400 | C7: =IFERROR(IFERROR(INDEX(DATOS_CONEX!$F$7:$F$4000,MATCH($B$4&"|"&A7,DATOS_CONEX!$N$7:$N$4000,0)),"Inicio de mes"),"") -> 46290.938 | E7: =IFERROR(IFERROR(INDEX(DATOS_CONEX!$C$7:$C$4000,MATCH($B$4&"|"&A7,DATOS_CONEX!$N$7:$N$4000,0)),"-"),"") -> POLAR COLOMBIA | G7: =IFERROR(SUMPRODUCT((DATOS_CONEX!$I$7:$I$4000="Sí")*(((DATOS_CONEX!$G$7:$G$4000+DATE(2026,$Z$4+1,1)-ABS(DATOS_CONEX!$G$7:$G$4000-DATE(2026,$Z$4+1,1)))/2-(DATOS_CONEX!$F$7:$F$4000+DATE(2026,$Z$4,1)+ABS(DATOS_CONEX!$F$7:$F$4000-DATE(2026,$Z$4,1)))/2)+ABS(((DATOS_CONEX!$G$7:$G$4000+DATE(2026,$Z$4+1,1)-ABS(DATOS_CONEX!$G$7:$G$4000-DATE(2026,$Z$4+1,1)))/2-(DATOS_CONEX!$F$7:$F$4000+DATE(2026,$Z$4,1)+ABS(DATOS_CONEX!$F$7:$F$4000-DATE(2026,$Z$4,1)))/2)))/2)/(DATE(2026,$Z$4+1,1)-DATE(2026,$Z$4,1)),"") -> 105.59009 | I7: =IFERROR(COUNTIF(D10:D40,">="&$F$4),"") -> 10 | K7: =IFERROR(MAX(G10:G40),"") -> 8 | M7: =IFERROR(IFERROR(AVERAGE(D10:D40),""),"") -> 137.56667 | O7: =IFERROR(I41,"") -> 3167.7028
A9: Fecha | B9: Día | C9: Conectados 00:00 | D9: Máx. simultáneo | E9: Conexiones | F9: Desconexiones | G9: PPK arrendados | H9: Reefers conectados en el día | I9: Reefer-días (equiv. 24 h)
A10: =IF(1<=DAY(DATE(2026,$Z$4+1,1)-1),DATE(2026,$Z$4,1),"") -> 46266 | B10: =IF($A10="","",DAY($A10)) -> 1 | C10: =IF($A10="","",COUNTIFS(DATOS_CONEX!$F$7:$F$4000,"<="&$A10,DATOS_CONEX!$G$7:$G$4000,">"&$A10,DATOS_CONEX!$I$7:$I$4000,"Sí")) -> 31 | D10: =IF($A10="","",MAX(C10,_xlfn.MAXIFS(DATOS_CONEX!$L$7:$L$4000,DATOS_CONEX!$F$7:$F$4000,">="&$A10,DATOS_CONEX!$F$7:$F$4000,"<"&($A10+1)))) -> 36 | E10: =IF($A10="","",COUNTIFS(DATOS_CONEX!$F$7:$F$4000,">"&$A10,DATOS_CONEX!$F$7:$F$4000,"<"&($A10+1),DATOS_CONEX!$I$7:$I$4000,"Sí")) -> 6 | F10: =IF($A10="","",COUNTIFS(DATOS_CONEX!$G$7:$G$4000,">="&$A10,DATOS_CONEX!$G$7:$G$4000,"<"&($A10+1),DATOS_CONEX!$I$7:$I$4000,"Sí")) -> 1 | G10: =IF($A10="","",COUNTIFS(DATOS_CONEX!$R$7:$R$4000,"<="&$A10,DATOS_CONEX!$S$7:$S$4000,">="&$A10)) -> 2 | H10: =IF($A10="","",COUNTIFS(DATOS_CONEX!$F$7:$F$4000,"<"&($A10+1),DATOS_CONEX!$G$7:$G$4000,">"&$A10,DATOS_CONEX!$I$7:$I$4000,"Sí")) -> 37 | I10: =IF($A10="","",SUMPRODUCT((DATOS_CONEX!$I$7:$I$4000="Sí")*(((DATOS_CONEX!$G$7:$G$4000+($A10+1)-ABS(DATOS_CONEX!$G$7:$G$4000-($A10+1)))/2-(DATOS_CONEX!$F$7:$F$4000+$A10+ABS(DATOS_CONEX!$F$7:$F$4000-$A10))/2)+ABS(((DATOS_CONEX!$G$7:$G$4000+($A10+1)-ABS(DATOS_CONEX!$G$7:$G$4000-($A10+1)))/2-(DATOS_CONEX!$F$7:$F$4000+$A10+ABS(DATOS_CONEX!$F$7:$F$4000-$A10))/2)))/2)) -> 33.057639 | Y10: =IF($A10="","",-F10) -> -1
A11: =IF(2<=DAY(DATE(2026,$Z$4+1,1)-1),DATE(2026,$Z$4,2),"") -> 46267 | B11: =IF($A11="","",DAY($A11)) -> 2 | C11: =IF($A11="","",COUNTIFS(DATOS_CONEX!$F$7:$F$4000,"<="&$A11,DATOS_CONEX!$G$7:$G$4000,">"&$A11,DATOS_CONEX!$I$7:$I$4000,"Sí")) -> 37 | D11: =IF($A11="","",MAX(C11,_xlfn.MAXIFS(DATOS_CONEX!$L$7:$L$4000,DATOS_CONEX!$F$7:$F$4000,">="&$A11,DATOS_CONEX!$F$7:$F$4000,"<"&($A11+1)))) -> 173 | E11: =IF($A11="","",COUNTIFS(DATOS_CONEX!$F$7:$F$4000,">"&$A11,DATOS_CONEX!$F$7:$F$4000,"<"&($A11+1),DATOS_CONEX!$I$7:$I$4000,"Sí")) -> 141 | F11: =IF($A11="","",COUNTIFS(DATOS_CONEX!$G$7:$G$4000,">="&$A11,DATOS_CONEX!$G$7:$G$4000,"<"&($A11+1),DATOS_CONEX!$I$7:$I$4000,"Sí")) -> 5 | G11: =IF($A11="","",COUNTIFS(DATOS_CONEX!$R$7:$R$4000,"<="&$A11,DATOS_CONEX!$S$7:$S$4000,">="&$A11)) -> 3 | H11: =IF($A11="","",COUNTIFS(DATOS_CONEX!$F$7:$F$4000,"<"&($A11+1),DATOS_CONEX!$G$7:$G$4000,">"&$A11,DATOS_CONEX!$I$7:$I$4000,"Sí")) -> 178 | I11: =IF($A11="","",SUMPRODUCT((DATOS_CONEX!$I$7:$I$4000="Sí")*(((DATOS_CONEX!$G$7:$G$4000+($A11+1)-ABS(DATOS_CONEX!$G$7:$G$4000-($A11+1)))/2-(DATOS_CONEX!$F$7:$F$4000+$A11+ABS(DATOS_CONEX!$F$7:$F$4000-$A11))/2)+ABS(((DATOS_CONEX!$G$7:$G$4000+($A11+1)-ABS(DATOS_CONEX!$G$7:$G$4000-($A11+1)))/2-(DATOS_CONEX!$F$7:$F$4000+$A11+ABS(DATOS_CONEX!$F$7:$F$4000-$A11))/2)))/2)) -> 115.83264 | Y11: =IF($A11="","",-F11) -> -5
A12: =IF(3<=DAY(DATE(2026,$Z$4+1,1)-1),DATE(2026,$Z$4,3),"") -> 46268 | B12: =IF($A12="","",DAY($A12)) -> 3 | C12: =IF($A12="","",COUNTIFS(DATOS_CONEX!$F$7:$F$4000,"<="&$A12,DATOS_CONEX!$G$7:$G$4000,">"&$A12,DATOS_CONEX!$I$7:$I$4000,"Sí")) -> 173 | D12: =IF($A12="","",MAX(C12,_xlfn.MAXIFS(DATOS_CONEX!$L$7:$L$4000,DATOS_CONEX!$F$7:$F$4000,">="&$A12,DATOS_CONEX!$F$7:$F$4000,"<"&($A12+1)))) -> 306 | E12: =IF($A12="","",COUNTIFS(DATOS_CONEX!$F$7:$F$4000,">"&$A12,DATOS_CONEX!$F$7:$F$4000,"<"&($A12+1),DATOS_CONEX!$I$7:$I$4000,"Sí")) -> 133 | F12: =IF($A12="","",COUNTIFS(DATOS_CONEX!$G$7:$G$4000,">="&$A12,DATOS_CONEX!$G$7:$G$4000,"<"&($A12+1),DATOS_CONEX!$I$7:$I$4000,"Sí")) -> 0 | G12: =IF($A12="","",COUNTIFS(DATOS_CONEX!$R$7:$R$4000,"<="&$A12,DATOS_CONEX!$S$7:$S$4000,">="&$A12)) -> 5 | H12: =IF($A12="","",COUNTIFS(DATOS_CONEX!$F$7:$F$4000,"<"&($A12+1),DATOS_CONEX!$G$7:$G$4000,">"&$A12,DATOS_CONEX!$I$7:$I$4000,"Sí")) -> 306 | I12: =IF($A12="","",SUMPRODUCT((DATOS_CONEX!$I$7:$I$4000="Sí")*(((DATOS_CONEX!$G$7:$G$4000+($A12+1)-ABS(DATOS_CONEX!$G$7:$G$4000-($A12+1)))/2-(DATOS_CONEX!$F$7:$F$4000+$A12+ABS(DATOS_CONEX!$F$7:$F$4000-$A12))/2)+ABS(((DATOS_CONEX!$G$7:$G$4000+($A12+1)-ABS(DATOS_CONEX!$G$7:$G$4000-($A12+1)))/2-(DATOS_CONEX!$F$7:$F$4000+$A12+ABS(DATOS_CONEX!$F$7:$F$4000-$A12))/2)))/2)) -> 256.65833 | Y12: =IF($A12="","",-F12) -> 0
A13: =IF(4<=DAY(DATE(2026,$Z$4+1,1)-1),DATE(2026,$Z$4,4),"") -> 46269 | B13: =IF($A13="","",DAY($A13)) -> 4 | C13: =IF($A13="","",COUNTIFS(DATOS_CONEX!$F$7:$F$4000,"<="&$A13,DATOS_CONEX!$G$7:$G$4000,">"&$A13,DATOS_CONEX!$I$7:$I$4000,"Sí")) -> 306 | D13: =IF($A13="","",MAX(C13,_xlfn.MAXIFS(DATOS_CONEX!$L$7:$L$4000,DATOS_CONEX!$F$7:$F$4000,">="&$A13,DATOS_CONEX!$F$7:$F$4000,"<"&($A13+1)))) -> 307 | E13: =IF($A13="","",COUNTIFS(DATOS_CONEX!$F$7:$F$4000,">"&$A13,DATOS_CONEX!$F$7:$F$4000,"<"&($A13+1),DATOS_CONEX!$I$7:$I$4000,"Sí")) -> 1 | F13: =IF($A13="","",COUNTIFS(DATOS_CONEX!$G$7:$G$4000,">="&$A13,DATOS_CONEX!$G$7:$G$4000,"<"&($A13+1),DATOS_CONEX!$I$7:$I$4000,"Sí")) -> 0 | G13: =IF($A13="","",COUNTIFS(DATOS_CONEX!$R$7:$R$4000,"<="&$A13,DATOS_CONEX!$S$7:$S$4000,">="&$A13)) -> 5 | H13: =IF($A13="","",COUNTIFS(DATOS_CONEX!$F$7:$F$4000,"<"&($A13+1),DATOS_CONEX!$G$7:$G$4000,">"&$A13,DATOS_CONEX!$I$7:$I$4000,"Sí")) -> 307 | I13: =IF($A13="","",SUMPRODUCT((DATOS_CONEX!$I$7:$I$4000="Sí")*(((DATOS_CONEX!$G$7:$G$4000+($A13+1)-ABS(DATOS_CONEX!$G$7:$G$4000-($A13+1)))/2-(DATOS_CONEX!$F$7:$F$4000+$A13+ABS(DATOS_CONEX!$F$7:$F$4000-$A13))/2)+ABS(((DATOS_CONEX!$G$7:$G$4000+($A13+1)-ABS(DATOS_CONEX!$G$7:$G$4000-($A13+1)))/2-(DATOS_CONEX!$F$7:$F$4000+$A13+ABS(DATOS_CONEX!$F$7:$F$4000-$A13))/2)))/2)) -> 306.56181 | Y13: =IF($A13="","",-F13) -> 0
A14: =IF(5<=DAY(DATE(2026,$Z$4+1,1)-1),DATE(2026,$Z$4,5),"") -> 46270 | B14: =IF($A14="","",DAY($A14)) -> 5 | C14: =IF($A14="","",COUNTIFS(DATOS_CONEX!$F$7:$F$4000,"<="&$A14,DATOS_CONEX!$G$7:$G$4000,">"&$A14,DATOS_CONEX!$I$7:$I$4000,"Sí")) -> 307 | D14: =IF($A14="","",MAX(C14,_xlfn.MAXIFS(DATOS_CONEX!$L$7:$L$4000,DATOS_CONEX!$F$7:$F$4000,">="&$A14,DATOS_CONEX!$F$7:$F$4000,"<"&($A14+1)))) -> 307 | E14: =IF($A14="","",COUNTIFS(DATOS_CONEX!$F$7:$F$4000,">"&$A14,DATOS_CONEX!$F$7:$F$4000,"<"&($A14+1),DATOS_CONEX!$I$7:$I$4000,"Sí")) -> 13 | F14: =IF($A14="","",COUNTIFS(DATOS_CONEX!$G$7:$G$4000,">="&$A14,DATOS_CONEX!$G$7:$G$4000,"<"&($A14+1),DATOS_CONEX!$I$7:$I$4000,"Sí")) -> 267 | G14: =IF($A14="","",COUNTIFS(DATOS_CONEX!$R$7:$R$4000,"<="&$A14,DATOS_CONEX!$S$7:$S$4000,">="&$A14)) -> 4 | H14: =IF($A14="","",COUNTIFS(DATOS_CONEX!$F$7:$F$4000,"<"&($A14+1),DATOS_CONEX!$G$7:$G$4000,">"&$A14,DATOS_CONEX!$I$7:$I$4000,"Sí")) -> 320 | I14: =IF($A14="","",SUMPRODUCT((DATOS_CONEX!$I$7:$I$4000="Sí")*(((DATOS_CONEX!$G$7:$G$4000+($A14+1)-ABS(DATOS_CONEX!$G$7:$G$4000-($A14+1)))/2-(DATOS_CONEX!$F$7:$F$4000+$A14+ABS(DATOS_CONEX!$F$7:$F$4000-$A14))/2)+ABS(((DATOS_CONEX!$G$7:$G$4000+($A14+1)-ABS(DATOS_CONEX!$G$7:$G$4000-($A14+1)))/2-(DATOS_CONEX!$F$7:$F$4000+$A14+ABS(DATOS_CONEX!$F$7:$F$4000-$A14))/2)))/2)) -> 193.45903 | Y14: =IF($A14="","",-F14) -> -267
A15: =IF(6<=DAY(DATE(2026,$Z$4+1,1)-1),DATE(2026,$Z$4,6),"") -> 46271 | B15: =IF($A15="","",DAY($A15)) -> 6 | C15: =IF($A15="","",COUNTIFS(DATOS_CONEX!$F$7:$F$4000,"<="&$A15,DATOS_CONEX!$G$7:$G$4000,">"&$A15,DATOS_CONEX!$I$7:$I$4000,"Sí")) -> 53 | D15: =IF($A15="","",MAX(C15,_xlfn.MAXIFS(DATOS_CONEX!$L$7:$L$4000,DATOS_CONEX!$F$7:$F$4000,">="&$A15,DATOS_CONEX!$F$7:$F$4000,"<"&($A15+1)))) -> 53 | E15: =IF($A15="","",COUNTIFS(DATOS_CONEX!$F$7:$F$4000,">"&$A15,DATOS_CONEX!$F$7:$F$4000,"<"&($A15+1),DATOS_CONEX!$I$7:$I$4000,"Sí")) -> 0 | F15: =IF($A15="","",COUNTIFS(DATOS_CONEX!$G$7:$G$4000,">="&$A15,DATOS_CONEX!$G$7:$G$4000,"<"&($A15+1),DATOS_CONEX!$I$7:$I$4000,"Sí")) -> 10 | G15: =IF($A15="","",COUNTIFS(DATOS_CONEX!$R$7:$R$4000,"<="&$A15,DATOS_CONEX!$S$7:$S$4000,">="&$A15)) -> 4 | H15: =IF($A15="","",COUNTIFS(DATOS_CONEX!$F$7:$F$4000,"<"&($A15+1),DATOS_CONEX!$G$7:$G$4000,">"&$A15,DATOS_CONEX!$I$7:$I$4000,"Sí")) -> 53 | I15: =IF($A15="","",SUMPRODUCT((DATOS_CONEX!$I$7:$I$4000="Sí")*(((DATOS_CONEX!$G$7:$G$4000+($A15+1)-ABS(DATOS_CONEX!$G$7:$G$4000-($A15+1)))/2-(DATOS_CONEX!$F$7:$F$4000+$A15+ABS(DATOS_CONEX!$F$7:$F$4000-$A15))/2)+ABS(((DATOS_CONEX!$G$7:$G$4000+($A15+1)-ABS(DATOS_CONEX!$G$7:$G$4000-($A15+1)))/2-(DATOS_CONEX!$F$7:$F$4000+$A15+ABS(DATOS_CONEX!$F$7:$F$4000-$A15))/2)))/2)) -> 52.158333 | Y15: =IF($A15="","",-F15) -> -10
A16: =IF(7<=DAY(DATE(2026,$Z$4+1,1)-1),DATE(2026,$Z$4,7),"") -> 46272 | B16: =IF($A16="","",DAY($A16)) -> 7 | C16: =IF($A16="","",COUNTIFS(DATOS_CONEX!$F$7:$F$4000,"<="&$A16,DATOS_CONEX!$G$7:$G$4000,">"&$A16,DATOS_CONEX!$I$7:$I$4000,"Sí")) -> 43 | D16: =IF($A16="","",MAX(C16,_xlfn.MAXIFS(DATOS_CONEX!$L$7:$L$4000,DATOS_CONEX!$F$7:$F$4000,">="&$A16,DATOS_CONEX!$F$7:$F$4000,"<"&($A16+1)))) -> 44 | E16: =IF($A16="","",COUNTIFS(DATOS_CONEX!$F$7:$F$4000,">"&$A16,DATOS_CONEX!$F$7:$F$4000,"<"&($A16+1),DATOS_CONEX!$I$7:$I$4000,"Sí")) -> 4 | F16: =IF($A16="","",COUNTIFS(DATOS_CONEX!$G$7:$G$4000,">="&$A16,DATOS_CONEX!$G$7:$G$4000,"<"&($A16+1),DATOS_CONEX!$I$7:$I$4000,"Sí")) -> 4 | G16: =IF($A16="","",COUNTIFS(DATOS_CONEX!$R$7:$R$4000,"<="&$A16,DATOS_CONEX!$S$7:$S$4000,">="&$A16)) -> 2 | H16: =IF($A16="","",COUNTIFS(DATOS_CONEX!$F$7:$F$4000,"<"&($A16+1),DATOS_CONEX!$G$7:$G$4000,">"&$A16,DATOS_CONEX!$I$7:$I$4000,"Sí")) -> 47 | I16: =IF($A16="","",SUMPRODUCT((DATOS_CONEX!$I$7:$I$4000="Sí")*(((DATOS_CONEX!$G$7:$G$4000+($A16+1)-ABS(DATOS_CONEX!$G$7:$G$4000-($A16+1)))/2-(DATOS_CONEX!$F$7:$F$4000+$A16+ABS(DATOS_CONEX!$F$7:$F$4000-$A16))/2)+ABS(((DATOS_CONEX!$G$7:$G$4000+($A16+1)-ABS(DATOS_CONEX!$G$7:$G$4000-($A16+1)))/2-(DATOS_CONEX!$F$7:$F$4000+$A16+ABS(DATOS_CONEX!$F$7:$F$4000-$A16))/2)))/2)) -> 42.381944 | Y16: =IF($A16="","",-F16) -> -4
A17: =IF(8<=DAY(DATE(2026,$Z$4+1,1)-1),DATE(2026,$Z$4,8),"") -> 46273 | B17: =IF($A17="","",DAY($A17)) -> 8 | C17: =IF($A17="","",COUNTIFS(DATOS_CONEX!$F$7:$F$4000,"<="&$A17,DATOS_CONEX!$G$7:$G$4000,">"&$A17,DATOS_CONEX!$I$7:$I$4000,"Sí")) -> 43 | D17: =IF($A17="","",MAX(C17,_xlfn.MAXIFS(DATOS_CONEX!$L$7:$L$4000,DATOS_CONEX!$F$7:$F$4000,">="&$A17,DATOS_CONEX!$F$7:$F$4000,"<"&($A17+1)))) -> 51 | E17: =IF($A17="","",COUNTIFS(DATOS_CONEX!$F$7:$F$4000,">"&$A17,DATOS_CONEX!$F$7:$F$4000,"<"&($A17+1),DATOS_CONEX!$I$7:$I$4000,"Sí")) -> 11 | F17: =IF($A17="","",COUNTIFS(DATOS_CONEX!$G$7:$G$4000,">="&$A17,DATOS_CONEX!$G$7:$G$4000,"<"&($A17+1),DATOS_CONEX!$I$7:$I$4000,"Sí")) -> 3 | G17: =IF($A17="","",COUNTIFS(DATOS_CONEX!$R$7:$R$4000,"<="&$A17,DATOS_CONEX!$S$7:$S$4000,">="&$A17)) -> 2 | H17: =IF($A17="","",COUNTIFS(DATOS_CONEX!$F$7:$F$4000,"<"&($A17+1),DATOS_CONEX!$G$7:$G$4000,">"&$A17,DATOS_CONEX!$I$7:$I$4000,"Sí")) -> 54 | I17: =IF($A17="","",SUMPRODUCT((DATOS_CONEX!$I$7:$I$4000="Sí")*(((DATOS_CONEX!$G$7:$G$4000+($A17+1)-ABS(DATOS_CONEX!$G$7:$G$4000-($A17+1)))/2-(DATOS_CONEX!$F$7:$F$4000+$A17+ABS(DATOS_CONEX!$F$7:$F$4000-$A17))/2)+ABS(((DATOS_CONEX!$G$7:$G$4000+($A17+1)-ABS(DATOS_CONEX!$G$7:$G$4000-($A17+1)))/2-(DATOS_CONEX!$F$7:$F$4000+$A17+ABS(DATOS_CONEX!$F$7:$F$4000-$A17))/2)))/2)) -> 45.027778 | Y17: =IF($A17="","",-F17) -> -3
A18: =IF(9<=DAY(DATE(2026,$Z$4+1,1)-1),DATE(2026,$Z$4,9),"") -> 46274 | B18: =IF($A18="","",DAY($A18)) -> 9 | C18: =IF($A18="","",COUNTIFS(DATOS_CONEX!$F$7:$F$4000,"<="&$A18,DATOS_CONEX!$G$7:$G$4000,">"&$A18,DATOS_CONEX!$I$7:$I$4000,"Sí")) -> 51 | D18: =IF($A18="","",MAX(C18,_xlfn.MAXIFS(DATOS_CONEX!$L$7:$L$4000,DATOS_CONEX!$F$7:$F$4000,">="&$A18,DATOS_CONEX!$F$7:$F$4000,"<"&($A18+1)))) -> 51 | E18: =IF($A18="","",COUNTIFS(DATOS_CONEX!$F$7:$F$4000,">"&$A18,DATOS_CONEX!$F$7:$F$4000,"<"&($A18+1),DATOS_CONEX!$I$7:$I$4000,"Sí")) -> 3 | F18: =IF($A18="","",COUNTIFS(DATOS_CONEX!$G$7:$G$4000,">="&$A18,DATOS_CONEX!$G$7:$G$4000,"<"&($A18+1),DATOS_CONEX!$I$7:$I$4000,"Sí")) -> 14 | G18: =IF($A18="","",COUNTIFS(DATOS_CONEX!$R$7:$R$4000,"<="&$A18,DATOS_CONEX!$S$7:$S$4000,">="&$A18)) -> 2 | H18: =IF($A18="","",COUNTIFS(DATOS_CONEX!$F$7:$F$4000,"<"&($A18+1),DATOS_CONEX!$G$7:$G$4000,">"&$A18,DATOS_CONEX!$I$7:$I$4000,"Sí")) -> 54 | I18: =IF($A18="","",SUMPRODUCT((DATOS_CONEX!$I$7:$I$4000="Sí")*(((DATOS_CONEX!$G$7:$G$4000+($A18+1)-ABS(DATOS_CONEX!$G$7:$G$4000-($A18+1)))/2-(DATOS_CONEX!$F$7:$F$4000+$A18+ABS(DATOS_CONEX!$F$7:$F$4000-$A18))/2)+ABS(((DATOS_CONEX!$G$7:$G$4000+($A18+1)-ABS(DATOS_CONEX!$G$7:$G$4000-($A18+1)))/2-(DATOS_CONEX!$F$7:$F$4000+$A18+ABS(DATOS_CONEX!$F$7:$F$4000-$A18))/2)))/2)) -> 46.298611 | Y18: =IF($A18="","",-F18) -> -14
A19: =IF(10<=DAY(DATE(2026,$Z$4+1,1)-1),DATE(2026,$Z$4,10),"") -> 46275 | B19: =IF($A19="","",DAY($A19)) -> 10 | C19: =IF($A19="","",COUNTIFS(DATOS_CONEX!$F$7:$F$4000,"<="&$A19,DATOS_CONEX!$G$7:$G$4000,">"&$A19,DATOS_CONEX!$I$7:$I$4000,"Sí")) -> 41 | D19: =IF($A19="","",MAX(C19,_xlfn.MAXIFS(DATOS_CONEX!$L$7:$L$4000,DATOS_CONEX!$F$7:$F$4000,">="&$A19,DATOS_CONEX!$F$7:$F$4000,"<"&($A19+1)))) -> 235 | E19: =IF($A19="","",COUNTIFS(DATOS_CONEX!$F$7:$F$4000,">"&$A19,DATOS_CONEX!$F$7:$F$4000,"<"&($A19+1),DATOS_CONEX!$I$7:$I$4000,"Sí")) -> 197 | F19: =IF($A19="","",COUNTIFS(DATOS_CONEX!$G$7:$G$4000,">="&$A19,DATOS_CONEX!$G$7:$G$4000,"<"&($A19+1),DATOS_CONEX!$I$7:$I$4000,"Sí")) -> 6 | G19: =IF($A19="","",COUNTIFS(DATOS_CONEX!$R$7:$R$4000,"<="&$A19,DATOS_CONEX!$S$7:$S$4000,">="&$A19)) -> 5 | H19: =IF($A19="","",COUNTIFS(DATOS_CONEX!$F$7:$F$4000,"<"&($A19+1),DATOS_CONEX!$G$7:$G$4000,">"&$A19,DATOS_CONEX!$I$7:$I$4000,"Sí")) -> 238 | I19: =IF($A19="","",SUMPRODUCT((DATOS_CONEX!$I$7:$I$4000="Sí")*(((DATOS_CONEX!$G$7:$G$4000+($A19+1)-ABS(DATOS_CONEX!$G$7:$G$4000-($A19+1)))/2-(DATOS_CONEX!$F$7:$F$4000+$A19+ABS(DATOS_CONEX!$F$7:$F$4000-$A19))/2)+ABS(((DATOS_CONEX!$G$7:$G$4000+($A19+1)-ABS(DATOS_CONEX!$G$7:$G$4000-($A19+1)))/2-(DATOS_CONEX!$F$7:$F$4000+$A19+ABS(DATOS_CONEX!$F$7:$F$4000-$A19))/2)))/2)) -> 180.9625 | Y19: =IF($A19="","",-F19) -> -6
A20: =IF(11<=DAY(DATE(2026,$Z$4+1,1)-1),DATE(2026,$Z$4,11),"") -> 46276 | B20: =IF($A20="","",DAY($A20)) -> 11 | C20: =IF($A20="","",COUNTIFS(DATOS_CONEX!$F$7:$F$4000,"<="&$A20,DATOS_CONEX!$G$7:$G$4000,">"&$A20,DATOS_CONEX!$I$7:$I$4000,"Sí")) -> 232 | D20: =IF($A20="","",MAX(C20,_xlfn.MAXIFS(DATOS_CONEX!$L$7:$L$4000,DATOS_CONEX!$F$7:$F$4000,">="&$A20,DATOS_CONEX!$F$7:$F$4000,"<"&($A20+1)))) -> 240 | E20: =IF($A20="","",COUNTIFS(DATOS_CONEX!$F$7:$F$4000,">"&$A20,DATOS_CONEX!$F$7:$F$4000,"<"&($A20+1),DATOS_CONEX!$I$7:$I$4000,"Sí")) -> 10 | F20: =IF($A20="","",COUNTIFS(DATOS_CONEX!$G$7:$G$4000,">="&$A20,DATOS_CONEX!$G$7:$G$4000,"<"&($A20+1),DATOS_CONEX!$I$7:$I$4000,"Sí")) -> 2 | G20: =IF($A20="","",COUNTIFS(DATOS_CONEX!$R$7:$R$4000,"<="&$A20,DATOS_CONEX!$S$7:$S$4000,">="&$A20)) -> 5 | H20: =IF($A20="","",COUNTIFS(DATOS_CONEX!$F$7:$F$4000,"<"&($A20+1),DATOS_CONEX!$G$7:$G$4000,">"&$A20,DATOS_CONEX!$I$7:$I$4000,"Sí")) -> 242 | I20: =IF($A20="","",SUMPRODUCT((DATOS_CONEX!$I$7:$I$4000="Sí")*(((DATOS_CONEX!$G$7:$G$4000+($A20+1)-ABS(DATOS_CONEX!$G$7:$G$4000-($A20+1)))/2-(DATOS_CONEX!$F$7:$F$4000+$A20+ABS(DATOS_CONEX!$F$7:$F$4000-$A20))/2)+ABS(((DATOS_CONEX!$G$7:$G$4000+($A20+1)-ABS(DATOS_CONEX!$G$7:$G$4000-($A20+1)))/2-(DATOS_CONEX!$F$7:$F$4000+$A20+ABS(DATOS_CONEX!$F$7:$F$4000-$A20))/2)))/2)) -> 234.37292 | Y20: =IF($A20="","",-F20) -> -2
A21: =IF(12<=DAY(DATE(2026,$Z$4+1,1)-1),DATE(2026,$Z$4,12),"") -> 46277 | B21: =IF($A21="","",DAY($A21)) -> 12 | C21: =IF($A21="","",COUNTIFS(DATOS_CONEX!$F$7:$F$4000,"<="&$A21,DATOS_CONEX!$G$7:$G$4000,">"&$A21,DATOS_CONEX!$I$7:$I$4000,"Sí")) -> 240 | D21: =IF($A21="","",MAX(C21,_xlfn.MAXIFS(DATOS_CONEX!$L$7:$L$4000,DATOS_CONEX!$F$7:$F$4000,">="&$A21,DATOS_CONEX!$F$7:$F$4000,"<"&($A21+1)))) -> 240 | E21: =IF($A21="","",COUNTIFS(DATOS_CONEX!$F$7:$F$4000,">"&$A21,DATOS_CONEX!$F$7:$F$4000,"<"&($A21+1),DATOS_CONEX!$I$7:$I$4000,"Sí")) -> 4 | F21: =IF($A21="","",COUNTIFS(DATOS_CONEX!$G$7:$G$4000,">="&$A21,DATOS_CONEX!$G$7:$G$4000,"<"&($A21+1),DATOS_CONEX!$I$7:$I$4000,"Sí")) -> 160 | G21: =IF($A21="","",COUNTIFS(DATOS_CONEX!$R$7:$R$4000,"<="&$A21,DATOS_CONEX!$S$7:$S$4000,">="&$A21)) -> 5 | H21: =IF($A21="","",COUNTIFS(DATOS_CONEX!$F$7:$F$4000,"<"&($A21+1),DATOS_CONEX!$G$7:$G$4000,">"&$A21,DATOS_CONEX!$I$7:$I$4000,"Sí")) -> 244 | I21: =IF($A21="","",SUMPRODUCT((DATOS_CONEX!$I$7:$I$4000="Sí")*(((DATOS_CONEX!$G$7:$G$4000+($A21+1)-ABS(DATOS_CONEX!$G$7:$G$4000-($A21+1)))/2-(DATOS_CONEX!$F$7:$F$4000+$A21+ABS(DATOS_CONEX!$F$7:$F$4000-$A21))/2)+ABS(((DATOS_CONEX!$G$7:$G$4000+($A21+1)-ABS(DATOS_CONEX!$G$7:$G$4000-($A21+1)))/2-(DATOS_CONEX!$F$7:$F$4000+$A21+ABS(DATOS_CONEX!$F$7:$F$4000-$A21))/2)))/2)) -> 196.02639 | Y21: =IF($A21="","",-F21) -> -160
A22: =IF(13<=DAY(DATE(2026,$Z$4+1,1)-1),DATE(2026,$Z$4,13),"") -> 46278 | B22: =IF($A22="","",DAY($A22)) -> 13 | C22: =IF($A22="","",COUNTIFS(DATOS_CONEX!$F$7:$F$4000,"<="&$A22,DATOS_CONEX!$G$7:$G$4000,">"&$A22,DATOS_CONEX!$I$7:$I$4000,"Sí")) -> 84 | D22: =IF($A22="","",MAX(C22,_xlfn.MAXIFS(DATOS_CONEX!$L$7:$L$4000,DATOS_CONEX!$F$7:$F$4000,">="&$A22,DATOS_CONEX!$F$7:$F$4000,"<"&($A22+1)))) -> 84 | E22: =IF($A22="","",COUNTIFS(DATOS_CONEX!$F$7:$F$4000,">"&$A22,DATOS_CONEX!$F$7:$F$4000,"<"&($A22+1),DATOS_CONEX!$I$7:$I$4000,"Sí")) -> 0 | F22: =IF($A22="","",COUNTIFS(DATOS_CONEX!$G$7:$G$4000,">="&$A22,DATOS_CONEX!$G$7:$G$4000,"<"&($A22+1),DATOS_CONEX!$I$7:$I$4000,"Sí")) -> 51 | G22: =IF($A22="","",COUNTIFS(DATOS_CONEX!$R$7:$R$4000,"<="&$A22,DATOS_CONEX!$S$7:$S$4000,">="&$A22)) -> 2 | H22: =IF($A22="","",COUNTIFS(DATOS_CONEX!$F$7:$F$4000,"<"&($A22+1),DATOS_CONEX!$G$7:$G$4000,">"&$A22,DATOS_CONEX!$I$7:$I$4000,"Sí")) -> 84 | I22: =IF($A22="","",SUMPRODUCT((DATOS_CONEX!$I$7:$I$4000="Sí")*(((DATOS_CONEX!$G$7:$G$4000+($A22+1)-ABS(DATOS_CONEX!$G$7:$G$4000-($A22+1)))/2-(DATOS_CONEX!$F$7:$F$4000+$A22+ABS(DATOS_CONEX!$F$7:$F$4000-$A22))/2)+ABS(((DATOS_CONEX!$G$7:$G$4000+($A22+1)-ABS(DATOS_CONEX!$G$7:$G$4000-($A22+1)))/2-(DATOS_CONEX!$F$7:$F$4000+$A22+ABS(DATOS_CONEX!$F$7:$F$4000-$A22))/2)))/2)) -> 37.074306 | Y22: =IF($A22="","",-F22) -> -51
A23: =IF(14<=DAY(DATE(2026,$Z$4+1,1)-1),DATE(2026,$Z$4,14),"") -> 46279 | B23: =IF($A23="","",DAY($A23)) -> 14 | C23: =IF($A23="","",COUNTIFS(DATOS_CONEX!$F$7:$F$4000,"<="&$A23,DATOS_CONEX!$G$7:$G$4000,">"&$A23,DATOS_CONEX!$I$7:$I$4000,"Sí")) -> 33 | D23: =IF($A23="","",MAX(C23,_xlfn.MAXIFS(DATOS_CONEX!$L$7:$L$4000,DATOS_CONEX!$F$7:$F$4000,">="&$A23,DATOS_CONEX!$F$7:$F$4000,"<"&($A23+1)))) -> 38 | E23: =IF($A23="","",COUNTIFS(DATOS_CONEX!$F$7:$F$4000,">"&$A23,DATOS_CONEX!$F$7:$F$4000,"<"&($A23+1),DATOS_CONEX!$I$7:$I$4000,"Sí")) -> 5 | F23: =IF($A23="","",COUNTIFS(DATOS_CONEX!$G$7:$G$4000,">="&$A23,DATOS_CONEX!$G$7:$G$4000,"<"&($A23+1),DATOS_CONEX!$I$7:$I$4000,"Sí")) -> 0 | G23: =IF($A23="","",COUNTIFS(DATOS_CONEX!$R$7:$R$4000,"<="&$A23,DATOS_CONEX!$S$7:$S$4000,">="&$A23)) -> 1 | H23: =IF($A23="","",COUNTIFS(DATOS_CONEX!$F$7:$F$4000,"<"&($A23+1),DATOS_CONEX!$G$7:$G$4000,">"&$A23,DATOS_CONEX!$I$7:$I$4000,"Sí")) -> 38 | I23: =IF($A23="","",SUMPRODUCT((DATOS_CONEX!$I$7:$I$4000="Sí")*(((DATOS_CONEX!$G$7:$G$4000+($A23+1)-ABS(DATOS_CONEX!$G$7:$G$4000-($A23+1)))/2-(DATOS_CONEX!$F$7:$F$4000+$A23+ABS(DATOS_CONEX!$F$7:$F$4000-$A23))/2)+ABS(((DATOS_CONEX!$G$7:$G$4000+($A23+1)-ABS(DATOS_CONEX!$G$7:$G$4000-($A23+1)))/2-(DATOS_CONEX!$F$7:$F$4000+$A23+ABS(DATOS_CONEX!$F$7:$F$4000-$A23))/2)))/2)) -> 34.970139 | Y23: =IF($A23="","",-F23) -> 0
A24: =IF(15<=DAY(DATE(2026,$Z$4+1,1)-1),DATE(2026,$Z$4,15),"") -> 46280 | B24: =IF($A24="","",DAY($A24)) -> 15 | C24: =IF($A24="","",COUNTIFS(DATOS_CONEX!$F$7:$F$4000,"<="&$A24,DATOS_CONEX!$G$7:$G$4000,">"&$A24,DATOS_CONEX!$I$7:$I$4000,"Sí")) -> 38 | D24: =IF($A24="","",MAX(C24,_xlfn.MAXIFS(DATOS_CONEX!$L$7:$L$4000,DATOS_CONEX!$F$7:$F$4000,">="&$A24,DATOS_CONEX!$F$7:$F$4000,"<"&($A24+1)))) -> 44 | E24: =IF($A24="","",COUNTIFS(DATOS_CONEX!$F$7:$F$4000,">"&$A24,DATOS_CONEX!$F$7:$F$4000,"<"&($A24+1),DATOS_CONEX!$I$7:$I$4000,"Sí")) -> 7 | F24: =IF($A24="","",COUNTIFS(DATOS_CONEX!$G$7:$G$4000,">="&$A24,DATOS_CONEX!$G$7:$G$4000,"<"&($A24+1),DATOS_CONEX!$I$7:$I$4000,"Sí")) -> 1 | G24: =IF($A24="","",COUNTIFS(DATOS_CONEX!$R$7:$R$4000,"<="&$A24,DATOS_CONEX!$S$7:$S$4000,">="&$A24)) -> 1 | H24: =IF($A24="","",COUNTIFS(DATOS_CONEX!$F$7:$F$4000,"<"&($A24+1),DATOS_CONEX!$G$7:$G$4000,">"&$A24,DATOS_CONEX!$I$7:$I$4000,"Sí")) -> 45 | I24: =IF($A24="","",SUMPRODUCT((DATOS_CONEX!$I$7:$I$4000="Sí")*(((DATOS_CONEX!$G$7:$G$4000+($A24+1)-ABS(DATOS_CONEX!$G$7:$G$4000-($A24+1)))/2-(DATOS_CONEX!$F$7:$F$4000+$A24+ABS(DATOS_CONEX!$F$7:$F$4000-$A24))/2)+ABS(((DATOS_CONEX!$G$7:$G$4000+($A24+1)-ABS(DATOS_CONEX!$G$7:$G$4000-($A24+1)))/2-(DATOS_CONEX!$F$7:$F$4000+$A24+ABS(DATOS_CONEX!$F$7:$F$4000-$A24))/2)))/2)) -> 40.813889 | Y24: =IF($A24="","",-F24) -> -1
A25: =IF(16<=DAY(DATE(2026,$Z$4+1,1)-1),DATE(2026,$Z$4,16),"") -> 46281 | B25: =IF($A25="","",DAY($A25)) -> 16 | C25: =IF($A25="","",COUNTIFS(DATOS_CONEX!$F$7:$F$4000,"<="&$A25,DATOS_CONEX!$G$7:$G$4000,">"&$A25,DATOS_CONEX!$I$7:$I$4000,"Sí")) -> 44 | D25: =IF($A25="","",MAX(C25,_xlfn.MAXIFS(DATOS_CONEX!$L$7:$L$4000,DATOS_CONEX!$F$7:$F$4000,">="&$A25,DATOS_CONEX!$F$7:$F$4000,"<"&($A25+1)))) -> 45 | E25: =IF($A25="","",COUNTIFS(DATOS_CONEX!$F$7:$F$4000,">"&$A25,DATOS_CONEX!$F$7:$F$4000,"<"&($A25+1),DATOS_CONEX!$I$7:$I$4000,"Sí")) -> 1 | F25: =IF($A25="","",COUNTIFS(DATOS_CONEX!$G$7:$G$4000,">="&$A25,DATOS_CONEX!$G$7:$G$4000,"<"&($A25+1),DATOS_CONEX!$I$7:$I$4000,"Sí")) -> 0 | G25: =IF($A25="","",COUNTIFS(DATOS_CONEX!$R$7:$R$4000,"<="&$A25,DATOS_CONEX!$S$7:$S$4000,">="&$A25)) -> 1 | H25: =IF($A25="","",COUNTIFS(DATOS_CONEX!$F$7:$F$4000,"<"&($A25+1),DATOS_CONEX!$G$7:$G$4000,">"&$A25,DATOS_CONEX!$I$7:$I$4000,"Sí")) -> 45 | I25: =IF($A25="","",SUMPRODUCT((DATOS_CONEX!$I$7:$I$4000="Sí")*(((DATOS_CONEX!$G$7:$G$4000+($A25+1)-ABS(DATOS_CONEX!$G$7:$G$4000-($A25+1)))/2-(DATOS_CONEX!$F$7:$F$4000+$A25+ABS(DATOS_CONEX!$F$7:$F$4000-$A25))/2)+ABS(((DATOS_CONEX!$G$7:$G$4000+($A25+1)-ABS(DATOS_CONEX!$G$7:$G$4000-($A25+1)))/2-(DATOS_CONEX!$F$7:$F$4000+$A25+ABS(DATOS_CONEX!$F$7:$F$4000-$A25))/2)))/2)) -> 44.370833 | Y25: =IF($A25="","",-F25) -> 0
A26: =IF(17<=DAY(DATE(2026,$Z$4+1,1)-1),DATE(2026,$Z$4,17),"") -> 46282 | B26: =IF($A26="","",DAY($A26)) -> 17 | C26: =IF($A26="","",COUNTIFS(DATOS_CONEX!$F$7:$F$4000,"<="&$A26,DATOS_CONEX!$G$7:$G$4000,">"&$A26,DATOS_CONEX!$I$7:$I$4000,"Sí")) -> 45 | D26: =IF($A26="","",MAX(C26,_xlfn.MAXIFS(DATOS_CONEX!$L$7:$L$4000,DATOS_CONEX!$F$7:$F$4000,">="&$A26,DATOS_CONEX!$F$7:$F$4000,"<"&($A26+1)))) -> 209 | E26: =IF($A26="","",COUNTIFS(DATOS_CONEX!$F$7:$F$4000,">"&$A26,DATOS_CONEX!$F$7:$F$4000,"<"&($A26+1),DATOS_CONEX!$I$7:$I$4000,"Sí")) -> 165 | F26: =IF($A26="","",COUNTIFS(DATOS_CONEX!$G$7:$G$4000,">="&$A26,DATOS_CONEX!$G$7:$G$4000,"<"&($A26+1),DATOS_CONEX!$I$7:$I$4000,"Sí")) -> 19 | G26: =IF($A26="","",COUNTIFS(DATOS_CONEX!$R$7:$R$4000,"<="&$A26,DATOS_CONEX!$S$7:$S$4000,">="&$A26)) -> 4 | H26: =IF($A26="","",COUNTIFS(DATOS_CONEX!$F$7:$F$4000,"<"&($A26+1),DATOS_CONEX!$G$7:$G$4000,">"&$A26,DATOS_CONEX!$I$7:$I$4000,"Sí")) -> 210 | I26: =IF($A26="","",SUMPRODUCT((DATOS_CONEX!$I$7:$I$4000="Sí")*(((DATOS_CONEX!$G$7:$G$4000+($A26+1)-ABS(DATOS_CONEX!$G$7:$G$4000-($A26+1)))/2-(DATOS_CONEX!$F$7:$F$4000+$A26+ABS(DATOS_CONEX!$F$7:$F$4000-$A26))/2)+ABS(((DATOS_CONEX!$G$7:$G$4000+($A26+1)-ABS(DATOS_CONEX!$G$7:$G$4000-($A26+1)))/2-(DATOS_CONEX!$F$7:$F$4000+$A26+ABS(DATOS_CONEX!$F$7:$F$4000-$A26))/2)))/2)) -> 168.00278 | Y26: =IF($A26="","",-F26) -> -19
A27: =IF(18<=DAY(DATE(2026,$Z$4+1,1)-1),DATE(2026,$Z$4,18),"") -> 46283 | B27: =IF($A27="","",DAY($A27)) -> 18 | C27: =IF($A27="","",COUNTIFS(DATOS_CONEX!$F$7:$F$4000,"<="&$A27,DATOS_CONEX!$G$7:$G$4000,">"&$A27,DATOS_CONEX!$I$7:$I$4000,"Sí")) -> 191 | D27: =IF($A27="","",MAX(C27,_xlfn.MAXIFS(DATOS_CONEX!$L$7:$L$4000,DATOS_CONEX!$F$7:$F$4000,">="&$A27,DATOS_CONEX!$F$7:$F$4000,"<"&($A27+1)))) -> 191 | E27: =IF($A27="","",COUNTIFS(DATOS_CONEX!$F$7:$F$4000,">"&$A27,DATOS_CONEX!$F$7:$F$4000,"<"&($A27+1),DATOS_CONEX!$I$7:$I$4000,"Sí")) -> 0 | F27: =IF($A27="","",COUNTIFS(DATOS_CONEX!$G$7:$G$4000,">="&$A27,DATOS_CONEX!$G$7:$G$4000,"<"&($A27+1),DATOS_CONEX!$I$7:$I$4000,"Sí")) -> 60 | G27: =IF($A27="","",COUNTIFS(DATOS_CONEX!$R$7:$R$4000,"<="&$A27,DATOS_CONEX!$S$7:$S$4000,">="&$A27)) -> 4 | H27: =IF($A27="","",COUNTIFS(DATOS_CONEX!$F$7:$F$4000,"<"&($A27+1),DATOS_CONEX!$G$7:$G$4000,">"&$A27,DATOS_CONEX!$I$7:$I$4000,"Sí")) -> 191 | I27: =IF($A27="","",SUMPRODUCT((DATOS_CONEX!$I$7:$I$4000="Sí")*(((DATOS_CONEX!$G$7:$G$4000+($A27+1)-ABS(DATOS_CONEX!$G$7:$G$4000-($A27+1)))/2-(DATOS_CONEX!$F$7:$F$4000+$A27+ABS(DATOS_CONEX!$F$7:$F$4000-$A27))/2)+ABS(((DATOS_CONEX!$G$7:$G$4000+($A27+1)-ABS(DATOS_CONEX!$G$7:$G$4000-($A27+1)))/2-(DATOS_CONEX!$F$7:$F$4000+$A27+ABS(DATOS_CONEX!$F$7:$F$4000-$A27))/2)))/2)) -> 165.57361 | Y27: =IF($A27="","",-F27) -> -60
A28: =IF(19<=DAY(DATE(2026,$Z$4+1,1)-1),DATE(2026,$Z$4,19),"") -> 46284 | B28: =IF($A28="","",DAY($A28)) -> 19 | C28: =IF($A28="","",COUNTIFS(DATOS_CONEX!$F$7:$F$4000,"<="&$A28,DATOS_CONEX!$G$7:$G$4000,">"&$A28,DATOS_CONEX!$I$7:$I$4000,"Sí")) -> 131 | D28: =IF($A28="","",MAX(C28,_xlfn.MAXIFS(DATOS_CONEX!$L$7:$L$4000,DATOS_CONEX!$F$7:$F$4000,">="&$A28,DATOS_CONEX!$F$7:$F$4000,"<"&($A28+1)))) -> 131 | E28: =IF($A28="","",COUNTIFS(DATOS_CONEX!$F$7:$F$4000,">"&$A28,DATOS_CONEX!$F$7:$F$4000,"<"&($A28+1),DATOS_CONEX!$I$7:$I$4000,"Sí")) -> 6 | F28: =IF($A28="","",COUNTIFS(DATOS_CONEX!$G$7:$G$4000,">="&$A28,DATOS_CONEX!$G$7:$G$4000,"<"&($A28+1),DATOS_CONEX!$I$7:$I$4000,"Sí")) -> 125 | G28: =IF($A28="","",COUNTIFS(DATOS_CONEX!$R$7:$R$4000,"<="&$A28,DATOS_CONEX!$S$7:$S$4000,">="&$A28)) -> 3 | H28: =IF($A28="","",COUNTIFS(DATOS_CONEX!$F$7:$F$4000,"<"&($A28+1),DATOS_CONEX!$G$7:$G$4000,">"&$A28,DATOS_CONEX!$I$7:$I$4000,"Sí")) -> 137 | I28: =IF($A28="","",SUMPRODUCT((DATOS_CONEX!$I$7:$I$4000="Sí")*(((DATOS_CONEX!$G$7:$G$4000+($A28+1)-ABS(DATOS_CONEX!$G$7:$G$4000-($A28+1)))/2-(DATOS_CONEX!$F$7:$F$4000+$A28+ABS(DATOS_CONEX!$F$7:$F$4000-$A28))/2)+ABS(((DATOS_CONEX!$G$7:$G$4000+($A28+1)-ABS(DATOS_CONEX!$G$7:$G$4000-($A28+1)))/2-(DATOS_CONEX!$F$7:$F$4000+$A28+ABS(DATOS_CONEX!$F$7:$F$4000-$A28))/2)))/2)) -> 49.280556 | Y28: =IF($A28="","",-F28) -> -125
A29: =IF(20<=DAY(DATE(2026,$Z$4+1,1)-1),DATE(2026,$Z$4,20),"") -> 46285 | B29: =IF($A29="","",DAY($A29)) -> 20 | C29: =IF($A29="","",COUNTIFS(DATOS_CONEX!$F$7:$F$4000,"<="&$A29,DATOS_CONEX!$G$7:$G$4000,">"&$A29,DATOS_CONEX!$I$7:$I$4000,"Sí")) -> 12 | D29: =IF($A29="","",MAX(C29,_xlfn.MAXIFS(DATOS_CONEX!$L$7:$L$4000,DATOS_CONEX!$F$7:$F$4000,">="&$A29,DATOS_CONEX!$F$7:$F$4000,"<"&($A29+1)))) -> 12 | E29: =IF($A29="","",COUNTIFS(DATOS_CONEX!$F$7:$F$4000,">"&$A29,DATOS_CONEX!$F$7:$F$4000,"<"&($A29+1),DATOS_CONEX!$I$7:$I$4000,"Sí")) -> 0 | F29: =IF($A29="","",COUNTIFS(DATOS_CONEX!$G$7:$G$4000,">="&$A29,DATOS_CONEX!$G$7:$G$4000,"<"&($A29+1),DATOS_CONEX!$I$7:$I$4000,"Sí")) -> 2 | G29: =IF($A29="","",COUNTIFS(DATOS_CONEX!$R$7:$R$4000,"<="&$A29,DATOS_CONEX!$S$7:$S$4000,">="&$A29)) -> 1 | H29: =IF($A29="","",COUNTIFS(DATOS_CONEX!$F$7:$F$4000,"<"&($A29+1),DATOS_CONEX!$G$7:$G$4000,">"&$A29,DATOS_CONEX!$I$7:$I$4000,"Sí")) -> 12 | I29: =IF($A29="","",SUMPRODUCT((DATOS_CONEX!$I$7:$I$4000="Sí")*(((DATOS_CONEX!$G$7:$G$4000+($A29+1)-ABS(DATOS_CONEX!$G$7:$G$4000-($A29+1)))/2-(DATOS_CONEX!$F$7:$F$4000+$A29+ABS(DATOS_CONEX!$F$7:$F$4000-$A29))/2)+ABS(((DATOS_CONEX!$G$7:$G$4000+($A29+1)-ABS(DATOS_CONEX!$G$7:$G$4000-($A29+1)))/2-(DATOS_CONEX!$F$7:$F$4000+$A29+ABS(DATOS_CONEX!$F$7:$F$4000-$A29))/2)))/2)) -> 11.465278 | Y29: =IF($A29="","",-F29) -> -2
A30: =IF(21<=DAY(DATE(2026,$Z$4+1,1)-1),DATE(2026,$Z$4,21),"") -> 46286 | B30: =IF($A30="","",DAY($A30)) -> 21 | C30: =IF($A30="","",COUNTIFS(DATOS_CONEX!$F$7:$F$4000,"<="&$A30,DATOS_CONEX!$G$7:$G$4000,">"&$A30,DATOS_CONEX!$I$7:$I$4000,"Sí")) -> 10 | D30: =IF($A30="","",MAX(C30,_xlfn.MAXIFS(DATOS_CONEX!$L$7:$L$4000,DATOS_CONEX!$F$7:$F$4000,">="&$A30,DATOS_CONEX!$F$7:$F$4000,"<"&($A30+1)))) -> 29 | E30: =IF($A30="","",COUNTIFS(DATOS_CONEX!$F$7:$F$4000,">"&$A30,DATOS_CONEX!$F$7:$F$4000,"<"&($A30+1),DATOS_CONEX!$I$7:$I$4000,"Sí")) -> 19 | F30: =IF($A30="","",COUNTIFS(DATOS_CONEX!$G$7:$G$4000,">="&$A30,DATOS_CONEX!$G$7:$G$4000,"<"&($A30+1),DATOS_CONEX!$I$7:$I$4000,"Sí")) -> 0 | G30: =IF($A30="","",COUNTIFS(DATOS_CONEX!$R$7:$R$4000,"<="&$A30,DATOS_CONEX!$S$7:$S$4000,">="&$A30)) -> 1 | H30: =IF($A30="","",COUNTIFS(DATOS_CONEX!$F$7:$F$4000,"<"&($A30+1),DATOS_CONEX!$G$7:$G$4000,">"&$A30,DATOS_CONEX!$I$7:$I$4000,"Sí")) -> 29 | I30: =IF($A30="","",SUMPRODUCT((DATOS_CONEX!$I$7:$I$4000="Sí")*(((DATOS_CONEX!$G$7:$G$4000+($A30+1)-ABS(DATOS_CONEX!$G$7:$G$4000-($A30+1)))/2-(DATOS_CONEX!$F$7:$F$4000+$A30+ABS(DATOS_CONEX!$F$7:$F$4000-$A30))/2)+ABS(((DATOS_CONEX!$G$7:$G$4000+($A30+1)-ABS(DATOS_CONEX!$G$7:$G$4000-($A30+1)))/2-(DATOS_CONEX!$F$7:$F$4000+$A30+ABS(DATOS_CONEX!$F$7:$F$4000-$A30))/2)))/2)) -> 18.086806 | Y30: =IF($A30="","",-F30) -> 0
A31: =IF(22<=DAY(DATE(2026,$Z$4+1,1)-1),DATE(2026,$Z$4,22),"") -> 46287 | B31: =IF($A31="","",DAY($A31)) -> 22 | C31: =IF($A31="","",COUNTIFS(DATOS_CONEX!$F$7:$F$4000,"<="&$A31,DATOS_CONEX!$G$7:$G$4000,">"&$A31,DATOS_CONEX!$I$7:$I$4000,"Sí")) -> 29 | D31: =IF($A31="","",MAX(C31,_xlfn.MAXIFS(DATOS_CONEX!$L$7:$L$4000,DATOS_CONEX!$F$7:$F$4000,">="&$A31,DATOS_CONEX!$F$7:$F$4000,"<"&($A31+1)))) -> 29 | E31: =IF($A31="","",COUNTIFS(DATOS_CONEX!$F$7:$F$4000,">"&$A31,DATOS_CONEX!$F$7:$F$4000,"<"&($A31+1),DATOS_CONEX!$I$7:$I$4000,"Sí")) -> 0 | F31: =IF($A31="","",COUNTIFS(DATOS_CONEX!$G$7:$G$4000,">="&$A31,DATOS_CONEX!$G$7:$G$4000,"<"&($A31+1),DATOS_CONEX!$I$7:$I$4000,"Sí")) -> 0 | G31: =IF($A31="","",COUNTIFS(DATOS_CONEX!$R$7:$R$4000,"<="&$A31,DATOS_CONEX!$S$7:$S$4000,">="&$A31)) -> 1 | H31: =IF($A31="","",COUNTIFS(DATOS_CONEX!$F$7:$F$4000,"<"&($A31+1),DATOS_CONEX!$G$7:$G$4000,">"&$A31,DATOS_CONEX!$I$7:$I$4000,"Sí")) -> 29 | I31: =IF($A31="","",SUMPRODUCT((DATOS_CONEX!$I$7:$I$4000="Sí")*(((DATOS_CONEX!$G$7:$G$4000+($A31+1)-ABS(DATOS_CONEX!$G$7:$G$4000-($A31+1)))/2-(DATOS_CONEX!$F$7:$F$4000+$A31+ABS(DATOS_CONEX!$F$7:$F$4000-$A31))/2)+ABS(((DATOS_CONEX!$G$7:$G$4000+($A31+1)-ABS(DATOS_CONEX!$G$7:$G$4000-($A31+1)))/2-(DATOS_CONEX!$F$7:$F$4000+$A31+ABS(DATOS_CONEX!$F$7:$F$4000-$A31))/2)))/2)) -> 29 | Y31: =IF($A31="","",-F31) -> 0
A32: =IF(23<=DAY(DATE(2026,$Z$4+1,1)-1),DATE(2026,$Z$4,23),"") -> 46288 | B32: =IF($A32="","",DAY($A32)) -> 23 | C32: =IF($A32="","",COUNTIFS(DATOS_CONEX!$F$7:$F$4000,"<="&$A32,DATOS_CONEX!$G$7:$G$4000,">"&$A32,DATOS_CONEX!$I$7:$I$4000,"Sí")) -> 29 | D32: =IF($A32="","",MAX(C32,_xlfn.MAXIFS(DATOS_CONEX!$L$7:$L$4000,DATOS_CONEX!$F$7:$F$4000,">="&$A32,DATOS_CONEX!$F$7:$F$4000,"<"&($A32+1)))) -> 29 | E32: =IF($A32="","",COUNTIFS(DATOS_CONEX!$F$7:$F$4000,">"&$A32,DATOS_CONEX!$F$7:$F$4000,"<"&($A32+1),DATOS_CONEX!$I$7:$I$4000,"Sí")) -> 0 | F32: =IF($A32="","",COUNTIFS(DATOS_CONEX!$G$7:$G$4000,">="&$A32,DATOS_CONEX!$G$7:$G$4000,"<"&($A32+1),DATOS_CONEX!$I$7:$I$4000,"Sí")) -> 0 | G32: =IF($A32="","",COUNTIFS(DATOS_CONEX!$R$7:$R$4000,"<="&$A32,DATOS_CONEX!$S$7:$S$4000,">="&$A32)) -> 1 | H32: =IF($A32="","",COUNTIFS(DATOS_CONEX!$F$7:$F$4000,"<"&($A32+1),DATOS_CONEX!$G$7:$G$4000,">"&$A32,DATOS_CONEX!$I$7:$I$4000,"Sí")) -> 29 | I32: =IF($A32="","",SUMPRODUCT((DATOS_CONEX!$I$7:$I$4000="Sí")*(((DATOS_CONEX!$G$7:$G$4000+($A32+1)-ABS(DATOS_CONEX!$G$7:$G$4000-($A32+1)))/2-(DATOS_CONEX!$F$7:$F$4000+$A32+ABS(DATOS_CONEX!$F$7:$F$4000-$A32))/2)+ABS(((DATOS_CONEX!$G$7:$G$4000+($A32+1)-ABS(DATOS_CONEX!$G$7:$G$4000-($A32+1)))/2-(DATOS_CONEX!$F$7:$F$4000+$A32+ABS(DATOS_CONEX!$F$7:$F$4000-$A32))/2)))/2)) -> 29 | Y32: =IF($A32="","",-F32) -> 0
A33: =IF(24<=DAY(DATE(2026,$Z$4+1,1)-1),DATE(2026,$Z$4,24),"") -> 46289 | B33: =IF($A33="","",DAY($A33)) -> 24 | C33: =IF($A33="","",COUNTIFS(DATOS_CONEX!$F$7:$F$4000,"<="&$A33,DATOS_CONEX!$G$7:$G$4000,">"&$A33,DATOS_CONEX!$I$7:$I$4000,"Sí")) -> 29 | D33: =IF($A33="","",MAX(C33,_xlfn.MAXIFS(DATOS_CONEX!$L$7:$L$4000,DATOS_CONEX!$F$7:$F$4000,">="&$A33,DATOS_CONEX!$F$7:$F$4000,"<"&($A33+1)))) -> 114 | E33: =IF($A33="","",COUNTIFS(DATOS_CONEX!$F$7:$F$4000,">"&$A33,DATOS_CONEX!$F$7:$F$4000,"<"&($A33+1),DATOS_CONEX!$I$7:$I$4000,"Sí")) -> 85 | F33: =IF($A33="","",COUNTIFS(DATOS_CONEX!$G$7:$G$4000,">="&$A33,DATOS_CONEX!$G$7:$G$4000,"<"&($A33+1),DATOS_CONEX!$I$7:$I$4000,"Sí")) -> 0 | G33: =IF($A33="","",COUNTIFS(DATOS_CONEX!$R$7:$R$4000,"<="&$A33,DATOS_CONEX!$S$7:$S$4000,">="&$A33)) -> 3 | H33: =IF($A33="","",COUNTIFS(DATOS_CONEX!$F$7:$F$4000,"<"&($A33+1),DATOS_CONEX!$G$7:$G$4000,">"&$A33,DATOS_CONEX!$I$7:$I$4000,"Sí")) -> 114 | I33: =IF($A33="","",SUMPRODUCT((DATOS_CONEX!$I$7:$I$4000="Sí")*(((DATOS_CONEX!$G$7:$G$4000+($A33+1)-ABS(DATOS_CONEX!$G$7:$G$4000-($A33+1)))/2-(DATOS_CONEX!$F$7:$F$4000+$A33+ABS(DATOS_CONEX!$F$7:$F$4000-$A33))/2)+ABS(((DATOS_CONEX!$G$7:$G$4000+($A33+1)-ABS(DATOS_CONEX!$G$7:$G$4000-($A33+1)))/2-(DATOS_CONEX!$F$7:$F$4000+$A33+ABS(DATOS_CONEX!$F$7:$F$4000-$A33))/2)))/2)) -> 47 | Y33: =IF($A33="","",-F33) -> 0
A34: =IF(25<=DAY(DATE(2026,$Z$4+1,1)-1),DATE(2026,$Z$4,25),"") -> 46290 | B34: =IF($A34="","",DAY($A34)) -> 25 | C34: =IF($A34="","",COUNTIFS(DATOS_CONEX!$F$7:$F$4000,"<="&$A34,DATOS_CONEX!$G$7:$G$4000,">"&$A34,DATOS_CONEX!$I$7:$I$4000,"Sí")) -> 114 | D34: =IF($A34="","",MAX(C34,_xlfn.MAXIFS(DATOS_CONEX!$L$7:$L$4000,DATOS_CONEX!$F$7:$F$4000,">="&$A34,DATOS_CONEX!$F$7:$F$4000,"<"&($A34+1)))) -> 400 | E34: =IF($A34="","",COUNTIFS(DATOS_CONEX!$F$7:$F$4000,">"&$A34,DATOS_CONEX!$F$7:$F$4000,"<"&($A34+1),DATOS_CONEX!$I$7:$I$4000,"Sí")) -> 301 | F34: =IF($A34="","",COUNTIFS(DATOS_CONEX!$G$7:$G$4000,">="&$A34,DATOS_CONEX!$G$7:$G$4000,"<"&($A34+1),DATOS_CONEX!$I$7:$I$4000,"Sí")) -> 15 | G34: =IF($A34="","",COUNTIFS(DATOS_CONEX!$R$7:$R$4000,"<="&$A34,DATOS_CONEX!$S$7:$S$4000,">="&$A34)) -> 8 | H34: =IF($A34="","",COUNTIFS(DATOS_CONEX!$F$7:$F$4000,"<"&($A34+1),DATOS_CONEX!$G$7:$G$4000,">"&$A34,DATOS_CONEX!$I$7:$I$4000,"Sí")) -> 415 | I34: =IF($A34="","",SUMPRODUCT((DATOS_CONEX!$I$7:$I$4000="Sí")*(((DATOS_CONEX!$G$7:$G$4000+($A34+1)-ABS(DATOS_CONEX!$G$7:$G$4000-($A34+1)))/2-(DATOS_CONEX!$F$7:$F$4000+$A34+ABS(DATOS_CONEX!$F$7:$F$4000-$A34))/2)+ABS(((DATOS_CONEX!$G$7:$G$4000+($A34+1)-ABS(DATOS_CONEX!$G$7:$G$4000-($A34+1)))/2-(DATOS_CONEX!$F$7:$F$4000+$A34+ABS(DATOS_CONEX!$F$7:$F$4000-$A34))/2)))/2)) -> 246.97083 | Y34: =IF($A34="","",-F34) -> -15
A35: =IF(26<=DAY(DATE(2026,$Z$4+1,1)-1),DATE(2026,$Z$4,26),"") -> 46291 | B35: =IF($A35="","",DAY($A35)) -> 26 | C35: =IF($A35="","",COUNTIFS(DATOS_CONEX!$F$7:$F$4000,"<="&$A35,DATOS_CONEX!$G$7:$G$4000,">"&$A35,DATOS_CONEX!$I$7:$I$4000,"Sí")) -> 400 | D35: =IF($A35="","",MAX(C35,_xlfn.MAXIFS(DATOS_CONEX!$L$7:$L$4000,DATOS_CONEX!$F$7:$F$4000,">="&$A35,DATOS_CONEX!$F$7:$F$4000,"<"&($A35+1)))) -> 400 | E35: =IF($A35="","",COUNTIFS(DATOS_CONEX!$F$7:$F$4000,">"&$A35,DATOS_CONEX!$F$7:$F$4000,"<"&($A35+1),DATOS_CONEX!$I$7:$I$4000,"Sí")) -> 0 | F35: =IF($A35="","",COUNTIFS(DATOS_CONEX!$G$7:$G$4000,">="&$A35,DATOS_CONEX!$G$7:$G$4000,"<"&($A35+1),DATOS_CONEX!$I$7:$I$4000,"Sí")) -> 76 | G35: =IF($A35="","",COUNTIFS(DATOS_CONEX!$R$7:$R$4000,"<="&$A35,DATOS_CONEX!$S$7:$S$4000,">="&$A35)) -> 8 | H35: =IF($A35="","",COUNTIFS(DATOS_CONEX!$F$7:$F$4000,"<"&($A35+1),DATOS_CONEX!$G$7:$G$4000,">"&$A35,DATOS_CONEX!$I$7:$I$4000,"Sí")) -> 400 | I35: =IF($A35="","",SUMPRODUCT((DATOS_CONEX!$I$7:$I$4000="Sí")*(((DATOS_CONEX!$G$7:$G$4000+($A35+1)-ABS(DATOS_CONEX!$G$7:$G$4000-($A35+1)))/2-(DATOS_CONEX!$F$7:$F$4000+$A35+ABS(DATOS_CONEX!$F$7:$F$4000-$A35))/2)+ABS(((DATOS_CONEX!$G$7:$G$4000+($A35+1)-ABS(DATOS_CONEX!$G$7:$G$4000-($A35+1)))/2-(DATOS_CONEX!$F$7:$F$4000+$A35+ABS(DATOS_CONEX!$F$7:$F$4000-$A35))/2)))/2)) -> 369.46389 | Y35: =IF($A35="","",-F35) -> -76
A36: =IF(27<=DAY(DATE(2026,$Z$4+1,1)-1),DATE(2026,$Z$4,27),"") -> 46292 | B36: =IF($A36="","",DAY($A36)) -> 27 | C36: =IF($A36="","",COUNTIFS(DATOS_CONEX!$F$7:$F$4000,"<="&$A36,DATOS_CONEX!$G$7:$G$4000,">"&$A36,DATOS_CONEX!$I$7:$I$4000,"Sí")) -> 324 | D36: =IF($A36="","",MAX(C36,_xlfn.MAXIFS(DATOS_CONEX!$L$7:$L$4000,DATOS_CONEX!$F$7:$F$4000,">="&$A36,DATOS_CONEX!$F$7:$F$4000,"<"&($A36+1)))) -> 324 | E36: =IF($A36="","",COUNTIFS(DATOS_CONEX!$F$7:$F$4000,">"&$A36,DATOS_CONEX!$F$7:$F$4000,"<"&($A36+1),DATOS_CONEX!$I$7:$I$4000,"Sí")) -> 0 | F36: =IF($A36="","",COUNTIFS(DATOS_CONEX!$G$7:$G$4000,">="&$A36,DATOS_CONEX!$G$7:$G$4000,"<"&($A36+1),DATOS_CONEX!$I$7:$I$4000,"Sí")) -> 323 | G36: =IF($A36="","",COUNTIFS(DATOS_CONEX!$R$7:$R$4000,"<="&$A36,DATOS_CONEX!$S$7:$S$4000,">="&$A36)) -> 4 | H36: =IF($A36="","",COUNTIFS(DATOS_CONEX!$F$7:$F$4000,"<"&($A36+1),DATOS_CONEX!$G$7:$G$4000,">"&$A36,DATOS_CONEX!$I$7:$I$4000,"Sí")) -> 324 | I36: =IF($A36="","",SUMPRODUCT((DATOS_CONEX!$I$7:$I$4000="Sí")*(((DATOS_CONEX!$G$7:$G$4000+($A36+1)-ABS(DATOS_CONEX!$G$7:$G$4000-($A36+1)))/2-(DATOS_CONEX!$F$7:$F$4000+$A36+ABS(DATOS_CONEX!$F$7:$F$4000-$A36))/2)+ABS(((DATOS_CONEX!$G$7:$G$4000+($A36+1)-ABS(DATOS_CONEX!$G$7:$G$4000-($A36+1)))/2-(DATOS_CONEX!$F$7:$F$4000+$A36+ABS(DATOS_CONEX!$F$7:$F$4000-$A36))/2)))/2)) -> 169.83681 | Y36: =IF($A36="","",-F36) -> -323
A37: =IF(28<=DAY(DATE(2026,$Z$4+1,1)-1),DATE(2026,$Z$4,28),"") -> 46293 | B37: =IF($A37="","",DAY($A37)) -> 28 | C37: =IF($A37="","",COUNTIFS(DATOS_CONEX!$F$7:$F$4000,"<="&$A37,DATOS_CONEX!$G$7:$G$4000,">"&$A37,DATOS_CONEX!$I$7:$I$4000,"Sí")) -> 1 | D37: =IF($A37="","",MAX(C37,_xlfn.MAXIFS(DATOS_CONEX!$L$7:$L$4000,DATOS_CONEX!$F$7:$F$4000,">="&$A37,DATOS_CONEX!$F$7:$F$4000,"<"&($A37+1)))) -> 2 | E37: =IF($A37="","",COUNTIFS(DATOS_CONEX!$F$7:$F$4000,">"&$A37,DATOS_CONEX!$F$7:$F$4000,"<"&($A37+1),DATOS_CONEX!$I$7:$I$4000,"Sí")) -> 1 | F37: =IF($A37="","",COUNTIFS(DATOS_CONEX!$G$7:$G$4000,">="&$A37,DATOS_CONEX!$G$7:$G$4000,"<"&($A37+1),DATOS_CONEX!$I$7:$I$4000,"Sí")) -> 0 | G37: =IF($A37="","",COUNTIFS(DATOS_CONEX!$R$7:$R$4000,"<="&$A37,DATOS_CONEX!$S$7:$S$4000,">="&$A37)) -> 1 | H37: =IF($A37="","",COUNTIFS(DATOS_CONEX!$F$7:$F$4000,"<"&($A37+1),DATOS_CONEX!$G$7:$G$4000,">"&$A37,DATOS_CONEX!$I$7:$I$4000,"Sí")) -> 2 | I37: =IF($A37="","",SUMPRODUCT((DATOS_CONEX!$I$7:$I$4000="Sí")*(((DATOS_CONEX!$G$7:$G$4000+($A37+1)-ABS(DATOS_CONEX!$G$7:$G$4000-($A37+1)))/2-(DATOS_CONEX!$F$7:$F$4000+$A37+ABS(DATOS_CONEX!$F$7:$F$4000-$A37))/2)+ABS(((DATOS_CONEX!$G$7:$G$4000+($A37+1)-ABS(DATOS_CONEX!$G$7:$G$4000-($A37+1)))/2-(DATOS_CONEX!$F$7:$F$4000+$A37+ABS(DATOS_CONEX!$F$7:$F$4000-$A37))/2)))/2)) -> 1.4326389 | Y37: =IF($A37="","",-F37) -> 0
A38: =IF(29<=DAY(DATE(2026,$Z$4+1,1)-1),DATE(2026,$Z$4,29),"") -> 46294 | B38: =IF($A38="","",DAY($A38)) -> 29 | C38: =IF($A38="","",COUNTIFS(DATOS_CONEX!$F$7:$F$4000,"<="&$A38,DATOS_CONEX!$G$7:$G$4000,">"&$A38,DATOS_CONEX!$I$7:$I$4000,"Sí")) -> 2 | D38: =IF($A38="","",MAX(C38,_xlfn.MAXIFS(DATOS_CONEX!$L$7:$L$4000,DATOS_CONEX!$F$7:$F$4000,">="&$A38,DATOS_CONEX!$F$7:$F$4000,"<"&($A38+1)))) -> 2 | E38: =IF($A38="","",COUNTIFS(DATOS_CONEX!$F$7:$F$4000,">"&$A38,DATOS_CONEX!$F$7:$F$4000,"<"&($A38+1),DATOS_CONEX!$I$7:$I$4000,"Sí")) -> 0 | F38: =IF($A38="","",COUNTIFS(DATOS_CONEX!$G$7:$G$4000,">="&$A38,DATOS_CONEX!$G$7:$G$4000,"<"&($A38+1),DATOS_CONEX!$I$7:$I$4000,"Sí")) -> 1 | G38: =IF($A38="","",COUNTIFS(DATOS_CONEX!$R$7:$R$4000,"<="&$A38,DATOS_CONEX!$S$7:$S$4000,">="&$A38)) -> 1 | H38: =IF($A38="","",COUNTIFS(DATOS_CONEX!$F$7:$F$4000,"<"&($A38+1),DATOS_CONEX!$G$7:$G$4000,">"&$A38,DATOS_CONEX!$I$7:$I$4000,"Sí")) -> 2 | I38: =IF($A38="","",SUMPRODUCT((DATOS_CONEX!$I$7:$I$4000="Sí")*(((DATOS_CONEX!$G$7:$G$4000+($A38+1)-ABS(DATOS_CONEX!$G$7:$G$4000-($A38+1)))/2-(DATOS_CONEX!$F$7:$F$4000+$A38+ABS(DATOS_CONEX!$F$7:$F$4000-$A38))/2)+ABS(((DATOS_CONEX!$G$7:$G$4000+($A38+1)-ABS(DATOS_CONEX!$G$7:$G$4000-($A38+1)))/2-(DATOS_CONEX!$F$7:$F$4000+$A38+ABS(DATOS_CONEX!$F$7:$F$4000-$A38))/2)))/2)) -> 1.5743056 | Y38: =IF($A38="","",-F38) -> -1
A39: =IF(30<=DAY(DATE(2026,$Z$4+1,1)-1),DATE(2026,$Z$4,30),"") -> 46295 | B39: =IF($A39="","",DAY($A39)) -> 30 | C39: =IF($A39="","",COUNTIFS(DATOS_CONEX!$F$7:$F$4000,"<="&$A39,DATOS_CONEX!$G$7:$G$4000,">"&$A39,DATOS_CONEX!$I$7:$I$4000,"Sí")) -> 1 | D39: =IF($A39="","",MAX(C39,_xlfn.MAXIFS(DATOS_CONEX!$L$7:$L$4000,DATOS_CONEX!$F$7:$F$4000,">="&$A39,DATOS_CONEX!$F$7:$F$4000,"<"&($A39+1)))) -> 1 | E39: =IF($A39="","",COUNTIFS(DATOS_CONEX!$F$7:$F$4000,">"&$A39,DATOS_CONEX!$F$7:$F$4000,"<"&($A39+1),DATOS_CONEX!$I$7:$I$4000,"Sí")) -> 0 | F39: =IF($A39="","",COUNTIFS(DATOS_CONEX!$G$7:$G$4000,">="&$A39,DATOS_CONEX!$G$7:$G$4000,"<"&($A39+1),DATOS_CONEX!$I$7:$I$4000,"Sí")) -> 1 | G39: =IF($A39="","",COUNTIFS(DATOS_CONEX!$R$7:$R$4000,"<="&$A39,DATOS_CONEX!$S$7:$S$4000,">="&$A39)) -> 1 | H39: =IF($A39="","",COUNTIFS(DATOS_CONEX!$F$7:$F$4000,"<"&($A39+1),DATOS_CONEX!$G$7:$G$4000,">"&$A39,DATOS_CONEX!$I$7:$I$4000,"Sí")) -> 1 | I39: =IF($A39="","",SUMPRODUCT((DATOS_CONEX!$I$7:$I$4000="Sí")*(((DATOS_CONEX!$G$7:$G$4000+($A39+1)-ABS(DATOS_CONEX!$G$7:$G$4000-($A39+1)))/2-(DATOS_CONEX!$F$7:$F$4000+$A39+ABS(DATOS_CONEX!$F$7:$F$4000-$A39))/2)+ABS(((DATOS_CONEX!$G$7:$G$4000+($A39+1)-ABS(DATOS_CONEX!$G$7:$G$4000-($A39+1)))/2-(DATOS_CONEX!$F$7:$F$4000+$A39+ABS(DATOS_CONEX!$F$7:$F$4000-$A39))/2)))/2)) -> 0.98819444 | Y39: =IF($A39="","",-F39) -> -1
A40: =IF(31<=DAY(DATE(2026,$Z$4+1,1)-1),DATE(2026,$Z$4,31),"") | B40: =IF($A40="","",DAY($A40)) | C40: =IF($A40="","",COUNTIFS(DATOS_CONEX!$F$7:$F$4000,"<="&$A40,DATOS_CONEX!$G$7:$G$4000,">"&$A40,DATOS_CONEX!$I$7:$I$4000,"Sí")) | D40: =IF($A40="","",MAX(C40,_xlfn.MAXIFS(DATOS_CONEX!$L$7:$L$4000,DATOS_CONEX!$F$7:$F$4000,">="&$A40,DATOS_CONEX!$F$7:$F$4000,"<"&($A40+1)))) | E40: =IF($A40="","",COUNTIFS(DATOS_CONEX!$F$7:$F$4000,">"&$A40,DATOS_CONEX!$F$7:$F$4000,"<"&($A40+1),DATOS_CONEX!$I$7:$I$4000,"Sí")) | F40: =IF($A40="","",COUNTIFS(DATOS_CONEX!$G$7:$G$4000,">="&$A40,DATOS_CONEX!$G$7:$G$4000,"<"&($A40+1),DATOS_CONEX!$I$7:$I$4000,"Sí")) | G40: =IF($A40="","",COUNTIFS(DATOS_CONEX!$R$7:$R$4000,"<="&$A40,DATOS_CONEX!$S$7:$S$4000,">="&$A40)) | H40: =IF($A40="","",COUNTIFS(DATOS_CONEX!$F$7:$F$4000,"<"&($A40+1),DATOS_CONEX!$G$7:$G$4000,">"&$A40,DATOS_CONEX!$I$7:$I$4000,"Sí")) | I40: =IF($A40="","",SUMPRODUCT((DATOS_CONEX!$I$7:$I$4000="Sí")*(((DATOS_CONEX!$G$7:$G$4000+($A40+1)-ABS(DATOS_CONEX!$G$7:$G$4000-($A40+1)))/2-(DATOS_CONEX!$F$7:$F$4000+$A40+ABS(DATOS_CONEX!$F$7:$F$4000-$A40))/2)+ABS(((DATOS_CONEX!$G$7:$G$4000+($A40+1)-ABS(DATOS_CONEX!$G$7:$G$4000-($A40+1)))/2-(DATOS_CONEX!$F$7:$F$4000+$A40+ABS(DATOS_CONEX!$F$7:$F$4000-$A40))/2)))/2)) | Y40: =IF($A40="","",-F40)
A41: MES | C41: =IFERROR(AVERAGE(C10:C40),"") -> 102.46667 | D41: =MAX(D10:D40) -> 400 | E41: =SUM(E10:E40) -> 1113 | F41: =SUM(F10:F40) -> 1146 | G41: =MAX(G10:G40) -> 8 | H41: =SUM(H10:H40) -> 4187 | I41: =SUM(I10:I40) -> 3167.7028
A42: Fila MES: C = promedio a las 00:00; D y G = máximo del mes; E, F, H, I = suma del mes. H = reefers que estuvieron enchufados en algún momento del día; I = horas reales conectadas ÷ 24.
A44: RESUMEN ANUAL
A45: Mes | B45: EDP | C45: Reefers EDP (válidos) | D45: Máx. simultáneo | E45: Fecha / hora del máx. | F45: Nave al máx. | G45: Promedio en paralelo | H45: Reefer-días
A46: Enero | B46: =IF(COUNTIF(DATOS_CONEX!$B$7:$B$4000,A46)>0,"Cargado",IF(DATE(2026,1,1)>TODAY(),"","Falta EDP")) -> Cargado | C46: =IF(COUNTIFS(DATOS_CONEX!$G$7:$G$4000,">="&DATE(2026,1,1),DATOS_CONEX!$G$7:$G$4000,"<"&DATE(2026,2,1),DATOS_CONEX!$I$7:$I$4000,"Sí")=0,"",COUNTIFS(DATOS_CONEX!$G$7:$G$4000,">="&DATE(2026,1,1),DATOS_CONEX!$G$7:$G$4000,"<"&DATE(2026,2,1),DATOS_CONEX!$I$7:$I$4000,"Sí")) -> 81 | D46: =IF(C46="","",MAX(_xlfn.MAXIFS(DATOS_CONEX!$L$7:$L$4000,DATOS_CONEX!$F$7:$F$4000,">="&DATE(2026,1,1),DATOS_CONEX!$F$7:$F$4000,"<"&DATE(2026,2,1)),COUNTIFS(DATOS_CONEX!$F$7:$F$4000,"<="&DATE(2026,1,1),DATOS_CONEX!$G$7:$G$4000,">"&DATE(2026,1,1),DATOS_CONEX!$I$7:$I$4000,"Sí"))) -> 29 | E46: =IF(D46="","",IFERROR(INDEX(DATOS_CONEX!$F$7:$F$4000,MATCH(A46&"|"&D46,DATOS_CONEX!$N$7:$N$4000,0)),"Inicio de mes")) -> 46046.743 | F46: =IF(D46="","",IFERROR(INDEX(DATOS_CONEX!$C$7:$C$4000,MATCH(A46&"|"&D46,DATOS_CONEX!$N$7:$N$4000,0)),"-")) -> HMM BLESSING | G46: =IF(C46="","",SUMPRODUCT((DATOS_CONEX!$I$7:$I$4000="Sí")*(((DATOS_CONEX!$G$7:$G$4000+DATE(2026,2,1)-ABS(DATOS_CONEX!$G$7:$G$4000-DATE(2026,2,1)))/2-(DATOS_CONEX!$F$7:$F$4000+DATE(2026,1,1)+ABS(DATOS_CONEX!$F$7:$F$4000-DATE(2026,1,1)))/2)+ABS(((DATOS_CONEX!$G$7:$G$4000+DATE(2026,2,1)-ABS(DATOS_CONEX!$G$7:$G$4000-DATE(2026,2,1)))/2-(DATOS_CONEX!$F$7:$F$4000+DATE(2026,1,1)+ABS(DATOS_CONEX!$F$7:$F$4000-DATE(2026,1,1)))/2)))/2)/(DATE(2026,2,1)-DATE(2026,1,1))) -> 15.796953 | H46: =IF(C46="","",SUMPRODUCT((DATOS_CONEX!$I$7:$I$4000="Sí")*(((DATOS_CONEX!$G$7:$G$4000+DATE(2026,2,1)-ABS(DATOS_CONEX!$G$7:$G$4000-DATE(2026,2,1)))/2-(DATOS_CONEX!$F$7:$F$4000+DATE(2026,1,1)+ABS(DATOS_CONEX!$F$7:$F$4000-DATE(2026,1,1)))/2)+ABS(((DATOS_CONEX!$G$7:$G$4000+DATE(2026,2,1)-ABS(DATOS_CONEX!$G$7:$G$4000-DATE(2026,2,1)))/2-(DATOS_CONEX!$F$7:$F$4000+DATE(2026,1,1)+ABS(DATOS_CONEX!$F$7:$F$4000-DATE(2026,1,1)))/2)))/2)) -> 489.70556
A47: Febrero | B47: =IF(COUNTIF(DATOS_CONEX!$B$7:$B$4000,A47)>0,"Cargado",IF(DATE(2026,2,1)>TODAY(),"","Falta EDP")) -> Cargado | C47: =IF(COUNTIFS(DATOS_CONEX!$G$7:$G$4000,">="&DATE(2026,2,1),DATOS_CONEX!$G$7:$G$4000,"<"&DATE(2026,3,1),DATOS_CONEX!$I$7:$I$4000,"Sí")=0,"",COUNTIFS(DATOS_CONEX!$G$7:$G$4000,">="&DATE(2026,2,1),DATOS_CONEX!$G$7:$G$4000,"<"&DATE(2026,3,1),DATOS_CONEX!$I$7:$I$4000,"Sí")) -> 58 | D47: =IF(C47="","",MAX(_xlfn.MAXIFS(DATOS_CONEX!$L$7:$L$4000,DATOS_CONEX!$F$7:$F$4000,">="&DATE(2026,2,1),DATOS_CONEX!$F$7:$F$4000,"<"&DATE(2026,3,1)),COUNTIFS(DATOS_CONEX!$F$7:$F$4000,"<="&DATE(2026,2,1),DATOS_CONEX!$G$7:$G$4000,">"&DATE(2026,2,1),DATOS_CONEX!$I$7:$I$4000,"Sí"))) -> 25 | E47: =IF(D47="","",IFERROR(INDEX(DATOS_CONEX!$F$7:$F$4000,MATCH(A47&"|"&D47,DATOS_CONEX!$N$7:$N$4000,0)),"Inicio de mes")) -> 46069 | F47: =IF(D47="","",IFERROR(INDEX(DATOS_CONEX!$C$7:$C$4000,MATCH(A47&"|"&D47,DATOS_CONEX!$N$7:$N$4000,0)),"-")) -> BUENAVENTURA EXPRESS | G47: =IF(C47="","",SUMPRODUCT((DATOS_CONEX!$I$7:$I$4000="Sí")*(((DATOS_CONEX!$G$7:$G$4000+DATE(2026,3,1)-ABS(DATOS_CONEX!$G$7:$G$4000-DATE(2026,3,1)))/2-(DATOS_CONEX!$F$7:$F$4000+DATE(2026,2,1)+ABS(DATOS_CONEX!$F$7:$F$4000-DATE(2026,2,1)))/2)+ABS(((DATOS_CONEX!$G$7:$G$4000+DATE(2026,3,1)-ABS(DATOS_CONEX!$G$7:$G$4000-DATE(2026,3,1)))/2-(DATOS_CONEX!$F$7:$F$4000+DATE(2026,2,1)+ABS(DATOS_CONEX!$F$7:$F$4000-DATE(2026,2,1)))/2)))/2)/(DATE(2026,3,1)-DATE(2026,2,1))) -> 15.759127 | H47: =IF(C47="","",SUMPRODUCT((DATOS_CONEX!$I$7:$I$4000="Sí")*(((DATOS_CONEX!$G$7:$G$4000+DATE(2026,3,1)-ABS(DATOS_CONEX!$G$7:$G$4000-DATE(2026,3,1)))/2-(DATOS_CONEX!$F$7:$F$4000+DATE(2026,2,1)+ABS(DATOS_CONEX!$F$7:$F$4000-DATE(2026,2,1)))/2)+ABS(((DATOS_CONEX!$G$7:$G$4000+DATE(2026,3,1)-ABS(DATOS_CONEX!$G$7:$G$4000-DATE(2026,3,1)))/2-(DATOS_CONEX!$F$7:$F$4000+DATE(2026,2,1)+ABS(DATOS_CONEX!$F$7:$F$4000-DATE(2026,2,1)))/2)))/2)) -> 441.25556
A48: Marzo | B48: =IF(COUNTIF(DATOS_CONEX!$B$7:$B$4000,A48)>0,"Cargado",IF(DATE(2026,3,1)>TODAY(),"","Falta EDP")) -> Cargado | C48: =IF(COUNTIFS(DATOS_CONEX!$G$7:$G$4000,">="&DATE(2026,3,1),DATOS_CONEX!$G$7:$G$4000,"<"&DATE(2026,4,1),DATOS_CONEX!$I$7:$I$4000,"Sí")=0,"",COUNTIFS(DATOS_CONEX!$G$7:$G$4000,">="&DATE(2026,3,1),DATOS_CONEX!$G$7:$G$4000,"<"&DATE(2026,4,1),DATOS_CONEX!$I$7:$I$4000,"Sí")) -> 74 | D48: =IF(C48="","",MAX(_xlfn.MAXIFS(DATOS_CONEX!$L$7:$L$4000,DATOS_CONEX!$F$7:$F$4000,">="&DATE(2026,3,1),DATOS_CONEX!$F$7:$F$4000,"<"&DATE(2026,4,1)),COUNTIFS(DATOS_CONEX!$F$7:$F$4000,"<="&DATE(2026,3,1),DATOS_CONEX!$G$7:$G$4000,">"&DATE(2026,3,1),DATOS_CONEX!$I$7:$I$4000,"Sí"))) -> 35 | E48: =IF(D48="","",IFERROR(INDEX(DATOS_CONEX!$F$7:$F$4000,MATCH(A48&"|"&D48,DATOS_CONEX!$N$7:$N$4000,0)),"Inicio de mes")) -> 46097.605 | F48: =IF(D48="","",IFERROR(INDEX(DATOS_CONEX!$C$7:$C$4000,MATCH(A48&"|"&D48,DATOS_CONEX!$N$7:$N$4000,0)),"-")) -> ONE SINCERITY | G48: =IF(C48="","",SUMPRODUCT((DATOS_CONEX!$I$7:$I$4000="Sí")*(((DATOS_CONEX!$G$7:$G$4000+DATE(2026,4,1)-ABS(DATOS_CONEX!$G$7:$G$4000-DATE(2026,4,1)))/2-(DATOS_CONEX!$F$7:$F$4000+DATE(2026,3,1)+ABS(DATOS_CONEX!$F$7:$F$4000-DATE(2026,3,1)))/2)+ABS(((DATOS_CONEX!$G$7:$G$4000+DATE(2026,4,1)-ABS(DATOS_CONEX!$G$7:$G$4000-DATE(2026,4,1)))/2-(DATOS_CONEX!$F$7:$F$4000+DATE(2026,3,1)+ABS(DATOS_CONEX!$F$7:$F$4000-DATE(2026,3,1)))/2)))/2)/(DATE(2026,4,1)-DATE(2026,3,1))) -> 16.706228 | H48: =IF(C48="","",SUMPRODUCT((DATOS_CONEX!$I$7:$I$4000="Sí")*(((DATOS_CONEX!$G$7:$G$4000+DATE(2026,4,1)-ABS(DATOS_CONEX!$G$7:$G$4000-DATE(2026,4,1)))/2-(DATOS_CONEX!$F$7:$F$4000+DATE(2026,3,1)+ABS(DATOS_CONEX!$F$7:$F$4000-DATE(2026,3,1)))/2)+ABS(((DATOS_CONEX!$G$7:$G$4000+DATE(2026,4,1)-ABS(DATOS_CONEX!$G$7:$G$4000-DATE(2026,4,1)))/2-(DATOS_CONEX!$F$7:$F$4000+DATE(2026,3,1)+ABS(DATOS_CONEX!$F$7:$F$4000-DATE(2026,3,1)))/2)))/2)) -> 517.89306
A49: Abril | B49: =IF(COUNTIF(DATOS_CONEX!$B$7:$B$4000,A49)>0,"Cargado",IF(DATE(2026,4,1)>TODAY(),"","Falta EDP")) -> Cargado | C49: =IF(COUNTIFS(DATOS_CONEX!$G$7:$G$4000,">="&DATE(2026,4,1),DATOS_CONEX!$G$7:$G$4000,"<"&DATE(2026,5,1),DATOS_CONEX!$I$7:$I$4000,"Sí")=0,"",COUNTIFS(DATOS_CONEX!$G$7:$G$4000,">="&DATE(2026,4,1),DATOS_CONEX!$G$7:$G$4000,"<"&DATE(2026,5,1),DATOS_CONEX!$I$7:$I$4000,"Sí")) -> 26 | D49: =IF(C49="","",MAX(_xlfn.MAXIFS(DATOS_CONEX!$L$7:$L$4000,DATOS_CONEX!$F$7:$F$4000,">="&DATE(2026,4,1),DATOS_CONEX!$F$7:$F$4000,"<"&DATE(2026,5,1)),COUNTIFS(DATOS_CONEX!$F$7:$F$4000,"<="&DATE(2026,4,1),DATOS_CONEX!$G$7:$G$4000,">"&DATE(2026,4,1),DATOS_CONEX!$I$7:$I$4000,"Sí"))) -> 16 | E49: =IF(D49="","",IFERROR(INDEX(DATOS_CONEX!$F$7:$F$4000,MATCH(A49&"|"&D49,DATOS_CONEX!$N$7:$N$4000,0)),"Inicio de mes")) -> 46142.519 | F49: =IF(D49="","",IFERROR(INDEX(DATOS_CONEX!$C$7:$C$4000,MATCH(A49&"|"&D49,DATOS_CONEX!$N$7:$N$4000,0)),"-")) -> ITAJAI EXPRESS | G49: =IF(C49="","",SUMPRODUCT((DATOS_CONEX!$I$7:$I$4000="Sí")*(((DATOS_CONEX!$G$7:$G$4000+DATE(2026,5,1)-ABS(DATOS_CONEX!$G$7:$G$4000-DATE(2026,5,1)))/2-(DATOS_CONEX!$F$7:$F$4000+DATE(2026,4,1)+ABS(DATOS_CONEX!$F$7:$F$4000-DATE(2026,4,1)))/2)+ABS(((DATOS_CONEX!$G$7:$G$4000+DATE(2026,5,1)-ABS(DATOS_CONEX!$G$7:$G$4000-DATE(2026,5,1)))/2-(DATOS_CONEX!$F$7:$F$4000+DATE(2026,4,1)+ABS(DATOS_CONEX!$F$7:$F$4000-DATE(2026,4,1)))/2)))/2)/(DATE(2026,5,1)-DATE(2026,4,1))) -> 6.31125 | H49: =IF(C49="","",SUMPRODUCT((DATOS_CONEX!$I$7:$I$4000="Sí")*(((DATOS_CONEX!$G$7:$G$4000+DATE(2026,5,1)-ABS(DATOS_CONEX!$G$7:$G$4000-DATE(2026,5,1)))/2-(DATOS_CONEX!$F$7:$F$4000+DATE(2026,4,1)+ABS(DATOS_CONEX!$F$7:$F$4000-DATE(2026,4,1)))/2)+ABS(((DATOS_CONEX!$G$7:$G$4000+DATE(2026,5,1)-ABS(DATOS_CONEX!$G$7:$G$4000-DATE(2026,5,1)))/2-(DATOS_CONEX!$F$7:$F$4000+DATE(2026,4,1)+ABS(DATOS_CONEX!$F$7:$F$4000-DATE(2026,4,1)))/2)))/2)) -> 189.3375
A50: Mayo | B50: =IF(COUNTIF(DATOS_CONEX!$B$7:$B$4000,A50)>0,"Cargado",IF(DATE(2026,5,1)>TODAY(),"","Falta EDP")) -> Cargado | C50: =IF(COUNTIFS(DATOS_CONEX!$G$7:$G$4000,">="&DATE(2026,5,1),DATOS_CONEX!$G$7:$G$4000,"<"&DATE(2026,6,1),DATOS_CONEX!$I$7:$I$4000,"Sí")=0,"",COUNTIFS(DATOS_CONEX!$G$7:$G$4000,">="&DATE(2026,5,1),DATOS_CONEX!$G$7:$G$4000,"<"&DATE(2026,6,1),DATOS_CONEX!$I$7:$I$4000,"Sí")) -> 54 | D50: =IF(C50="","",MAX(_xlfn.MAXIFS(DATOS_CONEX!$L$7:$L$4000,DATOS_CONEX!$F$7:$F$4000,">="&DATE(2026,5,1),DATOS_CONEX!$F$7:$F$4000,"<"&DATE(2026,6,1)),COUNTIFS(DATOS_CONEX!$F$7:$F$4000,"<="&DATE(2026,5,1),DATOS_CONEX!$G$7:$G$4000,">"&DATE(2026,5,1),DATOS_CONEX!$I$7:$I$4000,"Sí"))) -> 21 | E50: =IF(D50="","",IFERROR(INDEX(DATOS_CONEX!$F$7:$F$4000,MATCH(A50&"|"&D50,DATOS_CONEX!$N$7:$N$4000,0)),"Inicio de mes")) -> 46144.541 | F50: =IF(D50="","",IFERROR(INDEX(DATOS_CONEX!$C$7:$C$4000,MATCH(A50&"|"&D50,DATOS_CONEX!$N$7:$N$4000,0)),"-")) -> RIO JANEIRO EXPRESS | G50: =IF(C50="","",SUMPRODUCT((DATOS_CONEX!$I$7:$I$4000="Sí")*(((DATOS_CONEX!$G$7:$G$4000+DATE(2026,6,1)-ABS(DATOS_CONEX!$G$7:$G$4000-DATE(2026,6,1)))/2-(DATOS_CONEX!$F$7:$F$4000+DATE(2026,5,1)+ABS(DATOS_CONEX!$F$7:$F$4000-DATE(2026,5,1)))/2)+ABS(((DATOS_CONEX!$G$7:$G$4000+DATE(2026,6,1)-ABS(DATOS_CONEX!$G$7:$G$4000-DATE(2026,6,1)))/2-(DATOS_CONEX!$F$7:$F$4000+DATE(2026,5,1)+ABS(DATOS_CONEX!$F$7:$F$4000-DATE(2026,5,1)))/2)))/2)/(DATE(2026,6,1)-DATE(2026,5,1))) -> 8.8870296 | H50: =IF(C50="","",SUMPRODUCT((DATOS_CONEX!$I$7:$I$4000="Sí")*(((DATOS_CONEX!$G$7:$G$4000+DATE(2026,6,1)-ABS(DATOS_CONEX!$G$7:$G$4000-DATE(2026,6,1)))/2-(DATOS_CONEX!$F$7:$F$4000+DATE(2026,5,1)+ABS(DATOS_CONEX!$F$7:$F$4000-DATE(2026,5,1)))/2)+ABS(((DATOS_CONEX!$G$7:$G$4000+DATE(2026,6,1)-ABS(DATOS_CONEX!$G$7:$G$4000-DATE(2026,6,1)))/2-(DATOS_CONEX!$F$7:$F$4000+DATE(2026,5,1)+ABS(DATOS_CONEX!$F$7:$F$4000-DATE(2026,5,1)))/2)))/2)) -> 275.49792
A51: Junio | B51: =IF(COUNTIF(DATOS_CONEX!$B$7:$B$4000,A51)>0,"Cargado",IF(DATE(2026,6,1)>TODAY(),"","Falta EDP")) -> Cargado | C51: =IF(COUNTIFS(DATOS_CONEX!$G$7:$G$4000,">="&DATE(2026,6,1),DATOS_CONEX!$G$7:$G$4000,"<"&DATE(2026,7,1),DATOS_CONEX!$I$7:$I$4000,"Sí")=0,"",COUNTIFS(DATOS_CONEX!$G$7:$G$4000,">="&DATE(2026,6,1),DATOS_CONEX!$G$7:$G$4000,"<"&DATE(2026,7,1),DATOS_CONEX!$I$7:$I$4000,"Sí")) -> 220 | D51: =IF(C51="","",MAX(_xlfn.MAXIFS(DATOS_CONEX!$L$7:$L$4000,DATOS_CONEX!$F$7:$F$4000,">="&DATE(2026,6,1),DATOS_CONEX!$F$7:$F$4000,"<"&DATE(2026,7,1)),COUNTIFS(DATOS_CONEX!$F$7:$F$4000,"<="&DATE(2026,6,1),DATOS_CONEX!$G$7:$G$4000,">"&DATE(2026,6,1),DATOS_CONEX!$I$7:$I$4000,"Sí"))) -> 174 | E51: =IF(D51="","",IFERROR(INDEX(DATOS_CONEX!$F$7:$F$4000,MATCH(A51&"|"&D51,DATOS_CONEX!$N$7:$N$4000,0)),"Inicio de mes")) -> 46192.54 | F51: =IF(D51="","",IFERROR(INDEX(DATOS_CONEX!$C$7:$C$4000,MATCH(A51&"|"&D51,DATOS_CONEX!$N$7:$N$4000,0)),"-")) -> POLAR ARGENTINA | G51: =IF(C51="","",SUMPRODUCT((DATOS_CONEX!$I$7:$I$4000="Sí")*(((DATOS_CONEX!$G$7:$G$4000+DATE(2026,7,1)-ABS(DATOS_CONEX!$G$7:$G$4000-DATE(2026,7,1)))/2-(DATOS_CONEX!$F$7:$F$4000+DATE(2026,6,1)+ABS(DATOS_CONEX!$F$7:$F$4000-DATE(2026,6,1)))/2)+ABS(((DATOS_CONEX!$G$7:$G$4000+DATE(2026,7,1)-ABS(DATOS_CONEX!$G$7:$G$4000-DATE(2026,7,1)))/2-(DATOS_CONEX!$F$7:$F$4000+DATE(2026,6,1)+ABS(DATOS_CONEX!$F$7:$F$4000-DATE(2026,6,1)))/2)))/2)/(DATE(2026,7,1)-DATE(2026,6,1))) -> 16.034838 | H51: =IF(C51="","",SUMPRODUCT((DATOS_CONEX!$I$7:$I$4000="Sí")*(((DATOS_CONEX!$G$7:$G$4000+DATE(2026,7,1)-ABS(DATOS_CONEX!$G$7:$G$4000-DATE(2026,7,1)))/2-(DATOS_CONEX!$F$7:$F$4000+DATE(2026,6,1)+ABS(DATOS_CONEX!$F$7:$F$4000-DATE(2026,6,1)))/2)+ABS(((DATOS_CONEX!$G$7:$G$4000+DATE(2026,7,1)-ABS(DATOS_CONEX!$G$7:$G$4000-DATE(2026,7,1)))/2-(DATOS_CONEX!$F$7:$F$4000+DATE(2026,6,1)+ABS(DATOS_CONEX!$F$7:$F$4000-DATE(2026,6,1)))/2)))/2)) -> 481.04514
A52: Julio | B52: =IF(COUNTIF(DATOS_CONEX!$B$7:$B$4000,A52)>0,"Cargado",IF(DATE(2026,7,1)>TODAY(),"","Falta EDP")) -> Cargado | C52: =IF(COUNTIFS(DATOS_CONEX!$G$7:$G$4000,">="&DATE(2026,7,1),DATOS_CONEX!$G$7:$G$4000,"<"&DATE(2026,8,1),DATOS_CONEX!$I$7:$I$4000,"Sí")=0,"",COUNTIFS(DATOS_CONEX!$G$7:$G$4000,">="&DATE(2026,7,1),DATOS_CONEX!$G$7:$G$4000,"<"&DATE(2026,8,1),DATOS_CONEX!$I$7:$I$4000,"Sí")) -> 521 | D52: =IF(C52="","",MAX(_xlfn.MAXIFS(DATOS_CONEX!$L$7:$L$4000,DATOS_CONEX!$F$7:$F$4000,">="&DATE(2026,7,1),DATOS_CONEX!$F$7:$F$4000,"<"&DATE(2026,8,1)),COUNTIFS(DATOS_CONEX!$F$7:$F$4000,"<="&DATE(2026,7,1),DATOS_CONEX!$G$7:$G$4000,">"&DATE(2026,7,1),DATOS_CONEX!$I$7:$I$4000,"Sí"))) -> 205 | E52: =IF(D52="","",IFERROR(INDEX(DATOS_CONEX!$F$7:$F$4000,MATCH(A52&"|"&D52,DATOS_CONEX!$N$7:$N$4000,0)),"Inicio de mes")) -> 46234.563 | F52: =IF(D52="","",IFERROR(INDEX(DATOS_CONEX!$C$7:$C$4000,MATCH(A52&"|"&D52,DATOS_CONEX!$N$7:$N$4000,0)),"-")) -> RIO JANEIRO EXPRESS | G52: =IF(C52="","",SUMPRODUCT((DATOS_CONEX!$I$7:$I$4000="Sí")*(((DATOS_CONEX!$G$7:$G$4000+DATE(2026,8,1)-ABS(DATOS_CONEX!$G$7:$G$4000-DATE(2026,8,1)))/2-(DATOS_CONEX!$F$7:$F$4000+DATE(2026,7,1)+ABS(DATOS_CONEX!$F$7:$F$4000-DATE(2026,7,1)))/2)+ABS(((DATOS_CONEX!$G$7:$G$4000+DATE(2026,8,1)-ABS(DATOS_CONEX!$G$7:$G$4000-DATE(2026,8,1)))/2-(DATOS_CONEX!$F$7:$F$4000+DATE(2026,7,1)+ABS(DATOS_CONEX!$F$7:$F$4000-DATE(2026,7,1)))/2)))/2)/(DATE(2026,8,1)-DATE(2026,7,1))) -> 41.796259 | H52: =IF(C52="","",SUMPRODUCT((DATOS_CONEX!$I$7:$I$4000="Sí")*(((DATOS_CONEX!$G$7:$G$4000+DATE(2026,8,1)-ABS(DATOS_CONEX!$G$7:$G$4000-DATE(2026,8,1)))/2-(DATOS_CONEX!$F$7:$F$4000+DATE(2026,7,1)+ABS(DATOS_CONEX!$F$7:$F$4000-DATE(2026,7,1)))/2)+ABS(((DATOS_CONEX!$G$7:$G$4000+DATE(2026,8,1)-ABS(DATOS_CONEX!$G$7:$G$4000-DATE(2026,8,1)))/2-(DATOS_CONEX!$F$7:$F$4000+DATE(2026,7,1)+ABS(DATOS_CONEX!$F$7:$F$4000-DATE(2026,7,1)))/2)))/2)) -> 1295.684
A53: Agosto | B53: =IF(COUNTIF(DATOS_CONEX!$B$7:$B$4000,A53)>0,"Cargado",IF(DATE(2026,8,1)>TODAY(),"","Falta EDP")) -> Cargado | C53: =IF(COUNTIFS(DATOS_CONEX!$G$7:$G$4000,">="&DATE(2026,8,1),DATOS_CONEX!$G$7:$G$4000,"<"&DATE(2026,9,1),DATOS_CONEX!$I$7:$I$4000,"Sí")=0,"",COUNTIFS(DATOS_CONEX!$G$7:$G$4000,">="&DATE(2026,8,1),DATOS_CONEX!$G$7:$G$4000,"<"&DATE(2026,9,1),DATOS_CONEX!$I$7:$I$4000,"Sí")) -> 746 | D53: =IF(C53="","",MAX(_xlfn.MAXIFS(DATOS_CONEX!$L$7:$L$4000,DATOS_CONEX!$F$7:$F$4000,">="&DATE(2026,8,1),DATOS_CONEX!$F$7:$F$4000,"<"&DATE(2026,9,1)),COUNTIFS(DATOS_CONEX!$F$7:$F$4000,"<="&DATE(2026,8,1),DATOS_CONEX!$G$7:$G$4000,">"&DATE(2026,8,1),DATOS_CONEX!$I$7:$I$4000,"Sí"))) -> 344 | E53: =IF(D53="","",IFERROR(INDEX(DATOS_CONEX!$F$7:$F$4000,MATCH(A53&"|"&D53,DATOS_CONEX!$N$7:$N$4000,0)),"Inicio de mes")) -> 46257.869 | F53: =IF(D53="","",IFERROR(INDEX(DATOS_CONEX!$C$7:$C$4000,MATCH(A53&"|"&D53,DATOS_CONEX!$N$7:$N$4000,0)),"-")) -> POLAR PERU | G53: =IF(C53="","",SUMPRODUCT((DATOS_CONEX!$I$7:$I$4000="Sí")*(((DATOS_CONEX!$G$7:$G$4000+DATE(2026,9,1)-ABS(DATOS_CONEX!$G$7:$G$4000-DATE(2026,9,1)))/2-(DATOS_CONEX!$F$7:$F$4000+DATE(2026,8,1)+ABS(DATOS_CONEX!$F$7:$F$4000-DATE(2026,8,1)))/2)+ABS(((DATOS_CONEX!$G$7:$G$4000+DATE(2026,9,1)-ABS(DATOS_CONEX!$G$7:$G$4000-DATE(2026,9,1)))/2-(DATOS_CONEX!$F$7:$F$4000+DATE(2026,8,1)+ABS(DATOS_CONEX!$F$7:$F$4000-DATE(2026,8,1)))/2)))/2)/(DATE(2026,9,1)-DATE(2026,8,1))) -> 66.730063 | H53: =IF(C53="","",SUMPRODUCT((DATOS_CONEX!$I$7:$I$4000="Sí")*(((DATOS_CONEX!$G$7:$G$4000+DATE(2026,9,1)-ABS(DATOS_CONEX!$G$7:$G$4000-DATE(2026,9,1)))/2-(DATOS_CONEX!$F$7:$F$4000+DATE(2026,8,1)+ABS(DATOS_CONEX!$F$7:$F$4000-DATE(2026,8,1)))/2)+ABS(((DATOS_CONEX!$G$7:$G$4000+DATE(2026,9,1)-ABS(DATOS_CONEX!$G$7:$G$4000-DATE(2026,9,1)))/2-(DATOS_CONEX!$F$7:$F$4000+DATE(2026,8,1)+ABS(DATOS_CONEX!$F$7:$F$4000-DATE(2026,8,1)))/2)))/2)) -> 2068.6319
A54: Septiembre | B54: =IF(COUNTIF(DATOS_CONEX!$B$7:$B$4000,A54)>0,"Cargado",IF(DATE(2026,9,1)>TODAY(),"","Falta EDP")) -> Cargado | C54: =IF(COUNTIFS(DATOS_CONEX!$G$7:$G$4000,">="&DATE(2026,9,1),DATOS_CONEX!$G$7:$G$4000,"<"&DATE(2026,10,1),DATOS_CONEX!$I$7:$I$4000,"Sí")=0,"",COUNTIFS(DATOS_CONEX!$G$7:$G$4000,">="&DATE(2026,9,1),DATOS_CONEX!$G$7:$G$4000,"<"&DATE(2026,10,1),DATOS_CONEX!$I$7:$I$4000,"Sí")) -> 1146 | D54: =IF(C54="","",MAX(_xlfn.MAXIFS(DATOS_CONEX!$L$7:$L$4000,DATOS_CONEX!$F$7:$F$4000,">="&DATE(2026,9,1),DATOS_CONEX!$F$7:$F$4000,"<"&DATE(2026,10,1)),COUNTIFS(DATOS_CONEX!$F$7:$F$4000,"<="&DATE(2026,9,1),DATOS_CONEX!$G$7:$G$4000,">"&DATE(2026,9,1),DATOS_CONEX!$I$7:$I$4000,"Sí"))) -> 400 | E54: =IF(D54="","",IFERROR(INDEX(DATOS_CONEX!$F$7:$F$4000,MATCH(A54&"|"&D54,DATOS_CONEX!$N$7:$N$4000,0)),"Inicio de mes")) -> 46290.938 | F54: =IF(D54="","",IFERROR(INDEX(DATOS_CONEX!$C$7:$C$4000,MATCH(A54&"|"&D54,DATOS_CONEX!$N$7:$N$4000,0)),"-")) -> POLAR COLOMBIA | G54: =IF(C54="","",SUMPRODUCT((DATOS_CONEX!$I$7:$I$4000="Sí")*(((DATOS_CONEX!$G$7:$G$4000+DATE(2026,10,1)-ABS(DATOS_CONEX!$G$7:$G$4000-DATE(2026,10,1)))/2-(DATOS_CONEX!$F$7:$F$4000+DATE(2026,9,1)+ABS(DATOS_CONEX!$F$7:$F$4000-DATE(2026,9,1)))/2)+ABS(((DATOS_CONEX!$G$7:$G$4000+DATE(2026,10,1)-ABS(DATOS_CONEX!$G$7:$G$4000-DATE(2026,10,1)))/2-(DATOS_CONEX!$F$7:$F$4000+DATE(2026,9,1)+ABS(DATOS_CONEX!$F$7:$F$4000-DATE(2026,9,1)))/2)))/2)/(DATE(2026,10,1)-DATE(2026,9,1))) -> 105.59009 | H54: =IF(C54="","",SUMPRODUCT((DATOS_CONEX!$I$7:$I$4000="Sí")*(((DATOS_CONEX!$G$7:$G$4000+DATE(2026,10,1)-ABS(DATOS_CONEX!$G$7:$G$4000-DATE(2026,10,1)))/2-(DATOS_CONEX!$F$7:$F$4000+DATE(2026,9,1)+ABS(DATOS_CONEX!$F$7:$F$4000-DATE(2026,9,1)))/2)+ABS(((DATOS_CONEX!$G$7:$G$4000+DATE(2026,10,1)-ABS(DATOS_CONEX!$G$7:$G$4000-DATE(2026,10,1)))/2-(DATOS_CONEX!$F$7:$F$4000+DATE(2026,9,1)+ABS(DATOS_CONEX!$F$7:$F$4000-DATE(2026,9,1)))/2)))/2)) -> 3167.7028
A55: Octubre | B55: =IF(COUNTIF(DATOS_CONEX!$B$7:$B$4000,A55)>0,"Cargado",IF(DATE(2026,10,1)>TODAY(),"","Falta EDP")) -> Falta EDP | C55: =IF(COUNTIFS(DATOS_CONEX!$G$7:$G$4000,">="&DATE(2026,10,1),DATOS_CONEX!$G$7:$G$4000,"<"&DATE(2026,11,1),DATOS_CONEX!$I$7:$I$4000,"Sí")=0,"",COUNTIFS(DATOS_CONEX!$G$7:$G$4000,">="&DATE(2026,10,1),DATOS_CONEX!$G$7:$G$4000,"<"&DATE(2026,11,1),DATOS_CONEX!$I$7:$I$4000,"Sí")) | D55: =IF(C55="","",MAX(_xlfn.MAXIFS(DATOS_CONEX!$L$7:$L$4000,DATOS_CONEX!$F$7:$F$4000,">="&DATE(2026,10,1),DATOS_CONEX!$F$7:$F$4000,"<"&DATE(2026,11,1)),COUNTIFS(DATOS_CONEX!$F$7:$F$4000,"<="&DATE(2026,10,1),DATOS_CONEX!$G$7:$G$4000,">"&DATE(2026,10,1),DATOS_CONEX!$I$7:$I$4000,"Sí"))) | E55: =IF(D55="","",IFERROR(INDEX(DATOS_CONEX!$F$7:$F$4000,MATCH(A55&"|"&D55,DATOS_CONEX!$N$7:$N$4000,0)),"Inicio de mes")) | F55: =IF(D55="","",IFERROR(INDEX(DATOS_CONEX!$C$7:$C$4000,MATCH(A55&"|"&D55,DATOS_CONEX!$N$7:$N$4000,0)),"-")) | G55: =IF(C55="","",SUMPRODUCT((DATOS_CONEX!$I$7:$I$4000="Sí")*(((DATOS_CONEX!$G$7:$G$4000+DATE(2026,11,1)-ABS(DATOS_CONEX!$G$7:$G$4000-DATE(2026,11,1)))/2-(DATOS_CONEX!$F$7:$F$4000+DATE(2026,10,1)+ABS(DATOS_CONEX!$F$7:$F$4000-DATE(2026,10,1)))/2)+ABS(((DATOS_CONEX!$G$7:$G$4000+DATE(2026,11,1)-ABS(DATOS_CONEX!$G$7:$G$4000-DATE(2026,11,1)))/2-(DATOS_CONEX!$F$7:$F$4000+DATE(2026,10,1)+ABS(DATOS_CONEX!$F$7:$F$4000-DATE(2026,10,1)))/2)))/2)/(DATE(2026,11,1)-DATE(2026,10,1))) | H55: =IF(C55="","",SUMPRODUCT((DATOS_CONEX!$I$7:$I$4000="Sí")*(((DATOS_CONEX!$G$7:$G$4000+DATE(2026,11,1)-ABS(DATOS_CONEX!$G$7:$G$4000-DATE(2026,11,1)))/2-(DATOS_CONEX!$F$7:$F$4000+DATE(2026,10,1)+ABS(DATOS_CONEX!$F$7:$F$4000-DATE(2026,10,1)))/2)+ABS(((DATOS_CONEX!$G$7:$G$4000+DATE(2026,11,1)-ABS(DATOS_CONEX!$G$7:$G$4000-DATE(2026,11,1)))/2-(DATOS_CONEX!$F$7:$F$4000+DATE(2026,10,1)+ABS(DATOS_CONEX!$F$7:$F$4000-DATE(2026,10,1)))/2)))/2))
A56: Noviembre | B56: =IF(COUNTIF(DATOS_CONEX!$B$7:$B$4000,A56)>0,"Cargado",IF(DATE(2026,11,1)>TODAY(),"","Falta EDP")) | C56: =IF(COUNTIFS(DATOS_CONEX!$G$7:$G$4000,">="&DATE(2026,11,1),DATOS_CONEX!$G$7:$G$4000,"<"&DATE(2026,12,1),DATOS_CONEX!$I$7:$I$4000,"Sí")=0,"",COUNTIFS(DATOS_CONEX!$G$7:$G$4000,">="&DATE(2026,11,1),DATOS_CONEX!$G$7:$G$4000,"<"&DATE(2026,12,1),DATOS_CONEX!$I$7:$I$4000,"Sí")) | D56: =IF(C56="","",MAX(_xlfn.MAXIFS(DATOS_CONEX!$L$7:$L$4000,DATOS_CONEX!$F$7:$F$4000,">="&DATE(2026,11,1),DATOS_CONEX!$F$7:$F$4000,"<"&DATE(2026,12,1)),COUNTIFS(DATOS_CONEX!$F$7:$F$4000,"<="&DATE(2026,11,1),DATOS_CONEX!$G$7:$G$4000,">"&DATE(2026,11,1),DATOS_CONEX!$I$7:$I$4000,"Sí"))) | E56: =IF(D56="","",IFERROR(INDEX(DATOS_CONEX!$F$7:$F$4000,MATCH(A56&"|"&D56,DATOS_CONEX!$N$7:$N$4000,0)),"Inicio de mes")) | F56: =IF(D56="","",IFERROR(INDEX(DATOS_CONEX!$C$7:$C$4000,MATCH(A56&"|"&D56,DATOS_CONEX!$N$7:$N$4000,0)),"-")) | G56: =IF(C56="","",SUMPRODUCT((DATOS_CONEX!$I$7:$I$4000="Sí")*(((DATOS_CONEX!$G$7:$G$4000+DATE(2026,12,1)-ABS(DATOS_CONEX!$G$7:$G$4000-DATE(2026,12,1)))/2-(DATOS_CONEX!$F$7:$F$4000+DATE(2026,11,1)+ABS(DATOS_CONEX!$F$7:$F$4000-DATE(2026,11,1)))/2)+ABS(((DATOS_CONEX!$G$7:$G$4000+DATE(2026,12,1)-ABS(DATOS_CONEX!$G$7:$G$4000-DATE(2026,12,1)))/2-(DATOS_CONEX!$F$7:$F$4000+DATE(2026,11,1)+ABS(DATOS_CONEX!$F$7:$F$4000-DATE(2026,11,1)))/2)))/2)/(DATE(2026,12,1)-DATE(2026,11,1))) | H56: =IF(C56="","",SUMPRODUCT((DATOS_CONEX!$I$7:$I$4000="Sí")*(((DATOS_CONEX!$G$7:$G$4000+DATE(2026,12,1)-ABS(DATOS_CONEX!$G$7:$G$4000-DATE(2026,12,1)))/2-(DATOS_CONEX!$F$7:$F$4000+DATE(2026,11,1)+ABS(DATOS_CONEX!$F$7:$F$4000-DATE(2026,11,1)))/2)+ABS(((DATOS_CONEX!$G$7:$G$4000+DATE(2026,12,1)-ABS(DATOS_CONEX!$G$7:$G$4000-DATE(2026,12,1)))/2-(DATOS_CONEX!$F$7:$F$4000+DATE(2026,11,1)+ABS(DATOS_CONEX!$F$7:$F$4000-DATE(2026,11,1)))/2)))/2))
A57: Diciembre | B57: =IF(COUNTIF(DATOS_CONEX!$B$7:$B$4000,A57)>0,"Cargado",IF(DATE(2026,12,1)>TODAY(),"","Falta EDP")) | C57: =IF(COUNTIFS(DATOS_CONEX!$G$7:$G$4000,">="&DATE(2026,12,1),DATOS_CONEX!$G$7:$G$4000,"<"&DATE(2026,13,1),DATOS_CONEX!$I$7:$I$4000,"Sí")=0,"",COUNTIFS(DATOS_CONEX!$G$7:$G$4000,">="&DATE(2026,12,1),DATOS_CONEX!$G$7:$G$4000,"<"&DATE(2026,13,1),DATOS_CONEX!$I$7:$I$4000,"Sí")) | D57: =IF(C57="","",MAX(_xlfn.MAXIFS(DATOS_CONEX!$L$7:$L$4000,DATOS_CONEX!$F$7:$F$4000,">="&DATE(2026,12,1),DATOS_CONEX!$F$7:$F$4000,"<"&DATE(2026,13,1)),COUNTIFS(DATOS_CONEX!$F$7:$F$4000,"<="&DATE(2026,12,1),DATOS_CONEX!$G$7:$G$4000,">"&DATE(2026,12,1),DATOS_CONEX!$I$7:$I$4000,"Sí"))) | E57: =IF(D57="","",IFERROR(INDEX(DATOS_CONEX!$F$7:$F$4000,MATCH(A57&"|"&D57,DATOS_CONEX!$N$7:$N$4000,0)),"Inicio de mes")) | F57: =IF(D57="","",IFERROR(INDEX(DATOS_CONEX!$C$7:$C$4000,MATCH(A57&"|"&D57,DATOS_CONEX!$N$7:$N$4000,0)),"-")) | G57: =IF(C57="","",SUMPRODUCT((DATOS_CONEX!$I$7:$I$4000="Sí")*(((DATOS_CONEX!$G$7:$G$4000+DATE(2026,13,1)-ABS(DATOS_CONEX!$G$7:$G$4000-DATE(2026,13,1)))/2-(DATOS_CONEX!$F$7:$F$4000+DATE(2026,12,1)+ABS(DATOS_CONEX!$F$7:$F$4000-DATE(2026,12,1)))/2)+ABS(((DATOS_CONEX!$G$7:$G$4000+DATE(2026,13,1)-ABS(DATOS_CONEX!$G$7:$G$4000-DATE(2026,13,1)))/2-(DATOS_CONEX!$F$7:$F$4000+DATE(2026,12,1)+ABS(DATOS_CONEX!$F$7:$F$4000-DATE(2026,12,1)))/2)))/2)/(DATE(2026,13,1)-DATE(2026,12,1))) | H57: =IF(C57="","",SUMPRODUCT((DATOS_CONEX!$I$7:$I$4000="Sí")*(((DATOS_CONEX!$G$7:$G$4000+DATE(2026,13,1)-ABS(DATOS_CONEX!$G$7:$G$4000-DATE(2026,13,1)))/2-(DATOS_CONEX!$F$7:$F$4000+DATE(2026,12,1)+ABS(DATOS_CONEX!$F$7:$F$4000-DATE(2026,12,1)))/2)+ABS(((DATOS_CONEX!$G$7:$G$4000+DATE(2026,13,1)-ABS(DATOS_CONEX!$G$7:$G$4000-DATE(2026,13,1)))/2-(DATOS_CONEX!$F$7:$F$4000+DATE(2026,12,1)+ABS(DATOS_CONEX!$F$7:$F$4000-DATE(2026,12,1)))/2)))/2))

Sheet FLUJO DIARIO
A1: FLUJO DIARIO DE REEFERS Y PPK 2026
A2: Total del día = conectados a las 00:00 + nuevas conexiones · hacia abajo: desconexiones · abajo: PPK arrendados por día. Fuente: detalle EDP (DATOS_CONEX) y pestaña PPK.
A4: MES | B4: Septiembre | H4: EDP del mes | K4: =IF(COUNTIF(DATOS_CONEX!$B$7:$B$4000,$B$4)=0,"Falta EDP","Cargado ("&COUNTIFS(DATOS_CONEX!$B$7:$B$4000,$B$4,DATOS_CONEX!$I$7:$I$4000,"Sí")&" válidos)") -> Cargado (1146 válidos) | R4: Máx. total del día | U4: =MAX(B47:AF47) -> 415 | X4: Máx. PPK en un día | AA4: =MAX(B48:AF48) -> 8 | AH4: =MATCH($B$4,{"Enero","Febrero","Marzo","Abril","Mayo","Junio","Julio","Agosto","Septiembre","Octubre","Noviembre","Diciembre"},0) -> 9
A42: TABLA DEL MES
A43: Día | B43: =IF(B$52="","",DAY(B$52)) -> 1 | C43: =IF(C$52="","",DAY(C$52)) -> 2 | D43: =IF(D$52="","",DAY(D$52)) -> 3 | E43: =IF(E$52="","",DAY(E$52)) -> 4 | F43: =IF(F$52="","",DAY(F$52)) -> 5 | G43: =IF(G$52="","",DAY(G$52)) -> 6 | H43: =IF(H$52="","",DAY(H$52)) -> 7 | I43: =IF(I$52="","",DAY(I$52)) -> 8 | ... AF43: =IF(AF$52="","",DAY(AF$52))
A44: Conectados 00:00 | B44: =IF(B$52="","",COUNTIFS(DATOS_CONEX!$F$7:$F$4000,"<="&B$52,DATOS_CONEX!$G$7:$G$4000,">"&B$52,DATOS_CONEX!$I$7:$I$4000,"Sí")) -> 31 | C44: =IF(C$52="","",COUNTIFS(DATOS_CONEX!$F$7:$F$4000,"<="&C$52,DATOS_CONEX!$G$7:$G$4000,">"&C$52,DATOS_CONEX!$I$7:$I$4000,"Sí")) -> 37 | D44: =IF(D$52="","",COUNTIFS(DATOS_CONEX!$F$7:$F$4000,"<="&D$52,DATOS_CONEX!$G$7:$G$4000,">"&D$52,DATOS_CONEX!$I$7:$I$4000,"Sí")) -> 173 | E44: =IF(E$52="","",COUNTIFS(DATOS_CONEX!$F$7:$F$4000,"<="&E$52,DATOS_CONEX!$G$7:$G$4000,">"&E$52,DATOS_CONEX!$I$7:$I$4000,"Sí")) -> 306 | F44: =IF(F$52="","",COUNTIFS(DATOS_CONEX!$F$7:$F$4000,"<="&F$52,DATOS_CONEX!$G$7:$G$4000,">"&F$52,DATOS_CONEX!$I$7:$I$4000,"Sí")) -> 307 | G44: =IF(G$52="","",COUNTIFS(DATOS_CONEX!$F$7:$F$4000,"<="&G$52,DATOS_CONEX!$G$7:$G$4000,">"&G$52,DATOS_CONEX!$I$7:$I$4000,"Sí")) -> 53 | H44: =IF(H$52="","",COUNTIFS(DATOS_CONEX!$F$7:$F$4000,"<="&H$52,DATOS_CONEX!$G$7:$G$4000,">"&H$52,DATOS_CONEX!$I$7:$I$4000,"Sí")) -> 43 | I44: =IF(I$52="","",COUNTIFS(DATOS_CONEX!$F$7:$F$4000,"<="&I$52,DATOS_CONEX!$G$7:$G$4000,">"&I$52,DATOS_CONEX!$I$7:$I$4000,"Sí")) -> 43 | ... AF44: =IF(AF$52="","",COUNTIFS(DATOS_CONEX!$F$7:$F$4000,"<="&AF$52,DATOS_CONEX!$G$7:$G$4000,">"&AF$52,DATOS_CONEX!$I$7:$I$4000,"Sí"))
A45: Nuevas conexiones | B45: =IF(B$52="","",COUNTIFS(DATOS_CONEX!$F$7:$F$4000,">"&B$52,DATOS_CONEX!$F$7:$F$4000,"<"&(B$52+1),DATOS_CONEX!$I$7:$I$4000,"Sí")) -> 6 | C45: =IF(C$52="","",COUNTIFS(DATOS_CONEX!$F$7:$F$4000,">"&C$52,DATOS_CONEX!$F$7:$F$4000,"<"&(C$52+1),DATOS_CONEX!$I$7:$I$4000,"Sí")) -> 141 | D45: =IF(D$52="","",COUNTIFS(DATOS_CONEX!$F$7:$F$4000,">"&D$52,DATOS_CONEX!$F$7:$F$4000,"<"&(D$52+1),DATOS_CONEX!$I$7:$I$4000,"Sí")) -> 133 | E45: =IF(E$52="","",COUNTIFS(DATOS_CONEX!$F$7:$F$4000,">"&E$52,DATOS_CONEX!$F$7:$F$4000,"<"&(E$52+1),DATOS_CONEX!$I$7:$I$4000,"Sí")) -> 1 | F45: =IF(F$52="","",COUNTIFS(DATOS_CONEX!$F$7:$F$4000,">"&F$52,DATOS_CONEX!$F$7:$F$4000,"<"&(F$52+1),DATOS_CONEX!$I$7:$I$4000,"Sí")) -> 13 | G45: =IF(G$52="","",COUNTIFS(DATOS_CONEX!$F$7:$F$4000,">"&G$52,DATOS_CONEX!$F$7:$F$4000,"<"&(G$52+1),DATOS_CONEX!$I$7:$I$4000,"Sí")) -> 0 | H45: =IF(H$52="","",COUNTIFS(DATOS_CONEX!$F$7:$F$4000,">"&H$52,DATOS_CONEX!$F$7:$F$4000,"<"&(H$52+1),DATOS_CONEX!$I$7:$I$4000,"Sí")) -> 4 | I45: =IF(I$52="","",COUNTIFS(DATOS_CONEX!$F$7:$F$4000,">"&I$52,DATOS_CONEX!$F$7:$F$4000,"<"&(I$52+1),DATOS_CONEX!$I$7:$I$4000,"Sí")) -> 11 | ... AF45: =IF(AF$52="","",COUNTIFS(DATOS_CONEX!$F$7:$F$4000,">"&AF$52,DATOS_CONEX!$F$7:$F$4000,"<"&(AF$52+1),DATOS_CONEX!$I$7:$I$4000,"Sí"))
A46: Desconexiones | B46: =IF(B$52="","",COUNTIFS(DATOS_CONEX!$G$7:$G$4000,">="&B$52,DATOS_CONEX!$G$7:$G$4000,"<"&(B$52+1),DATOS_CONEX!$I$7:$I$4000,"Sí")) -> 1 | C46: =IF(C$52="","",COUNTIFS(DATOS_CONEX!$G$7:$G$4000,">="&C$52,DATOS_CONEX!$G$7:$G$4000,"<"&(C$52+1),DATOS_CONEX!$I$7:$I$4000,"Sí")) -> 5 | D46: =IF(D$52="","",COUNTIFS(DATOS_CONEX!$G$7:$G$4000,">="&D$52,DATOS_CONEX!$G$7:$G$4000,"<"&(D$52+1),DATOS_CONEX!$I$7:$I$4000,"Sí")) -> 0 | E46: =IF(E$52="","",COUNTIFS(DATOS_CONEX!$G$7:$G$4000,">="&E$52,DATOS_CONEX!$G$7:$G$4000,"<"&(E$52+1),DATOS_CONEX!$I$7:$I$4000,"Sí")) -> 0 | F46: =IF(F$52="","",COUNTIFS(DATOS_CONEX!$G$7:$G$4000,">="&F$52,DATOS_CONEX!$G$7:$G$4000,"<"&(F$52+1),DATOS_CONEX!$I$7:$I$4000,"Sí")) -> 267 | G46: =IF(G$52="","",COUNTIFS(DATOS_CONEX!$G$7:$G$4000,">="&G$52,DATOS_CONEX!$G$7:$G$4000,"<"&(G$52+1),DATOS_CONEX!$I$7:$I$4000,"Sí")) -> 10 | H46: =IF(H$52="","",COUNTIFS(DATOS_CONEX!$G$7:$G$4000,">="&H$52,DATOS_CONEX!$G$7:$G$4000,"<"&(H$52+1),DATOS_CONEX!$I$7:$I$4000,"Sí")) -> 4 | I46: =IF(I$52="","",COUNTIFS(DATOS_CONEX!$G$7:$G$4000,">="&I$52,DATOS_CONEX!$G$7:$G$4000,"<"&(I$52+1),DATOS_CONEX!$I$7:$I$4000,"Sí")) -> 3 | ... AF46: =IF(AF$52="","",COUNTIFS(DATOS_CONEX!$G$7:$G$4000,">="&AF$52,DATOS_CONEX!$G$7:$G$4000,"<"&(AF$52+1),DATOS_CONEX!$I$7:$I$4000,"Sí"))
A47: Total del día | B47: =IF(B$52="","",B44+B45) -> 37 | C47: =IF(C$52="","",C44+C45) -> 178 | D47: =IF(D$52="","",D44+D45) -> 306 | E47: =IF(E$52="","",E44+E45) -> 307 | F47: =IF(F$52="","",F44+F45) -> 320 | G47: =IF(G$52="","",G44+G45) -> 53 | H47: =IF(H$52="","",H44+H45) -> 47 | I47: =IF(I$52="","",I44+I45) -> 54 | ... AF47: =IF(AF$52="","",AF44+AF45)
A48: PPK arrendados | B48: =IF(B$52="","",COUNTIFS(DATOS_CONEX!$R$7:$R$4000,"<="&B$52,DATOS_CONEX!$S$7:$S$4000,">="&B$52)) -> 2 | C48: =IF(C$52="","",COUNTIFS(DATOS_CONEX!$R$7:$R$4000,"<="&C$52,DATOS_CONEX!$S$7:$S$4000,">="&C$52)) -> 3 | D48: =IF(D$52="","",COUNTIFS(DATOS_CONEX!$R$7:$R$4000,"<="&D$52,DATOS_CONEX!$S$7:$S$4000,">="&D$52)) -> 5 | E48: =IF(E$52="","",COUNTIFS(DATOS_CONEX!$R$7:$R$4000,"<="&E$52,DATOS_CONEX!$S$7:$S$4000,">="&E$52)) -> 5 | F48: =IF(F$52="","",COUNTIFS(DATOS_CONEX!$R$7:$R$4000,"<="&F$52,DATOS_CONEX!$S$7:$S$4000,">="&F$52)) -> 4 | G48: =IF(G$52="","",COUNTIFS(DATOS_CONEX!$R$7:$R$4000,"<="&G$52,DATOS_CONEX!$S$7:$S$4000,">="&G$52)) -> 4 | H48: =IF(H$52="","",COUNTIFS(DATOS_CONEX!$R$7:$R$4000,"<="&H$52,DATOS_CONEX!$S$7:$S$4000,">="&H$52)) -> 2 | I48: =IF(I$52="","",COUNTIFS(DATOS_CONEX!$R$7:$R$4000,"<="&I$52,DATOS_CONEX!$S$7:$S$4000,">="&I$52)) -> 2 | ... AF48: =IF(AF$52="","",COUNTIFS(DATOS_CONEX!$R$7:$R$4000,"<="&AF$52,DATOS_CONEX!$S$7:$S$4000,">="&AF$52))
A50: Las desconexiones de 20 o más se marcan en color. Filas 52-53 ocultas: fechas del mes y desconexiones en negativo para el gráfico.
A52: Fecha | B52: =IF(1<=DAY(DATE(2026,$AH$4+1,1)-1),DATE(2026,$AH$4,1),"") -> 46266 | C52: =IF(2<=DAY(DATE(2026,$AH$4+1,1)-1),DATE(2026,$AH$4,2),"") -> 46267 | D52: =IF(3<=DAY(DATE(2026,$AH$4+1,1)-1),DATE(2026,$AH$4,3),"") -> 46268 | E52: =IF(4<=DAY(DATE(2026,$AH$4+1,1)-1),DATE(2026,$AH$4,4),"") -> 46269 | F52: =IF(5<=DAY(DATE(2026,$AH$4+1,1)-1),DATE(2026,$AH$4,5),"") -> 46270 | G52: =IF(6<=DAY(DATE(2026,$AH$4+1,1)-1),DATE(2026,$AH$4,6),"") -> 46271 | H52: =IF(7<=DAY(DATE(2026,$AH$4+1,1)-1),DATE(2026,$AH$4,7),"") -> 46272 | I52: =IF(8<=DAY(DATE(2026,$AH$4+1,1)-1),DATE(2026,$AH$4,8),"") -> 46273 | J52: =IF(9<=DAY(DATE(2026,$AH$4+1,1)-1),DATE(2026,$AH$4,9),"") -> 46274 | K52: =IF(10<=DAY(DATE(2026,$AH$4+1,1)-1),DATE(2026,$AH$4,10),"") -> 46275 | L52: =IF(11<=DAY(DATE(2026,$AH$4+1,1)-1),DATE(2026,$AH$4,11),"") -> 46276 | M52: =IF(12<=DAY(DATE(2026,$AH$4+1,1)-1),DATE(2026,$AH$4,12),"") -> 46277 | N52: =IF(13<=DAY(DATE(2026,$AH$4+1,1)-1),DATE(2026,$AH$4,13),"") -> 46278 | O52: =IF(14<=DAY(DATE(2026,$AH$4+1,1)-1),DATE(2026,$AH$4,14),"") -> 46279 | P52: =IF(15<=DAY(DATE(2026,$AH$4+1,1)-1),DATE(2026,$AH$4,15),"") -> 46280 | Q52: =IF(16<=DAY(DATE(2026,$AH$4+1,1)-1),DATE(2026,$AH$4,16),"") -> 46281 | R52: =IF(17<=DAY(DATE(2026,$AH$4+1,1)-1),DATE(2026,$AH$4,17),"") -> 46282 | S52: =IF(18<=DAY(DATE(2026,$AH$4+1,1)-1),DATE(2026,$AH$4,18),"") -> 46283 | T52: =IF(19<=DAY(DATE(2026,$AH$4+1,1)-1),DATE(2026,$AH$4,19),"") -> 46284 | U52: =IF(20<=DAY(DATE(2026,$AH$4+1,1)-1),DATE(2026,$AH$4,20),"") -> 46285 | V52: =IF(21<=DAY(DATE(2026,$AH$4+1,1)-1),DATE(2026,$AH$4,21),"") -> 46286 | W52: =IF(22<=DAY(DATE(2026,$AH$4+1,1)-1),DATE(2026,$AH$4,22),"") -> 46287 | X52: =IF(23<=DAY(DATE(2026,$AH$4+1,1)-1),DATE(2026,$AH$4,23),"") -> 46288 | Y52: =IF(24<=DAY(DATE(2026,$AH$4+1,1)-1),DATE(2026,$AH$4,24),"") -> 46289 | Z52: =IF(25<=DAY(DATE(2026,$AH$4+1,1)-1),DATE(2026,$AH$4,25),"") -> 46290 | AA52: =IF(26<=DAY(DATE(2026,$AH$4+1,1)-1),DATE(2026,$AH$4,26),"") -> 46291 | AB52: =IF(27<=DAY(DATE(2026,$AH$4+1,1)-1),DATE(2026,$AH$4,27),"") -> 46292 | AC52: =IF(28<=DAY(DATE(2026,$AH$4+1,1)-1),DATE(2026,$AH$4,28),"") -> 46293 | AD52: =IF(29<=DAY(DATE(2026,$AH$4+1,1)-1),DATE(2026,$AH$4,29),"") -> 46294 | AE52: =IF(30<=DAY(DATE(2026,$AH$4+1,1)-1),DATE(2026,$AH$4,30),"") -> 46295 | AF52: =IF(31<=DAY(DATE(2026,$AH$4+1,1)-1),DATE(2026,$AH$4,31),"")
A53: Desc. negativo | B53: =IF(B46="","",-B46) -> -1 | C53: =IF(C46="","",-C46) -> -5 | D53: =IF(D46="","",-D46) -> 0 | E53: =IF(E46="","",-E46) -> 0 | F53: =IF(F46="","",-F46) -> -267 | G53: =IF(G46="","",-G46) -> -10 | H53: =IF(H46="","",-H46) -> -4 | I53: =IF(I46="","",-I46) -> -3 | ... AF53: =IF(AF46="","",-AF46)

Sheet BUDGET vs FCST
A1: COMPARATIVO REEFER 2026 — BUDGET vs FCST 2 vs FCST 3
A5: Mes a comparar | B5: Junio | D5: Elige el mes en la celda amarilla. Verde = a favor del real, rojo = en contra (en costo, gastar más que el plan es rojo). Acumulado = enero hasta el mes elegido. | S5: =MATCH($B$5,$A$30:$A$41,0) -> 6
A7: ="MES: "&UPPER($B$5) -> MES: JUNIO
A8: Indicador | B8: Real | C8: Budget | D8: Dif. vs Budget | E8: Var. % | F8: FCST 2 | G8: Dif. vs FCST 2 | H8: Var. % | I8: FCST 3 | J8: Dif. vs FCST 3 | K8: Var. %
A9: Cantidad de reefers | B9: =IF(INDEX(E$30:E$41,$S$5)="","",INDEX(E$30:E$41,$S$5)) -> 213 | C9: =INDEX(B$30:B$41,$S$5) -> 199 | D9: =IF($B9="","",$B9-C9) -> 14 | E9: =IF(OR($B9="",C9=0),"",$B9/C9-1) -> 0.070351759 | F9: =INDEX(C$30:C$41,$S$5) -> 207 | G9: =IF($B9="","",$B9-F9) -> 6 | H9: =IF(OR($B9="",F9=0),"",$B9/F9-1) -> 0.028985507 | I9: =INDEX(D$30:D$41,$S$5) -> 213 | J9: =IF($B9="","",$B9-I9) -> 0 | K9: =IF(OR($B9="",I9=0),"",$B9/I9-1) -> 0
A10: Venta (USD) | B10: =IF(INDEX(I$30:I$41,$S$5)="","",INDEX(I$30:I$41,$S$5)) -> 54592 | C10: =INDEX(F$30:F$41,$S$5) -> 130845.71 | D10: =IF($B10="","",$B10-C10) -> -76253.71 | E10: =IF(OR($B10="",C10=0),"",$B10/C10-1) -> -0.58277577 | F10: =INDEX(G$30:G$41,$S$5) -> 137672.35 | G10: =IF($B10="","",$B10-F10) -> -83080.35 | H10: =IF(OR($B10="",F10=0),"",$B10/F10-1) -> -0.60346431 | I10: =INDEX(H$30:H$41,$S$5) -> 54592 | J10: =IF($B10="","",$B10-I10) -> 0 | K10: =IF(OR($B10="",I10=0),"",$B10/I10-1) -> 0
A11: Costo (USD) | B11: =IF(INDEX(M$30:M$41,$S$5)="","",INDEX(M$30:M$41,$S$5)) -> 32451.087 | C11: =INDEX(J$30:J$41,$S$5) -> 33961.95 | D11: =IF($B11="","",$B11-C11) -> -1510.863 | E11: =IF(OR($B11="",C11=0),"",$B11/C11-1) -> -0.044486934 | F11: =INDEX(K$30:K$41,$S$5) -> 42558.9 | G11: =IF($B11="","",$B11-F11) -> -10107.813 | H11: =IF(OR($B11="",F11=0),"",$B11/F11-1) -> -0.23750175 | I11: =INDEX(L$30:L$41,$S$5) -> 31360.91 | J11: =IF($B11="","",$B11-I11) -> 1090.177 | K11: =IF(OR($B11="",I11=0),"",$B11/I11-1) -> 0.034762287
A12: Margen (USD) | B12: =IF(INDEX(Q$30:Q$41,$S$5)="","",INDEX(Q$30:Q$41,$S$5)) -> 22140.913 | C12: =INDEX(N$30:N$41,$S$5) -> 96883.76 | D12: =IF($B12="","",$B12-C12) -> -74742.847 | E12: =IF(OR($B12="",C12=0),"",$B12/C12-1) -> -0.7714693 | F12: =INDEX(O$30:O$41,$S$5) -> 95113.45 | G12: =IF($B12="","",$B12-F12) -> -72972.537 | H12: =IF(OR($B12="",F12=0),"",$B12/F12-1) -> -0.76721575 | I12: =INDEX(P$30:P$41,$S$5) -> 23231.09 | J12: =IF($B12="","",$B12-I12) -> -1090.177 | K12: =IF(OR($B12="",I12=0),"",$B12/I12-1) -> -0.046927499
A13: Margen % | B13: =IF(B12="","",IFERROR(B12/B10,"")) -> 0.40557065 | C13: =IFERROR(C12/C10,"") -> 0.74044277 | D13: =IF(OR($B13="",C13=""),"",$B13-C13) -> -0.33487212 | F13: =IFERROR(F12/F10,"") -> 0.69086821 | G13: =IF(OR($B13="",F13=""),"",$B13-F13) -> -0.28529756 | I13: =IFERROR(I12/I10,"") -> 0.42554019 | J13: =IF(OR($B13="",I13=""),"",$B13-I13) -> -0.019969537
A15: ="ACUMULADO ENERO – "&UPPER($B$5) -> ACUMULADO ENERO – JUNIO
A16: Indicador | B16: Real | C16: Budget | D16: Dif. vs Budget | E16: Var. % | F16: FCST 2 | G16: Dif. vs FCST 2 | H16: Var. % | I16: FCST 3 | J16: Dif. vs FCST 3 | K16: Var. %
A17: Cantidad de reefers | B17: =IF(INDEX(E$30:E$41,$S$5)="","",SUM(E$30:INDEX(E$30:E$41,$S$5))) -> 497 | C17: =SUM(B$30:INDEX(B$30:B$41,$S$5)) -> 618 | D17: =IF($B17="","",$B17-C17) -> -121 | E17: =IF(OR($B17="",C17=0),"",$B17/C17-1) -> -0.19579288 | F17: =SUM(C$30:INDEX(C$30:C$41,$S$5)) -> 533 | G17: =IF($B17="","",$B17-F17) -> -36 | H17: =IF(OR($B17="",F17=0),"",$B17/F17-1) -> -0.067542214 | I17: =SUM(D$30:INDEX(D$30:D$41,$S$5)) -> 485 | J17: =IF($B17="","",$B17-I17) -> 12 | K17: =IF(OR($B17="",I17=0),"",$B17/I17-1) -> 0.024742268
A18: Venta (USD) | B18: =IF(INDEX(I$30:I$41,$S$5)="","",SUM(I$30:INDEX(I$30:I$41,$S$5))) -> 312359 | C18: =SUM(F$30:INDEX(F$30:F$41,$S$5)) -> 417567.46 | D18: =IF($B18="","",$B18-C18) -> -105208.46 | E18: =IF(OR($B18="",C18=0),"",$B18/C18-1) -> -0.2519556 | F18: =SUM(G$30:INDEX(G$30:G$41,$S$5)) -> 395439.35 | G18: =IF($B18="","",$B18-F18) -> -83080.35 | H18: =IF(OR($B18="",F18=0),"",$B18/F18-1) -> -0.21009631 | I18: =SUM(H$30:INDEX(H$30:H$41,$S$5)) -> 312359 | J18: =IF($B18="","",$B18-I18) -> 0 | K18: =IF(OR($B18="",I18=0),"",$B18/I18-1) -> 0
A19: Costo (USD) | B19: =IF(INDEX(M$30:M$41,$S$5)="","",SUM(M$30:INDEX(M$30:M$41,$S$5))) -> 197527.26 | C19: =SUM(J$30:INDEX(J$30:J$41,$S$5)) -> 175208.44 | D19: =IF($B19="","",$B19-C19) -> 22318.821 | E19: =IF(OR($B19="",C19=0),"",$B19/C19-1) -> 0.12738439 | F19: =SUM(K$30:INDEX(K$30:K$41,$S$5)) -> 206559 | G19: =IF($B19="","",$B19-F19) -> -9031.7392 | H19: =IF(OR($B19="",F19=0),"",$B19/F19-1) -> -0.043724743 | I19: =SUM(L$30:INDEX(L$30:L$41,$S$5)) -> 195361.01 | J19: =IF($B19="","",$B19-I19) -> 2166.2508 | K19: =IF(OR($B19="",I19=0),"",$B19/I19-1) -> 0.01108845
A20: Margen (USD) | B20: =IF(INDEX(Q$30:Q$41,$S$5)="","",SUM(Q$30:INDEX(Q$30:Q$41,$S$5))) -> 114831.74 | C20: =SUM(N$30:INDEX(N$30:N$41,$S$5)) -> 242359.02 | D20: =IF($B20="","",$B20-C20) -> -127527.28 | E20: =IF(OR($B20="",C20=0),"",$B20/C20-1) -> -0.5261916 | F20: =SUM(O$30:INDEX(O$30:O$41,$S$5)) -> 188880.35 | G20: =IF($B20="","",$B20-F20) -> -74048.611 | H20: =IF(OR($B20="",F20=0),"",$B20/F20-1) -> -0.39203978 | I20: =SUM(P$30:INDEX(P$30:P$41,$S$5)) -> 116997.99 | J20: =IF($B20="","",$B20-I20) -> -2166.2508 | K20: =IF(OR($B20="",I20=0),"",$B20/I20-1) -> -0.018515282
A21: Margen % | B21: =IF(B20="","",IFERROR(B20/B18,"")) -> 0.36762744 | C21: =IFERROR(C20/C18,"") -> 0.58040686 | D21: =IF(OR($B21="",C21=""),"",$B21-C21) -> -0.21277943 | F21: =IFERROR(F20/F18,"") -> 0.47764682 | G21: =IF(OR($B21="",F21=""),"",$B21-F21) -> -0.11001939 | I21: =IFERROR(I20/I18,"") -> 0.37456257 | J21: =IF(OR($B21="",I21=""),"",$B21-I21) -> -0.0069351317
A23: Indicador anual | B23: Budget 2026 | C23: FCST 2 | D23: FCST 3 | E23: Real (Ene-Sep) | F23: Dif. FCST 2-Budget | G23: Var. FCST 2 % | H23: Dif. FCST 3-Budget | I23: Var. FCST 3 % | J23: Dif. FCST 3-FCST 2 | K23: Var. FCST 3 vs FCST 2 %
A24: Cantidad de reefers | B24: =SUM(B30:B41) -> 1438 | C24: =SUM(C30:C41) -> 1383 | D24: =SUM(D30:D41) -> 1845 | E24: =IFERROR(SUM(E30:E41),"") -> 2946 | F24: =IFERROR(C24-B24,"") -> -55 | G24: =IFERROR(C24/B24-1,"") -> -0.038247566 | H24: =IFERROR(D24-B24,"") -> 407 | I24: =IFERROR(D24/B24-1,"") -> 0.28303199 | J24: =IFERROR(D24-C24,"") -> 462 | K24: =IFERROR(D24/C24-1,"") -> 0.3340564
A25: Venta (USD) | B25: =SUM(F30:F41) -> 962703.52 | C25: =SUM(G30:G41) -> 967972.72 | D25: =SUM(H30:H41) -> 1028097.2 | E25: =IFERROR(SUM(I30:I41),"") -> 1446679 | F25: =IFERROR(C25-B25,"") -> 5269.2 | G25: =IFERROR(C25/B25-1,"") -> 0.0054733362 | H25: =IFERROR(D25-B25,"") -> 65393.702 | I25: =IFERROR(D25/B25-1,"") -> 0.067927145 | J25: =IFERROR(D25-C25,"") -> 60124.502 | K25: =IFERROR(D25/C25-1,"") -> 0.062113839
A26: Costo (USD) | B26: =SUM(J30:J41) -> 324738.54 | C26: =SUM(K30:K41) -> 385417.58 | D26: =SUM(L30:L41) -> 460003.52 | E26: =IFERROR(SUM(M30:M41),"") -> 456973.62 | F26: =IFERROR(C26-B26,"") -> 60679.04 | G26: =IFERROR(C26/B26-1,"") -> 0.18685506 | H26: =IFERROR(D26-B26,"") -> 135264.98 | I26: =IFERROR(D26/B26-1,"") -> 0.41653502 | J26: =IFERROR(D26-C26,"") -> 74585.935 | K26: =IFERROR(D26/C26-1,"") -> 0.19351981
A27: Margen (USD) | B27: =B25-B26 -> 637964.98 | C27: =C25-C26 -> 582555.14 | D27: =D25-D26 -> 568093.71 | E27: =IFERROR(E25-E26,"") -> 989705.38 | F27: =IFERROR(C27-B27,"") -> -55409.84 | G27: =IFERROR(C27/B27-1,"") -> -0.086854046 | H27: =IFERROR(D27-B27,"") -> -69871.273 | I27: =IFERROR(D27/B27-1,"") -> -0.10952211 | J27: =IFERROR(D27-C27,"") -> -14461.433 | K27: =IFERROR(D27/C27-1,"") -> -0.024824145
A29: Mes | B29: Cant. Budget | C29: Cant. FCST 2 | D29: Cant. FCST 3 | E29: Cant. Real | F29: Venta Budget USD | G29: Venta FCST 2 USD | H29: Venta FCST 3 USD | I29: Venta Real USD | J29: Costo Budget USD | K29: Costo FCST 2 USD | L29: Costo FCST 3 USD | M29: Costo Real USD | N29: Margen Budget USD | O29: Margen FCST 2 USD | P29: Margen FCST 3 USD | Q29: Margen Real USD
A30: Enero | B30: 80 | C30: 86 | D30: 75 | E30: =IFERROR(RESUMEN!B9,"") -> 88 | F30: 54744.01 | G30: 71088.33 | H30: 71088.33 | I30: =IF(RESUMEN!V9="","",RESUMEN!V9) -> 71088.33 | J30: 28797.69 | K30: 31893.9 | L30: 31893.9 | M30: =IFERROR(RESUMEN!N9/RESUMEN!M9,"") -> 33912.568 | N30: =F30-J30 -> 25946.32 | O30: =G30-K30 -> 39194.43 | P30: =H30-L30 -> 39194.43 | Q30: =IFERROR(I30-M30,"") -> 37175.762
A31: Febrero | B31: 80 | C31: 66 | D31: 55 | E31: =IFERROR(RESUMEN!B10,"") -> 54 | F31: 54744.01 | G31: 53916.57 | H31: 53916.57 | I31: =IF(RESUMEN!V10="","",RESUMEN!V10) -> 53916.57 | J31: 27977.92 | K31: 36712.93 | L31: 36712.93 | M31: =IFERROR(RESUMEN!N10/RESUMEN!M10,"") -> 35560.254 | N31: =F31-J31 -> 26766.09 | O31: =G31-K31 -> 17203.64 | P31: =H31-L31 -> 17203.64 | Q31: =IFERROR(I31-M31,"") -> 18356.316
A32: Marzo | B32: 99 | C32: 77 | D32: 72 | E32: =IFERROR(RESUMEN!B11,"") -> 72 | F32: 67745.71 | G32: 71738.1 | H32: 71738.1 | I32: =IF(RESUMEN!V11="","",RESUMEN!V11) -> 71738.1 | J32: 30289.57 | K32: 31860.89 | L32: 31860.89 | M32: =IFERROR(RESUMEN!N11/RESUMEN!M11,"") -> 33704.168 | N32: =F32-J32 -> 37456.14 | O32: =G32-K32 -> 39877.21 | P32: =H32-L32 -> 39877.21 | Q32: =IFERROR(I32-M32,"") -> 38033.932
A33: Abril | B33: 80 | C33: 31 | D33: 23 | E33: =IFERROR(RESUMEN!B12,"") -> 23 | F33: 54744.01 | G33: 19736 | H33: 19736 | I33: =IF(RESUMEN!V12="","",RESUMEN!V12) -> 19736 | J33: 28524.43 | K33: 26545.42 | L33: 26545.42 | M33: =IFERROR(RESUMEN!N12/RESUMEN!M12,"") -> 25525.01 | N33: =F33-J33 -> 26219.58 | O33: =G33-K33 -> -6809.42 | P33: =H33-L33 -> -6809.42 | Q33: =IFERROR(I33-M33,"") -> -5789.0096
A34: Mayo | B34: 80 | C34: 66 | D34: 47 | E34: =IFERROR(RESUMEN!B13,"") -> 47 | F34: 54744.01 | G34: 41288 | H34: 41288 | I34: =IF(RESUMEN!V13="","",RESUMEN!V13) -> 41288 | J34: 25656.88 | K34: 36986.96 | L34: 36986.96 | M34: =IFERROR(RESUMEN!N13/RESUMEN!M13,"") -> 36374.173 | N34: =F34-J34 -> 29087.13 | O34: =G34-K34 -> 4301.04 | P34: =H34-L34 -> 4301.04 | Q34: =IFERROR(I34-M34,"") -> 4913.8267
A35: Junio | B35: 199 | C35: 207 | D35: 213 | E35: =IFERROR(RESUMEN!B14,"") -> 213 | F35: 130845.71 | G35: 137672.35 | H35: 54592 | I35: =IF(RESUMEN!V14="","",RESUMEN!V14) -> 54592 | J35: 33961.95 | K35: 42558.9 | L35: 31360.91 | M35: =IFERROR(RESUMEN!N14/RESUMEN!M14,"") -> 32451.087 | N35: =F35-J35 -> 96883.76 | O35: =G35-K35 -> 95113.45 | P35: =H35-L35 -> 23231.09 | Q35: =IFERROR(I35-M35,"") -> 22140.913
A36: Julio | B36: 180 | C36: 188 | D36: 547 | E36: =IFERROR(RESUMEN!B15,"") -> 547 | F36: 117844.01 | G36: 124416.27 | H36: 198088 | I36: =IF(RESUMEN!V15="","",RESUMEN!V15) -> 198088 | J36: 33116.29 | K36: 41218.72 | L36: 48024.46 | M36: =IFERROR(RESUMEN!N15/RESUMEN!M15,"") -> 48769.22 | N36: =F36-J36 -> 84727.72 | O36: =G36-K36 -> 83197.55 | P36: =H36-L36 -> 150063.54 | Q36: =IFERROR(I36-M36,"") -> 149318.78
A37: Agosto | B37: 180 | C37: 188 | D37: 349 | E37: =IFERROR(RESUMEN!B16,"") -> 751 | F37: 117844.01 | G37: 124416.27 | H37: 305408 | I37: =IF(RESUMEN!V16="","",RESUMEN!V16) -> 305408 | J37: 33116.29 | K37: 41218.72 | L37: 82416.453 | M37: =IFERROR(RESUMEN!N16/RESUMEN!M16,"") -> 86839.948 | N37: =F37-J37 -> 84727.72 | O37: =G37-K37 -> 83197.55 | P37: =H37-L37 -> 222991.55 | Q37: =IFERROR(I37-M37,"") -> 218568.05
A38: Septiembre | B38: 199 | C38: 208 | D38: 316 | E38: =IFERROR(RESUMEN!B17,"") -> 1151 | F38: 130845.71 | G38: 138370.04 | H38: 110965.81 | I38: =IF(RESUMEN!V17="","",RESUMEN!V17) -> 630824 | J38: 33961.95 | K38: 42645.38 | L38: 51783.304 | M38: =IFERROR(RESUMEN!N17/RESUMEN!M17,"") -> 123837.19 | N38: =F38-J38 -> 96883.76 | O38: =G38-K38 -> 95724.66 | P38: =H38-L38 -> 59182.501 | Q38: =IFERROR(I38-M38,"") -> 506986.81
A39: Octubre | B39: 82 | C39: 89 | D39: 46 | E39: =IFERROR(RESUMEN!B18,"") | F39: 56112.61 | G39: 62000.57 | H39: 31477.805 | I39: =IF(RESUMEN!V18="","",RESUMEN!V18) | J39: 16248.89 | K39: 17938.34 | L39: 27385.479 | M39: =IFERROR(RESUMEN!N18/RESUMEN!M18,"") | N39: =F39-J39 -> 39863.72 | O39: =G39-K39 -> 44062.23 | P39: =H39-L39 -> 4092.3261 | Q39: =IFERROR(I39-M39,"")
A40: Noviembre | B40: 80 | C40: 88 | D40: 56 | E40: =IFERROR(RESUMEN!B19,"") | F40: 54744.01 | G40: 61316.27 | H40: 38320.806 | I40: =IF(RESUMEN!V19="","",RESUMEN!V19) | J40: 16170.37 | K40: 17899.08 | L40: 27647.33 | M40: =IFERROR(RESUMEN!N19/RESUMEN!M19,"") | N40: =F40-J40 -> 38573.64 | O40: =G40-K40 -> 43417.19 | P40: =H40-L40 -> 10673.477 | Q40: =IFERROR(I40-M40,"")
A41: Diciembre | B41: 99 | C41: 89 | D41: 46 | E41: =IFERROR(RESUMEN!B20,"") | F41: 67745.71 | G41: 62013.95 | H41: 31477.805 | I41: =IF(RESUMEN!V20="","",RESUMEN!V20) | J41: 16916.31 | K41: 17938.34 | L41: 27385.479 | M41: =IFERROR(RESUMEN!N20/RESUMEN!M20,"") | N41: =F41-J41 -> 50829.4 | O41: =G41-K41 -> 44075.61 | P41: =H41-L41 -> 4092.3261 | Q41: =IFERROR(I41-M41,"")
A42: TOTAL / PROM. | B42: =IF(COUNT(B30:B41)=0,"",SUM(B30:B41)) -> 1438 | C42: =IF(COUNT(C30:C41)=0,"",SUM(C30:C41)) -> 1383 | D42: =IF(COUNT(D30:D41)=0,"",SUM(D30:D41)) -> 1845 | E42: =IF(COUNT(E30:E41)=0,"",SUM(E30:E41)) -> 2946 | F42: =IF(COUNT(F30:F41)=0,"",SUM(F30:F41)) -> 962703.52 | G42: =IF(COUNT(G30:G41)=0,"",SUM(G30:G41)) -> 967972.72 | H42: =IF(COUNT(H30:H41)=0,"",SUM(H30:H41)) -> 1028097.2 | I42: =IF(COUNT(I30:I41)=0,"",SUM(I30:I41)) -> 1446679 | ... Q42: =IF(COUNT(Q30:Q41)=0,"",SUM(Q30:Q41)) -> 989705.38
A43: FCST 3: enero–agosto corresponden al real de contabilidad; septiembre–diciembre son proyección.
A45: VISTA MENSUAL — REAL Y DIFERENCIA CONTRA CADA PLAN
B46: Cantidad de reefers | F46: Venta USD | J46: Costo USD | N46: Margen USD
A47: Mes | B47: Real | C47: vs Budget | D47: vs FCST 2 | E47: vs FCST 3 | F47: Real | G47: vs Budget | H47: vs FCST 2 | I47: vs FCST 3 | J47: Real | K47: vs Budget | L47: vs FCST 2 | M47: vs FCST 3 | N47: Real | O47: vs Budget | P47: vs FCST 2 | Q47: vs FCST 3
A48: Enero | B48: =IF(E30="","",E30) -> 88 | C48: =IF($B48="","",$B48-B30) -> 8 | D48: =IF($B48="","",$B48-C30) -> 2 | E48: =IF($B48="","",$B48-D30) -> 13 | F48: =IF(I30="","",I30) -> 71088.33 | G48: =IF($F48="","",$F48-F30) -> 16344.32 | H48: =IF($F48="","",$F48-G30) -> 0 | I48: =IF($F48="","",$F48-H30) -> 0 | J48: =IF(M30="","",M30) -> 33912.568 | K48: =IF($J48="","",$J48-J30) -> 5114.8783 | L48: =IF($J48="","",$J48-K30) -> 2018.6683 | M48: =IF($J48="","",$J48-L30) -> 2018.6683 | N48: =IF(Q30="","",Q30) -> 37175.762 | O48: =IF($N48="","",$N48-N30) -> 11229.442 | P48: =IF($N48="","",$N48-O30) -> -2018.6683 | Q48: =IF($N48="","",$N48-P30) -> -2018.6683
A49: Febrero | B49: =IF(E31="","",E31) -> 54 | C49: =IF($B49="","",$B49-B31) -> -26 | D49: =IF($B49="","",$B49-C31) -> -12 | E49: =IF($B49="","",$B49-D31) -> -1 | F49: =IF(I31="","",I31) -> 53916.57 | G49: =IF($F49="","",$F49-F31) -> -827.44 | H49: =IF($F49="","",$F49-G31) -> 0 | I49: =IF($F49="","",$F49-H31) -> 0 | J49: =IF(M31="","",M31) -> 35560.254 | K49: =IF($J49="","",$J49-J31) -> 7582.3343 | L49: =IF($J49="","",$J49-K31) -> -1152.6757 | M49: =IF($J49="","",$J49-L31) -> -1152.6757 | N49: =IF(Q31="","",Q31) -> 18356.316 | O49: =IF($N49="","",$N49-N31) -> -8409.7743 | P49: =IF($N49="","",$N49-O31) -> 1152.6757 | Q49: =IF($N49="","",$N49-P31) -> 1152.6757
A50: Marzo | B50: =IF(E32="","",E32) -> 72 | C50: =IF($B50="","",$B50-B32) -> -27 | D50: =IF($B50="","",$B50-C32) -> -5 | E50: =IF($B50="","",$B50-D32) -> 0 | F50: =IF(I32="","",I32) -> 71738.1 | G50: =IF($F50="","",$F50-F32) -> 3992.39 | H50: =IF($F50="","",$F50-G32) -> 0 | I50: =IF($F50="","",$F50-H32) -> 0 | J50: =IF(M32="","",M32) -> 33704.168 | K50: =IF($J50="","",$J50-J32) -> 3414.5983 | L50: =IF($J50="","",$J50-K32) -> 1843.2783 | M50: =IF($J50="","",$J50-L32) -> 1843.2783 | N50: =IF(Q32="","",Q32) -> 38033.932 | O50: =IF($N50="","",$N50-N32) -> 577.79171 | P50: =IF($N50="","",$N50-O32) -> -1843.2783 | Q50: =IF($N50="","",$N50-P32) -> -1843.2783
A51: Abril | B51: =IF(E33="","",E33) -> 23 | C51: =IF($B51="","",$B51-B33) -> -57 | D51: =IF($B51="","",$B51-C33) -> -8 | E51: =IF($B51="","",$B51-D33) -> 0 | F51: =IF(I33="","",I33) -> 19736 | G51: =IF($F51="","",$F51-F33) -> -35008.01 | H51: =IF($F51="","",$F51-G33) -> 0 | I51: =IF($F51="","",$F51-H33) -> 0 | J51: =IF(M33="","",M33) -> 25525.01 | K51: =IF($J51="","",$J51-J33) -> -2999.4204 | L51: =IF($J51="","",$J51-K33) -> -1020.4104 | M51: =IF($J51="","",$J51-L33) -> -1020.4104 | N51: =IF(Q33="","",Q33) -> -5789.0096 | O51: =IF($N51="","",$N51-N33) -> -32008.59 | P51: =IF($N51="","",$N51-O33) -> 1020.4104 | Q51: =IF($N51="","",$N51-P33) -> 1020.4104
A52: Mayo | B52: =IF(E34="","",E34) -> 47 | C52: =IF($B52="","",$B52-B34) -> -33 | D52: =IF($B52="","",$B52-C34) -> -19 | E52: =IF($B52="","",$B52-D34) -> 0 | F52: =IF(I34="","",I34) -> 41288 | G52: =IF($F52="","",$F52-F34) -> -13456.01 | H52: =IF($F52="","",$F52-G34) -> 0 | I52: =IF($F52="","",$F52-H34) -> 0 | J52: =IF(M34="","",M34) -> 36374.173 | K52: =IF($J52="","",$J52-J34) -> 10717.293 | L52: =IF($J52="","",$J52-K34) -> -612.78666 | M52: =IF($J52="","",$J52-L34) -> -612.78666 | N52: =IF(Q34="","",Q34) -> 4913.8267 | O52: =IF($N52="","",$N52-N34) -> -24173.303 | P52: =IF($N52="","",$N52-O34) -> 612.78666 | Q52: =IF($N52="","",$N52-P34) -> 612.78666
A53: Junio | B53: =IF(E35="","",E35) -> 213 | C53: =IF($B53="","",$B53-B35) -> 14 | D53: =IF($B53="","",$B53-C35) -> 6 | E53: =IF($B53="","",$B53-D35) -> 0 | F53: =IF(I35="","",I35) -> 54592 | G53: =IF($F53="","",$F53-F35) -> -76253.71 | H53: =IF($F53="","",$F53-G35) -> -83080.35 | I53: =IF($F53="","",$F53-H35) -> 0 | J53: =IF(M35="","",M35) -> 32451.087 | K53: =IF($J53="","",$J53-J35) -> -1510.863 | L53: =IF($J53="","",$J53-K35) -> -10107.813 | M53: =IF($J53="","",$J53-L35) -> 1090.177 | N53: =IF(Q35="","",Q35) -> 22140.913 | O53: =IF($N53="","",$N53-N35) -> -74742.847 | P53: =IF($N53="","",$N53-O35) -> -72972.537 | Q53: =IF($N53="","",$N53-P35) -> -1090.177
A54: Julio | B54: =IF(E36="","",E36) -> 547 | C54: =IF($B54="","",$B54-B36) -> 367 | D54: =IF($B54="","",$B54-C36) -> 359 | E54: =IF($B54="","",$B54-D36) -> 0 | F54: =IF(I36="","",I36) -> 198088 | G54: =IF($F54="","",$F54-F36) -> 80243.99 | H54: =IF($F54="","",$F54-G36) -> 73671.73 | I54: =IF($F54="","",$F54-H36) -> 0 | J54: =IF(M36="","",M36) -> 48769.22 | K54: =IF($J54="","",$J54-J36) -> 15652.93 | L54: =IF($J54="","",$J54-K36) -> 7550.5002 | M54: =IF($J54="","",$J54-L36) -> 744.7602 | N54: =IF(Q36="","",Q36) -> 149318.78 | O54: =IF($N54="","",$N54-N36) -> 64591.06 | P54: =IF($N54="","",$N54-O36) -> 66121.23 | Q54: =IF($N54="","",$N54-P36) -> -744.7602
A55: Agosto | B55: =IF(E37="","",E37) -> 751 | C55: =IF($B55="","",$B55-B37) -> 571 | D55: =IF($B55="","",$B55-C37) -> 563 | E55: =IF($B55="","",$B55-D37) -> 402 | F55: =IF(I37="","",I37) -> 305408 | G55: =IF($F55="","",$F55-F37) -> 187563.99 | H55: =IF($F55="","",$F55-G37) -> 180991.73 | I55: =IF($F55="","",$F55-H37) -> 0 | J55: =IF(M37="","",M37) -> 86839.948 | K55: =IF($J55="","",$J55-J37) -> 53723.658 | L55: =IF($J55="","",$J55-K37) -> 45621.228 | M55: =IF($J55="","",$J55-L37) -> 4423.4946 | N55: =IF(Q37="","",Q37) -> 218568.05 | O55: =IF($N55="","",$N55-N37) -> 133840.33 | P55: =IF($N55="","",$N55-O37) -> 135370.5 | Q55: =IF($N55="","",$N55-P37) -> -4423.4946
A56: Septiembre | B56: =IF(E38="","",E38) -> 1151 | C56: =IF($B56="","",$B56-B38) -> 952 | D56: =IF($B56="","",$B56-C38) -> 943 | E56: =IF($B56="","",$B56-D38) -> 835 | F56: =IF(I38="","",I38) -> 630824 | G56: =IF($F56="","",$F56-F38) -> 499978.29 | H56: =IF($F56="","",$F56-G38) -> 492453.96 | I56: =IF($F56="","",$F56-H38) -> 519858.19 | J56: =IF(M38="","",M38) -> 123837.19 | K56: =IF($J56="","",$J56-J38) -> 89875.24 | L56: =IF($J56="","",$J56-K38) -> 81191.81 | M56: =IF($J56="","",$J56-L38) -> 72053.886 | N56: =IF(Q38="","",Q38) -> 506986.81 | O56: =IF($N56="","",$N56-N38) -> 410103.05 | P56: =IF($N56="","",$N56-O38) -> 411262.15 | Q56: =IF($N56="","",$N56-P38) -> 447804.31
A57: Octubre | B57: =IF(E39="","",E39) | C57: =IF($B57="","",$B57-B39) | D57: =IF($B57="","",$B57-C39) | E57: =IF($B57="","",$B57-D39) | F57: =IF(I39="","",I39) | G57: =IF($F57="","",$F57-F39) | H57: =IF($F57="","",$F57-G39) | I57: =IF($F57="","",$F57-H39) | J57: =IF(M39="","",M39) | K57: =IF($J57="","",$J57-J39) | L57: =IF($J57="","",$J57-K39) | M57: =IF($J57="","",$J57-L39) | N57: =IF(Q39="","",Q39) | O57: =IF($N57="","",$N57-N39) | P57: =IF($N57="","",$N57-O39) | Q57: =IF($N57="","",$N57-P39)
A58: Noviembre | B58: =IF(E40="","",E40) | C58: =IF($B58="","",$B58-B40) | D58: =IF($B58="","",$B58-C40) | E58: =IF($B58="","",$B58-D40) | F58: =IF(I40="","",I40) | G58: =IF($F58="","",$F58-F40) | H58: =IF($F58="","",$F58-G40) | I58: =IF($F58="","",$F58-H40) | J58: =IF(M40="","",M40) | K58: =IF($J58="","",$J58-J40) | L58: =IF($J58="","",$J58-K40) | M58: =IF($J58="","",$J58-L40) | N58: =IF(Q40="","",Q40) | O58: =IF($N58="","",$N58-N40) | P58: =IF($N58="","",$N58-O40) | Q58: =IF($N58="","",$N58-P40)
A59: Diciembre | B59: =IF(E41="","",E41) | C59: =IF($B59="","",$B59-B41) | D59: =IF($B59="","",$B59-C41) | E59: =IF($B59="","",$B59-D41) | F59: =IF(I41="","",I41) | G59: =IF($F59="","",$F59-F41) | H59: =IF($F59="","",$F59-G41) | I59: =IF($F59="","",$F59-H41) | J59: =IF(M41="","",M41) | K59: =IF($J59="","",$J59-J41) | L59: =IF($J59="","",$J59-K41) | M59: =IF($J59="","",$J59-L41) | N59: =IF(Q41="","",Q41) | O59: =IF($N59="","",$N59-N41) | P59: =IF($N59="","",$N59-O41) | Q59: =IF($N59="","",$N59-P41)
A60: Acum. con real | B60: =SUM(B48:B59) -> 2946 | C60: =SUM(C48:C59) -> 1769 | D60: =SUM(D48:D59) -> 1829 | E60: =SUM(E48:E59) -> 1249 | F60: =SUM(F48:F59) -> 1446679 | G60: =SUM(G48:G59) -> 662577.81 | H60: =SUM(H48:H59) -> 664037.07 | I60: =SUM(I48:I59) -> 519858.19 | ... Q60: =SUM(Q48:Q59) -> 440469.8

Sheet NAVES
A1: REEFERS, ESTADÍA Y COSTOS ASIGNADOS POR NAVE
A2: Costos reales PPK y SITRANS por nave. El combustible permanece únicamente a nivel mensual.
A4: Usa los filtros para elegir mes, línea o nave. “EDP válidos” muestra la cobertura usada para calcular la estadía.
A6: Mes | B6: CI | C6: Línea | D6: Nave | E6: Reefers | F6: EDP válidos | G6: Estadía prom. días | H6: Estado EDP | I6: SITRANS asignado CLP | J6: PPK asignado CLP | K6: Total asignado CLP | L6: CLP/reefer | M6: Correlativo | N6: Venta reefer USD | P6: Aux vista mes
A7: Enero | B7: 8263 | C7: HAPAG LLOYD / ON | D7: ONE SAPHIRE | E7: 29 | F7: 29 | G7: 6.0994732 | H7: Disponible | I7: =IFERROR(IF(E7="","",E7*INDEX(ACTUALIZAR!$C$7:$C$18,MATCH(A7,ACTUALIZAR!$A$7:$A$18,0))/SUMIF($A$7:$A$200,A7,$E$7:$E$200)),"") -> 4257158.1 | J7: =IFERROR(IF(E7="","",E7*INDEX(PPK!$F$7:$F$18,MATCH(A7,PPK!$A$7:$A$18,0))/SUMIF($A$7:$A$200,A7,$E$7:$E$200)),"") -> 3135553.8 | K7: =IF(AND(I7="",J7=""),"",SUM(I7:J7)) -> 7392712 | L7: =IFERROR(K7/E7,"") -> 254921.1 | M7: 2025-313 | N7: 29336 | P7: =IF($A7='VISTA MES'!$B$4,COUNTIF($A$7:$A7,'VISTA MES'!$B$4),"")
A8: Enero | B8: 8268 | C8: HAPAG LLOYD / MSC / ON | D8: MONTEVIDEO EXPRESS | E8: 16 | F8: 16 | G8: 6.1142361 | H8: Disponible | I8: =IFERROR(IF(E8="","",E8*INDEX(ACTUALIZAR!$C$7:$C$18,MATCH(A8,ACTUALIZAR!$A$7:$A$18,0))/SUMIF($A$7:$A$200,A8,$E$7:$E$200)),"") -> 2348776.9 | J8: =IFERROR(IF(E8="","",E8*INDEX(PPK!$F$7:$F$18,MATCH(A8,PPK!$A$7:$A$18,0))/SUMIF($A$7:$A$200,A8,$E$7:$E$200)),"") -> 1729960.7 | K8: =IF(AND(I8="",J8=""),"",SUM(I8:J8)) -> 4078737.6 | L8: =IFERROR(K8/E8,"") -> 254921.1 | M8: 2025-322 | N8: 15264 | P8: =IF($A8='VISTA MES'!$B$4,COUNTIF($A$7:$A8,'VISTA MES'!$B$4),"")
A9: Enero | B9: 8273 | C9: HAPAG LLOYD / ON | D9: ONE SPHERE | E9: 8 | F9: 7 | G9: 7.6922619 | H9: Disponible | I9: =IFERROR(IF(E9="","",E9*INDEX(ACTUALIZAR!$C$7:$C$18,MATCH(A9,ACTUALIZAR!$A$7:$A$18,0))/SUMIF($A$7:$A$200,A9,$E$7:$E$200)),"") -> 1174388.5 | J9: =IFERROR(IF(E9="","",E9*INDEX(PPK!$F$7:$F$18,MATCH(A9,PPK!$A$7:$A$18,0))/SUMIF($A$7:$A$200,A9,$E$7:$E$200)),"") -> 864980.36 | K9: =IF(AND(I9="",J9=""),"",SUM(I9:J9)) -> 2039368.8 | L9: =IFERROR(K9/E9,"") -> 254921.1 | M9: 2026-7 | N9: 6960 | P9: =IF($A9='VISTA MES'!$B$4,COUNTIF($A$7:$A9,'VISTA MES'!$B$4),"")
A10: Enero | B10: 8278 | C10: HAPAG LLOYD / MSC / ON | D10: HMM BLESSING | E10: 23 | F10: 22 | G10: 6.0719381 | H10: Disponible | I10: =IFERROR(IF(E10="","",E10*INDEX(ACTUALIZAR!$C$7:$C$18,MATCH(A10,ACTUALIZAR!$A$7:$A$18,0))/SUMIF($A$7:$A$200,A10,$E$7:$E$200)),"") -> 3376366.8 | J10: =IFERROR(IF(E10="","",E10*INDEX(PPK!$F$7:$F$18,MATCH(A10,PPK!$A$7:$A$18,0))/SUMIF($A$7:$A$200,A10,$E$7:$E$200)),"") -> 2486818.5 | K10: =IF(AND(I10="",J10=""),"",SUM(I10:J10)) -> 5863185.4 | L10: =IFERROR(K10/E10,"") -> 254921.1 | M10: 2026-9 | N10: 19056.33 | P10: =IF($A10='VISTA MES'!$B$4,COUNTIF($A$7:$A10,'VISTA MES'!$B$4),"")
A11: Enero | B11: 8262 | C11: MAERSK | D11: POLAR ARGENTINA | E11: 1 | H11: Sin registro | I11: =IFERROR(IF(E11="","",E11*INDEX(ACTUALIZAR!$C$7:$C$18,MATCH(A11,ACTUALIZAR!$A$7:$A$18,0))/SUMIF($A$7:$A$200,A11,$E$7:$E$200)),"") -> 146798.56 | J11: =IFERROR(IF(E11="","",E11*INDEX(PPK!$F$7:$F$18,MATCH(A11,PPK!$A$7:$A$18,0))/SUMIF($A$7:$A$200,A11,$E$7:$E$200)),"") -> 108122.55 | K11: =IF(AND(I11="",J11=""),"",SUM(I11:J11)) -> 254921.1 | L11: =IFERROR(K11/E11,"") -> 254921.1 | N11: 0 | P11: =IF($A11='VISTA MES'!$B$4,COUNTIF($A$7:$A11,'VISTA MES'!$B$4),"")
A12: Enero | B12: 8267 | C12: MAERSK | D12: POLAR PERU | E12: 1 | H12: Sin registro | I12: =IFERROR(IF(E12="","",E12*INDEX(ACTUALIZAR!$C$7:$C$18,MATCH(A12,ACTUALIZAR!$A$7:$A$18,0))/SUMIF($A$7:$A$200,A12,$E$7:$E$200)),"") -> 146798.56 | J12: =IFERROR(IF(E12="","",E12*INDEX(PPK!$F$7:$F$18,MATCH(A12,PPK!$A$7:$A$18,0))/SUMIF($A$7:$A$200,A12,$E$7:$E$200)),"") -> 108122.55 | K12: =IF(AND(I12="",J12=""),"",SUM(I12:J12)) -> 254921.1 | L12: =IFERROR(K12/E12,"") -> 254921.1 | N12: 0 | P12: =IF($A12='VISTA MES'!$B$4,COUNTIF($A$7:$A12,'VISTA MES'!$B$4),"")
A13: Enero | B13: 8271 | C13: MAERSK | D13: POLAR COLOMBIA | E13: 1 | F13: 1 | G13: 1.3145833 | H13: Disponible | I13: =IFERROR(IF(E13="","",E13*INDEX(ACTUALIZAR!$C$7:$C$18,MATCH(A13,ACTUALIZAR!$A$7:$A$18,0))/SUMIF($A$7:$A$200,A13,$E$7:$E$200)),"") -> 146798.56 | J13: =IFERROR(IF(E13="","",E13*INDEX(PPK!$F$7:$F$18,MATCH(A13,PPK!$A$7:$A$18,0))/SUMIF($A$7:$A$200,A13,$E$7:$E$200)),"") -> 108122.55 | K13: =IF(AND(I13="",J13=""),"",SUM(I13:J13)) -> 254921.1 | L13: =IFERROR(K13/E13,"") -> 254921.1 | M13: 2025-319 | N13: 472 | P13: =IF($A13='VISTA MES'!$B$4,COUNTIF($A$7:$A13,'VISTA MES'!$B$4),"")
A14: Enero | B14: 8277 | C14: MAERSK | D14: POLAR CHILE | E14: 1 | H14: Sin registro | I14: =IFERROR(IF(E14="","",E14*INDEX(ACTUALIZAR!$C$7:$C$18,MATCH(A14,ACTUALIZAR!$A$7:$A$18,0))/SUMIF($A$7:$A$200,A14,$E$7:$E$200)),"") -> 146798.56 | J14: =IFERROR(IF(E14="","",E14*INDEX(PPK!$F$7:$F$18,MATCH(A14,PPK!$A$7:$A$18,0))/SUMIF($A$7:$A$200,A14,$E$7:$E$200)),"") -> 108122.55 | K14: =IF(AND(I14="",J14=""),"",SUM(I14:J14)) -> 254921.1 | L14: =IFERROR(K14/E14,"") -> 254921.1 | N14: 0 | P14: =IF($A14='VISTA MES'!$B$4,COUNTIF($A$7:$A14,'VISTA MES'!$B$4),"")
A15: Enero | B15: 8282 | C15: MAERSK | D15: POLAR ARGENTINA | E15: 2 | H15: Sin registro | I15: =IFERROR(IF(E15="","",E15*INDEX(ACTUALIZAR!$C$7:$C$18,MATCH(A15,ACTUALIZAR!$A$7:$A$18,0))/SUMIF($A$7:$A$200,A15,$E$7:$E$200)),"") -> 293597.11 | J15: =IFERROR(IF(E15="","",E15*INDEX(PPK!$F$7:$F$18,MATCH(A15,PPK!$A$7:$A$18,0))/SUMIF($A$7:$A$200,A15,$E$7:$E$200)),"") -> 216245.09 | K15: =IF(AND(I15="",J15=""),"",SUM(I15:J15)) -> 509842.2 | L15: =IFERROR(K15/E15,"") -> 254921.1 | N15: 0 | P15: =IF($A15='VISTA MES'!$B$4,COUNTIF($A$7:$A15,'VISTA MES'!$B$4),"")
A16: Enero | B16: 8261 | C16: Pendiente | D16: LITTLE GRACE | E16: 2 | H16: Sin registro | I16: =IFERROR(IF(E16="","",E16*INDEX(ACTUALIZAR!$C$7:$C$18,MATCH(A16,ACTUALIZAR!$A$7:$A$18,0))/SUMIF($A$7:$A$200,A16,$E$7:$E$200)),"") -> 293597.11 | J16: =IFERROR(IF(E16="","",E16*INDEX(PPK!$F$7:$F$18,MATCH(A16,PPK!$A$7:$A$18,0))/SUMIF($A$7:$A$200,A16,$E$7:$E$200)),"") -> 216245.09 | K16: =IF(AND(I16="",J16=""),"",SUM(I16:J16)) -> 509842.2 | L16: =IFERROR(K16/E16,"") -> 254921.1 | N16: 0 | P16: =IF($A16='VISTA MES'!$B$4,COUNTIF($A$7:$A16,'VISTA MES'!$B$4),"")
A17: Enero | B17: 8265 | C17: HAPAG LLOYD | D17: CAPE BRUNO | E17: 1 | H17: Sin registro | I17: =IFERROR(IF(E17="","",E17*INDEX(ACTUALIZAR!$C$7:$C$18,MATCH(A17,ACTUALIZAR!$A$7:$A$18,0))/SUMIF($A$7:$A$200,A17,$E$7:$E$200)),"") -> 146798.56 | J17: =IFERROR(IF(E17="","",E17*INDEX(PPK!$F$7:$F$18,MATCH(A17,PPK!$A$7:$A$18,0))/SUMIF($A$7:$A$200,A17,$E$7:$E$200)),"") -> 108122.55 | K17: =IF(AND(I17="",J17=""),"",SUM(I17:J17)) -> 254921.1 | L17: =IFERROR(K17/E17,"") -> 254921.1 | N17: 0 | P17: =IF($A17='VISTA MES'!$B$4,COUNTIF($A$7:$A17,'VISTA MES'!$B$4),"")
A18: Enero | B18: 8275 | C18: HAPAG LLOYD | D18: CAPE BRUNO | E18: 3 | H18: Sin registro | I18: =IFERROR(IF(E18="","",E18*INDEX(ACTUALIZAR!$C$7:$C$18,MATCH(A18,ACTUALIZAR!$A$7:$A$18,0))/SUMIF($A$7:$A$200,A18,$E$7:$E$200)),"") -> 440395.67 | J18: =IFERROR(IF(E18="","",E18*INDEX(PPK!$F$7:$F$18,MATCH(A18,PPK!$A$7:$A$18,0))/SUMIF($A$7:$A$200,A18,$E$7:$E$200)),"") -> 324367.64 | K18: =IF(AND(I18="",J18=""),"",SUM(I18:J18)) -> 764763.31 | L18: =IFERROR(K18/E18,"") -> 254921.1 | N18: 0 | P18: =IF($A18='VISTA MES'!$B$4,COUNTIF($A$7:$A18,'VISTA MES'!$B$4),"")
A19: Febrero | B19: 8283 | C19: ON | D19: MANZANILLO EXPRESS | E19: 13 | F19: 13 | G19: 35.445032 | H19: Disponible | I19: =IFERROR(IF(E19="","",E19*INDEX(ACTUALIZAR!$C$7:$C$18,MATCH(A19,ACTUALIZAR!$A$7:$A$18,0))/SUMIF($A$7:$A$200,A19,$E$7:$E$200)),"") -> 3109954.6 | J19: =IFERROR(IF(E19="","",E19*INDEX(PPK!$F$7:$F$18,MATCH(A19,PPK!$A$7:$A$18,0))/SUMIF($A$7:$A$200,A19,$E$7:$E$200)),"") -> 2488534.9 | K19: =IF(AND(I19="",J19=""),"",SUM(I19:J19)) -> 5598489.5 | L19: =IFERROR(K19/E19,"") -> 430653.04 | M19: 2026-10 | N19: 13128 | P19: =IF($A19='VISTA MES'!$B$4,COUNTIF($A$7:$A19,'VISTA MES'!$B$4),"")
A20: Febrero | B20: 8288 | C20: HAPAG LLOYD / ON | D20: ITAJAI EXPRESS | E20: 8 | F20: 8 | G20: 6.4684028 | H20: Disponible | I20: =IFERROR(IF(E20="","",E20*INDEX(ACTUALIZAR!$C$7:$C$18,MATCH(A20,ACTUALIZAR!$A$7:$A$18,0))/SUMIF($A$7:$A$200,A20,$E$7:$E$200)),"") -> 1913818.2 | J20: =IFERROR(IF(E20="","",E20*INDEX(PPK!$F$7:$F$18,MATCH(A20,PPK!$A$7:$A$18,0))/SUMIF($A$7:$A$200,A20,$E$7:$E$200)),"") -> 1531406.1 | K20: =IF(AND(I20="",J20=""),"",SUM(I20:J20)) -> 3445224.3 | L20: =IFERROR(K20/E20,"") -> 430653.04 | M20: 2026-17 | N20: 8288 | P20: =IF($A20='VISTA MES'!$B$4,COUNTIF($A$7:$A20,'VISTA MES'!$B$4),"")
A21: Febrero | B21: 8293 | C21: HAPAG LLOYD / MSC / ON | D21: RIO DE JANEIRO EXPRESS | E21: 13 | F21: 13 | G21: 8.5551816 | H21: Disponible | I21: =IFERROR(IF(E21="","",E21*INDEX(ACTUALIZAR!$C$7:$C$18,MATCH(A21,ACTUALIZAR!$A$7:$A$18,0))/SUMIF($A$7:$A$200,A21,$E$7:$E$200)),"") -> 3109954.6 | J21: =IFERROR(IF(E21="","",E21*INDEX(PPK!$F$7:$F$18,MATCH(A21,PPK!$A$7:$A$18,0))/SUMIF($A$7:$A$200,A21,$E$7:$E$200)),"") -> 2488534.9 | K21: =IF(AND(I21="",J21=""),"",SUM(I21:J21)) -> 5598489.5 | L21: =IFERROR(K21/E21,"") -> 430653.04 | M21: 2026-28 | N21: 13568 | P21: =IF($A21='VISTA MES'!$B$4,COUNTIF($A$7:$A21,'VISTA MES'!$B$4),"")
A22: Febrero | B22: 8299 | C22: HAPAG LLOYD / ON | D22: BUENAVENTURA EXPRESS | E22: 16 | F22: 12 | G22: 9.1368056 | H22: Parcial | I22: =IFERROR(IF(E22="","",E22*INDEX(ACTUALIZAR!$C$7:$C$18,MATCH(A22,ACTUALIZAR!$A$7:$A$18,0))/SUMIF($A$7:$A$200,A22,$E$7:$E$200)),"") -> 3827636.4 | J22: =IFERROR(IF(E22="","",E22*INDEX(PPK!$F$7:$F$18,MATCH(A22,PPK!$A$7:$A$18,0))/SUMIF($A$7:$A$200,A22,$E$7:$E$200)),"") -> 3062812.1 | K22: =IF(AND(I22="",J22=""),"",SUM(I22:J22)) -> 6890448.6 | L22: =IFERROR(K22/E22,"") -> 430653.04 | M22: 2026-34 | N22: 16384 | P22: =IF($A22='VISTA MES'!$B$4,COUNTIF($A$7:$A22,'VISTA MES'!$B$4),"")
A23: Febrero | B23: 8292 | C23: MAERSK | D23: POLAR COLOMBIA | E23: 2 | F23: 2 | G23: 2.1670139 | H23: Disponible | I23: =IFERROR(IF(E23="","",E23*INDEX(ACTUALIZAR!$C$7:$C$18,MATCH(A23,ACTUALIZAR!$A$7:$A$18,0))/SUMIF($A$7:$A$200,A23,$E$7:$E$200)),"") -> 478454.56 | J23: =IFERROR(IF(E23="","",E23*INDEX(PPK!$F$7:$F$18,MATCH(A23,PPK!$A$7:$A$18,0))/SUMIF($A$7:$A$200,A23,$E$7:$E$200)),"") -> 382851.52 | K23: =IF(AND(I23="",J23=""),"",SUM(I23:J23)) -> 861306.07 | L23: =IFERROR(K23/E23,"") -> 430653.04 | M23: 2026-30 | N23: 1012.57 | P23: =IF($A23='VISTA MES'!$B$4,COUNTIF($A$7:$A23,'VISTA MES'!$B$4),"")
A24: Febrero | B24: 8295 | C24: HAPAG LLOYD | D24: CAPE BRUNO | E24: 2 | F24: 1 | G24: 2.1340278 | H24: Parcial | I24: =IFERROR(IF(E24="","",E24*INDEX(ACTUALIZAR!$C$7:$C$18,MATCH(A24,ACTUALIZAR!$A$7:$A$18,0))/SUMIF($A$7:$A$200,A24,$E$7:$E$200)),"") -> 478454.56 | J24: =IFERROR(IF(E24="","",E24*INDEX(PPK!$F$7:$F$18,MATCH(A24,PPK!$A$7:$A$18,0))/SUMIF($A$7:$A$200,A24,$E$7:$E$200)),"") -> 382851.52 | K24: =IF(AND(I24="",J24=""),"",SUM(I24:J24)) -> 861306.07 | L24: =IFERROR(K24/E24,"") -> 430653.04 | M24: 2026-16 | N24: 1024 | P24: =IF($A24='VISTA MES'!$B$4,COUNTIF($A$7:$A24,'VISTA MES'!$B$4),"")
A25: Febrero | C25: MAERSK | D25: POLAR ARGENTINA | F25: 1 | G25: 6.8638889 | H25: Disponible (solo EDP) | I25: =IFERROR(IF(E25="","",E25*INDEX(ACTUALIZAR!$C$7:$C$18,MATCH(A25,ACTUALIZAR!$A$7:$A$18,0))/SUMIF($A$7:$A$200,A25,$E$7:$E$200)),"") | J25: =IFERROR(IF(E25="","",E25*INDEX(PPK!$F$7:$F$18,MATCH(A25,PPK!$A$7:$A$18,0))/SUMIF($A$7:$A$200,A25,$E$7:$E$200)),"") | K25: =IF(AND(I25="",J25=""),"",SUM(I25:J25)) | L25: =IFERROR(K25/E25,"") | M25: 2026-45 | N25: 512 | P25: =IF($A25='VISTA MES'!$B$4,COUNTIF($A$7:$A25,'VISTA MES'!$B$4),"")
A26: Marzo | B26: 8304 | C26: HAPAG LLOYD / ON | D26: LIMA EXPRESS | E26: 20 | F26: 20 | G26: 5.7558333 | H26: Disponible | I26: =IFERROR(IF(E26="","",E26*INDEX(ACTUALIZAR!$C$7:$C$18,MATCH(A26,ACTUALIZAR!$A$7:$A$18,0))/SUMIF($A$7:$A$200,A26,$E$7:$E$200)),"") -> 3588409.2 | J26: =IFERROR(IF(E26="","",E26*INDEX(PPK!$F$7:$F$18,MATCH(A26,PPK!$A$7:$A$18,0))/SUMIF($A$7:$A$200,A26,$E$7:$E$200)),"") -> 2642995.6 | K26: =IF(AND(I26="",J26=""),"",SUM(I26:J26)) -> 6231404.7 | L26: =IFERROR(K26/E26,"") -> 311570.24 | M26: 2026-36 | N26: 17616 | P26: =IF($A26='VISTA MES'!$B$4,COUNTIF($A$7:$A26,'VISTA MES'!$B$4),"")
A27: Marzo | B27: 8313 | C27: HAPAG LLOYD / ON | D27: HUMBOLDT EXPRESS | E27: 21 | F27: 21 | G27: 8.0509921 | H27: Disponible | I27: =IFERROR(IF(E27="","",E27*INDEX(ACTUALIZAR!$C$7:$C$18,MATCH(A27,ACTUALIZAR!$A$7:$A$18,0))/SUMIF($A$7:$A$200,A27,$E$7:$E$200)),"") -> 3767829.6 | J27: =IFERROR(IF(E27="","",E27*INDEX(PPK!$F$7:$F$18,MATCH(A27,PPK!$A$7:$A$18,0))/SUMIF($A$7:$A$200,A27,$E$7:$E$200)),"") -> 2775145.3 | K27: =IF(AND(I27="",J27=""),"",SUM(I27:J27)) -> 6542975 | L27: =IFERROR(K27/E27,"") -> 311570.24 | M27: 2026-38 | N27: 22344 | P27: =IF($A27='VISTA MES'!$B$4,COUNTIF($A$7:$A27,'VISTA MES'!$B$4),"")
A28: Marzo | B28: 8318 | C28: HAPAG LLOYD / ON | D28: ONE SINCERITY | E28: 16 | F28: 16 | G28: 10.436502 | H28: Disponible | I28: =IFERROR(IF(E28="","",E28*INDEX(ACTUALIZAR!$C$7:$C$18,MATCH(A28,ACTUALIZAR!$A$7:$A$18,0))/SUMIF($A$7:$A$200,A28,$E$7:$E$200)),"") -> 2870727.3 | J28: =IFERROR(IF(E28="","",E28*INDEX(PPK!$F$7:$F$18,MATCH(A28,PPK!$A$7:$A$18,0))/SUMIF($A$7:$A$200,A28,$E$7:$E$200)),"") -> 2114396.4 | K28: =IF(AND(I28="",J28=""),"",SUM(I28:J28)) -> 4985123.8 | L28: =IFERROR(K28/E28,"") -> 311570.24 | M28: 2026-40 | N28: 16608 | P28: =IF($A28='VISTA MES'!$B$4,COUNTIF($A$7:$A28,'VISTA MES'!$B$4),"")
A29: Marzo | B29: 8322 | C29: HAPAG LLOYD / ON | D29: ONE SAPHIRE | E29: 10 | F29: 10 | G29: 9.0853472 | H29: Disponible | I29: =IFERROR(IF(E29="","",E29*INDEX(ACTUALIZAR!$C$7:$C$18,MATCH(A29,ACTUALIZAR!$A$7:$A$18,0))/SUMIF($A$7:$A$200,A29,$E$7:$E$200)),"") -> 1794204.6 | J29: =IFERROR(IF(E29="","",E29*INDEX(PPK!$F$7:$F$18,MATCH(A29,PPK!$A$7:$A$18,0))/SUMIF($A$7:$A$200,A29,$E$7:$E$200)),"") -> 1321497.8 | K29: =IF(AND(I29="",J29=""),"",SUM(I29:J29)) -> 3115702.4 | L29: =IFERROR(K29/E29,"") -> 311570.24 | M29: 2026-41 | N29: 10578.1 | P29: =IF($A29='VISTA MES'!$B$4,COUNTIF($A$7:$A29,'VISTA MES'!$B$4),"")
A30: Marzo | B30: 8311 | C30: MAERSK | D30: POLAR COLOMBIA | E30: 1 | F30: 1 | G30: 11.527083 | H30: Disponible | I30: =IFERROR(IF(E30="","",E30*INDEX(ACTUALIZAR!$C$7:$C$18,MATCH(A30,ACTUALIZAR!$A$7:$A$18,0))/SUMIF($A$7:$A$200,A30,$E$7:$E$200)),"") -> 179420.46 | J30: =IFERROR(IF(E30="","",E30*INDEX(PPK!$F$7:$F$18,MATCH(A30,PPK!$A$7:$A$18,0))/SUMIF($A$7:$A$200,A30,$E$7:$E$200)),"") -> 132149.78 | K30: =IF(AND(I30="",J30=""),"",SUM(I30:J30)) -> 311570.24 | L30: =IFERROR(K30/E30,"") -> 311570.24 | M30: 2026-50 | N30: 984 | P30: =IF($A30='VISTA MES'!$B$4,COUNTIF($A$7:$A30,'VISTA MES'!$B$4),"")
A31: Marzo | B31: 8308 | C31: CMA CGM | D31: MEDKON DON | E31: 3 | F31: 3 | G31: 8.9578704 | H31: Disponible | I31: =IFERROR(IF(E31="","",E31*INDEX(ACTUALIZAR!$C$7:$C$18,MATCH(A31,ACTUALIZAR!$A$7:$A$18,0))/SUMIF($A$7:$A$200,A31,$E$7:$E$200)),"") -> 538261.38 | J31: =IFERROR(IF(E31="","",E31*INDEX(PPK!$F$7:$F$18,MATCH(A31,PPK!$A$7:$A$18,0))/SUMIF($A$7:$A$200,A31,$E$7:$E$200)),"") -> 396449.33 | K31: =IF(AND(I31="",J31=""),"",SUM(I31:J31)) -> 934710.71 | L31: =IFERROR(K31/E31,"") -> 311570.24 | M31: 2026-52 | N31: 2952 | P31: =IF($A31='VISTA MES'!$B$4,COUNTIF($A$7:$A31,'VISTA MES'!$B$4),"")
A32: Marzo | B32: 8315 | C32: MSC | D32: MSC ANZU | E32: 1 | F32: 1 | G32: 5.0444444 | H32: Disponible | I32: =IFERROR(IF(E32="","",E32*INDEX(ACTUALIZAR!$C$7:$C$18,MATCH(A32,ACTUALIZAR!$A$7:$A$18,0))/SUMIF($A$7:$A$200,A32,$E$7:$E$200)),"") -> 179420.46 | J32: =IFERROR(IF(E32="","",E32*INDEX(PPK!$F$7:$F$18,MATCH(A32,PPK!$A$7:$A$18,0))/SUMIF($A$7:$A$200,A32,$E$7:$E$200)),"") -> 132149.78 | K32: =IF(AND(I32="",J32=""),"",SUM(I32:J32)) -> 311570.24 | L32: =IFERROR(K32/E32,"") -> 311570.24 | M32: 2026-56 | N32: 656 | P32: =IF($A32='VISTA MES'!$B$4,COUNTIF($A$7:$A32,'VISTA MES'!$B$4),"")
A33: Abril | B33: 8327 | C33: HAPAG LLOYD / ON | D33: MONTEVIDEO EXPRESS | E33: 8 | F33: 8 | G33: 7.8615451 | H33: Disponible | I33: =IFERROR(IF(E33="","",E33*INDEX(ACTUALIZAR!$C$7:$C$18,MATCH(A33,ACTUALIZAR!$A$7:$A$18,0))/SUMIF($A$7:$A$200,A33,$E$7:$E$200)),"") -> 4493312.3 | J33: =IFERROR(IF(E33="","",E33*INDEX(PPK!$F$7:$F$18,MATCH(A33,PPK!$A$7:$A$18,0))/SUMIF($A$7:$A$200,A33,$E$7:$E$200)),"") -> 3214161.7 | K33: =IF(AND(I33="",J33=""),"",SUM(I33:J33)) -> 7707474.1 | L33: =IFERROR(K33/E33,"") -> 963434.26 | M33: 2026-68 | N33: 7280 | P33: =IF($A33='VISTA MES'!$B$4,COUNTIF($A$7:$A33,'VISTA MES'!$B$4),"")
A34: Abril | B34: 8331 | C34: ON | D34: ONE SPHERE | E34: 3 | F34: 3 | G34: 7.7435185 | H34: Disponible | I34: =IFERROR(IF(E34="","",E34*INDEX(ACTUALIZAR!$C$7:$C$18,MATCH(A34,ACTUALIZAR!$A$7:$A$18,0))/SUMIF($A$7:$A$200,A34,$E$7:$E$200)),"") -> 1684992.1 | J34: =IFERROR(IF(E34="","",E34*INDEX(PPK!$F$7:$F$18,MATCH(A34,PPK!$A$7:$A$18,0))/SUMIF($A$7:$A$200,A34,$E$7:$E$200)),"") -> 1205310.7 | K34: =IF(AND(I34="",J34=""),"",SUM(I34:J34)) -> 2890302.8 | L34: =IFERROR(K34/E34,"") -> 963434.26 | M34: 2026-72 | N34: 2664 | P34: =IF($A34='VISTA MES'!$B$4,COUNTIF($A$7:$A34,'VISTA MES'!$B$4),"")
A35: Abril | B35: 8333 | C35: HAPAG LLOYD | D35: CAPE BRUNO | E35: 1 | F35: 1 | G35: 3.09375 | H35: Disponible | I35: =IFERROR(IF(E35="","",E35*INDEX(ACTUALIZAR!$C$7:$C$18,MATCH(A35,ACTUALIZAR!$A$7:$A$18,0))/SUMIF($A$7:$A$200,A35,$E$7:$E$200)),"") -> 561664.04 | J35: =IFERROR(IF(E35="","",E35*INDEX(PPK!$F$7:$F$18,MATCH(A35,PPK!$A$7:$A$18,0))/SUMIF($A$7:$A$200,A35,$E$7:$E$200)),"") -> 401770.22 | K35: =IF(AND(I35="",J35=""),"",SUM(I35:J35)) -> 963434.26 | L35: =IFERROR(K35/E35,"") -> 963434.26 | M35: 2026-79 | N35: 656 | P35: =IF($A35='VISTA MES'!$B$4,COUNTIF($A$7:$A35,'VISTA MES'!$B$4),"")
A36: Abril | B36: 8336 | C36: ON | D36: HMM BLESSING | E36: 8 | F36: 8 | G36: 5.3175347 | H36: Disponible | I36: =IFERROR(IF(E36="","",E36*INDEX(ACTUALIZAR!$C$7:$C$18,MATCH(A36,ACTUALIZAR!$A$7:$A$18,0))/SUMIF($A$7:$A$200,A36,$E$7:$E$200)),"") -> 4493312.3 | J36: =IFERROR(IF(E36="","",E36*INDEX(PPK!$F$7:$F$18,MATCH(A36,PPK!$A$7:$A$18,0))/SUMIF($A$7:$A$200,A36,$E$7:$E$200)),"") -> 3214161.7 | K36: =IF(AND(I36="",J36=""),"",SUM(I36:J36)) -> 7707474.1 | L36: =IFERROR(K36/E36,"") -> 963434.26 | M36: 2026-80 | N36: 6776 | P36: =IF($A36='VISTA MES'!$B$4,COUNTIF($A$7:$A36,'VISTA MES'!$B$4),"")
A37: Abril | B37: 8341 | C37: ON | D37: MANZANILLO EXPRESS | E37: 2 | F37: 2 | G37: 5.1760417 | H37: Disponible | I37: =IFERROR(IF(E37="","",E37*INDEX(ACTUALIZAR!$C$7:$C$18,MATCH(A37,ACTUALIZAR!$A$7:$A$18,0))/SUMIF($A$7:$A$200,A37,$E$7:$E$200)),"") -> 1123328.1 | J37: =IFERROR(IF(E37="","",E37*INDEX(PPK!$F$7:$F$18,MATCH(A37,PPK!$A$7:$A$18,0))/SUMIF($A$7:$A$200,A37,$E$7:$E$200)),"") -> 803540.43 | K37: =IF(AND(I37="",J37=""),"",SUM(I37:J37)) -> 1926868.5 | L37: =IFERROR(K37/E37,"") -> 963434.26 | M37: 2026-84 | N37: 1968 | P37: =IF($A37='VISTA MES'!$B$4,COUNTIF($A$7:$A37,'VISTA MES'!$B$4),"")
... A58: Julio | B58: 8395 | C58: MAERSK | D58: POLAR CHILE | E58: 8 | F58: 8 | G58: 5.4197917 | H58: Disponible | I58: =IFERROR(IF(E58="","",E58*INDEX(ACTUALIZAR!$C$7:$C$18,MATCH(A58,ACTUALIZAR!$A$7:$A$18,0))/SUMIF($A$7:$A$200,A58,$E$7:$E$200)),"") -> 198697.89 | J58: =IFERROR(IF(E58="","",E58*INDEX(PPK!$F$7:$F$18,MATCH(A58,PPK!$A$7:$A$18,0))/SUMIF($A$7:$A$200,A58,$E$7:$E$200)),"") -> 155189.21 | K58: =IF(AND(I58="",J58=""),"",SUM(I58:J58)) -> 353887.1 | L58: =IFERROR(K58/E58,"") -> 44235.887 | M58: 2026-139 | N58: 3896 | P58: =IF($A58='VISTA MES'!$B$4,COUNTIF($A$7:$A58,'VISTA MES'!$B$4),"")
A59: Julio | B59: 8394 | C59: MSC | D59: CATHERINE C | E59: 1 | F59: 0 | H59: Parcial | I59: =IFERROR(IF(E59="","",E59*INDEX(ACTUALIZAR!$C$7:$C$18,MATCH(A59,ACTUALIZAR!$A$7:$A$18,0))/SUMIF($A$7:$A$200,A59,$E$7:$E$200)),"") -> 24837.237 | J59: =IFERROR(IF(E59="","",E59*INDEX(PPK!$F$7:$F$18,MATCH(A59,PPK!$A$7:$A$18,0))/SUMIF($A$7:$A$200,A59,$E$7:$E$200)),"") -> 19398.651 | K59: =IF(AND(I59="",J59=""),"",SUM(I59:J59)) -> 44235.887 | L59: =IFERROR(K59/E59,"") -> 44235.887 | M59: 2026-140 | N59: 840 | P59: =IF($A59='VISTA MES'!$B$4,COUNTIF($A$7:$A59,'VISTA MES'!$B$4),"")
A60: Julio | B60: 8399 | C60: HAPAG LLOYD / ON | D60: MANZANILLO EXPRESS | E60: 34 | F60: 33 | G60: 10.455724 | H60: Parcial | I60: =IFERROR(IF(E60="","",E60*INDEX(ACTUALIZAR!$C$7:$C$18,MATCH(A60,ACTUALIZAR!$A$7:$A$18,0))/SUMIF($A$7:$A$200,A60,$E$7:$E$200)),"") -> 844466.05 | J60: =IFERROR(IF(E60="","",E60*INDEX(PPK!$F$7:$F$18,MATCH(A60,PPK!$A$7:$A$18,0))/SUMIF($A$7:$A$200,A60,$E$7:$E$200)),"") -> 659554.13 | K60: =IF(AND(I60="",J60=""),"",SUM(I60:J60)) -> 1504020.2 | L60: =IFERROR(K60/E60,"") -> 44235.887 | M60: 2026-141 | N60: 30240 | P60: =IF($A60='VISTA MES'!$B$4,COUNTIF($A$7:$A60,'VISTA MES'!$B$4),"")
A61: Julio | B61: 8404 | C61: HAPAG LLOYD / ON | D61: ITAJAI EXPRESS | E61: 3 | F61: 3 | G61: 8.3590278 | H61: Disponible | I61: =IFERROR(IF(E61="","",E61*INDEX(ACTUALIZAR!$C$7:$C$18,MATCH(A61,ACTUALIZAR!$A$7:$A$18,0))/SUMIF($A$7:$A$200,A61,$E$7:$E$200)),"") -> 74511.71 | J61: =IFERROR(IF(E61="","",E61*INDEX(PPK!$F$7:$F$18,MATCH(A61,PPK!$A$7:$A$18,0))/SUMIF($A$7:$A$200,A61,$E$7:$E$200)),"") -> 58195.952 | K61: =IF(AND(I61="",J61=""),"",SUM(I61:J61)) -> 132707.66 | L61: =IFERROR(K61/E61,"") -> 44235.887 | M61: 2026-142 | N61: 3296 | P61: =IF($A61='VISTA MES'!$B$4,COUNTIF($A$7:$A61,'VISTA MES'!$B$4),"")
A62: Julio | B62: 8393 | C62: HAPAG LLOYD | D62: CAPE BRUNO | E62: 1 | F62: 1 | G62: 15.946528 | H62: Disponible | I62: =IFERROR(IF(E62="","",E62*INDEX(ACTUALIZAR!$C$7:$C$18,MATCH(A62,ACTUALIZAR!$A$7:$A$18,0))/SUMIF($A$7:$A$200,A62,$E$7:$E$200)),"") -> 24837.237 | J62: =IFERROR(IF(E62="","",E62*INDEX(PPK!$F$7:$F$18,MATCH(A62,PPK!$A$7:$A$18,0))/SUMIF($A$7:$A$200,A62,$E$7:$E$200)),"") -> 19398.651 | K62: =IF(AND(I62="",J62=""),"",SUM(I62:J62)) -> 44235.887 | L62: =IFERROR(K62/E62,"") -> 44235.887 | M62: 2026-145 | N62: 472 | P62: =IF($A62='VISTA MES'!$B$4,COUNTIF($A$7:$A62,'VISTA MES'!$B$4),"")
A63: Julio | B63: 8398 | C63: MAERSK | D63: POLAR ARGENTINA | E63: 14 | F63: 14 | G63: 4.0005456 | H63: Disponible | I63: =IFERROR(IF(E63="","",E63*INDEX(ACTUALIZAR!$C$7:$C$18,MATCH(A63,ACTUALIZAR!$A$7:$A$18,0))/SUMIF($A$7:$A$200,A63,$E$7:$E$200)),"") -> 347721.31 | J63: =IFERROR(IF(E63="","",E63*INDEX(PPK!$F$7:$F$18,MATCH(A63,PPK!$A$7:$A$18,0))/SUMIF($A$7:$A$200,A63,$E$7:$E$200)),"") -> 271581.11 | K63: =IF(AND(I63="",J63=""),"",SUM(I63:J63)) -> 619302.42 | L63: =IFERROR(K63/E63,"") -> 44235.887 | M63: 2026-146 | N63: 7168 | P63: =IF($A63='VISTA MES'!$B$4,COUNTIF($A$7:$A63,'VISTA MES'!$B$4),"")
A64: Julio | B64: 8397 | C64: MSC | D64: MSC LILY | E64: 2 | F64: 2 | G64: 4.5371528 | H64: Disponible | I64: =IFERROR(IF(E64="","",E64*INDEX(ACTUALIZAR!$C$7:$C$18,MATCH(A64,ACTUALIZAR!$A$7:$A$18,0))/SUMIF($A$7:$A$200,A64,$E$7:$E$200)),"") -> 49674.473 | J64: =IFERROR(IF(E64="","",E64*INDEX(PPK!$F$7:$F$18,MATCH(A64,PPK!$A$7:$A$18,0))/SUMIF($A$7:$A$200,A64,$E$7:$E$200)),"") -> 38797.302 | K64: =IF(AND(I64="",J64=""),"",SUM(I64:J64)) -> 88471.775 | L64: =IFERROR(K64/E64,"") -> 44235.887 | M64: 2026-147 | N64: 1864 | P64: =IF($A64='VISTA MES'!$B$4,COUNTIF($A$7:$A64,'VISTA MES'!$B$4),"")
A65: Julio | B65: 8406 | C65: MSC | D65: MSC SENEGAL | E65: 1 | F65: 1 | G65: 4.0027778 | H65: Disponible | I65: =IFERROR(IF(E65="","",E65*INDEX(ACTUALIZAR!$C$7:$C$18,MATCH(A65,ACTUALIZAR!$A$7:$A$18,0))/SUMIF($A$7:$A$200,A65,$E$7:$E$200)),"") -> 24837.237 | J65: =IFERROR(IF(E65="","",E65*INDEX(PPK!$F$7:$F$18,MATCH(A65,PPK!$A$7:$A$18,0))/SUMIF($A$7:$A$200,A65,$E$7:$E$200)),"") -> 19398.651 | K65: =IF(AND(I65="",J65=""),"",SUM(I65:J65)) -> 44235.887 | L65: =IFERROR(K65/E65,"") -> 44235.887 | M65: 2026-150 | N65: 840 | P65: =IF($A65='VISTA MES'!$B$4,COUNTIF($A$7:$A65,'VISTA MES'!$B$4),"")
A66: Julio | B66: 8403 | C66: MAERSK | D66: POLAR PERU | E66: 99 | F66: 98 | G66: 1.942191 | H66: Parcial | I66: =IFERROR(IF(E66="","",E66*INDEX(ACTUALIZAR!$C$7:$C$18,MATCH(A66,ACTUALIZAR!$A$7:$A$18,0))/SUMIF($A$7:$A$200,A66,$E$7:$E$200)),"") -> 2458886.4 | J66: =IFERROR(IF(E66="","",E66*INDEX(PPK!$F$7:$F$18,MATCH(A66,PPK!$A$7:$A$18,0))/SUMIF($A$7:$A$200,A66,$E$7:$E$200)),"") -> 1920466.4 | K66: =IF(AND(I66="",J66=""),"",SUM(I66:J66)) -> 4379352.9 | L66: =IFERROR(K66/E66,"") -> 44235.887 | M66: 2026-152 | N66: 35256 | P66: =IF($A66='VISTA MES'!$B$4,COUNTIF($A$7:$A66,'VISTA MES'!$B$4),"")
A67: Julio | B67: 8407 | C67: MAERSK | D67: POLAR COLOMBIA | E67: 188 | F67: 188 | G67: 1.1246749 | H67: Disponible | I67: =IFERROR(IF(E67="","",E67*INDEX(ACTUALIZAR!$C$7:$C$18,MATCH(A67,ACTUALIZAR!$A$7:$A$18,0))/SUMIF($A$7:$A$200,A67,$E$7:$E$200)),"") -> 4669400.5 | J67: =IFERROR(IF(E67="","",E67*INDEX(PPK!$F$7:$F$18,MATCH(A67,PPK!$A$7:$A$18,0))/SUMIF($A$7:$A$200,A67,$E$7:$E$200)),"") -> 3646946.4 | K67: =IF(AND(I67="",J67=""),"",SUM(I67:J67)) -> 8316346.8 | L67: =IFERROR(K67/E67,"") -> 44235.887 | M67: 2026-153 | N67: 47280 | P67: =IF($A67='VISTA MES'!$B$4,COUNTIF($A$7:$A67,'VISTA MES'!$B$4),"")
A68: Agosto | B68: 8411 | C68: HAPAG LLOYD / ON | D68: RIO DE JANEIRO EXPRESS | E68: 28 | F68: 28 | G68: 8.78 | H68: Disponible | I68: =IFERROR(IF(E68="","",E68*INDEX(ACTUALIZAR!$C$7:$C$18,MATCH(A68,ACTUALIZAR!$A$7:$A$18,0))/SUMIF($A$7:$A$200,A68,$E$7:$E$200)),"") -> 518981.12 | J68: =IFERROR(IF(E68="","",E68*INDEX(PPK!$F$7:$F$18,MATCH(A68,PPK!$A$7:$A$18,0))/SUMIF($A$7:$A$200,A68,$E$7:$E$200)),"") -> 794131.86 | K68: =IF(AND(I68="",J68=""),"",SUM(I68:J68)) -> 1313113 | L68: =IFERROR(K68/E68,"") -> 46896.892 | M68: 2026-143 | N68: 14096 | P68: =IF($A68='VISTA MES'!$B$4,COUNTIF($A$7:$A68,'VISTA MES'!$B$4),"")
A69: Agosto | B69: 8415 | C69: HAPAG LLOYD / ON | D69: BUENAVENTURA EXPRESS | E69: 10 | F69: 10 | G69: 8.34 | H69: Disponible | I69: =IFERROR(IF(E69="","",E69*INDEX(ACTUALIZAR!$C$7:$C$18,MATCH(A69,ACTUALIZAR!$A$7:$A$18,0))/SUMIF($A$7:$A$200,A69,$E$7:$E$200)),"") -> 185350.4 | J69: =IFERROR(IF(E69="","",E69*INDEX(PPK!$F$7:$F$18,MATCH(A69,PPK!$A$7:$A$18,0))/SUMIF($A$7:$A$200,A69,$E$7:$E$200)),"") -> 283618.52 | K69: =IF(AND(I69="",J69=""),"",SUM(I69:J69)) -> 468968.92 | L69: =IFERROR(K69/E69,"") -> 46896.892 | M69: 2026-154 | N69: 11920 | P69: =IF($A69='VISTA MES'!$B$4,COUNTIF($A$7:$A69,'VISTA MES'!$B$4),"")
A70: Agosto | B70: 8420 | C70: HAPAG LLOYD / ON | D70: LIMA EXPRESS | E70: 38 | F70: 38 | G70: 7.63 | H70: Disponible | I70: =IFERROR(IF(E70="","",E70*INDEX(ACTUALIZAR!$C$7:$C$18,MATCH(A70,ACTUALIZAR!$A$7:$A$18,0))/SUMIF($A$7:$A$200,A70,$E$7:$E$200)),"") -> 704331.52 | J70: =IFERROR(IF(E70="","",E70*INDEX(PPK!$F$7:$F$18,MATCH(A70,PPK!$A$7:$A$18,0))/SUMIF($A$7:$A$200,A70,$E$7:$E$200)),"") -> 1077750.4 | K70: =IF(AND(I70="",J70=""),"",SUM(I70:J70)) -> 1782081.9 | L70: =IFERROR(K70/E70,"") -> 46896.892 | M70: 2026-155 | N70: 32864 | P70: =IF($A70='VISTA MES'!$B$4,COUNTIF($A$7:$A70,'VISTA MES'!$B$4),"")
A71: Agosto | B71: 8412 | C71: MAERSK | D71: POLAR CHILE | E71: 260 | F71: 260 | G71: 1.72 | H71: Disponible | I71: =IFERROR(IF(E71="","",E71*INDEX(ACTUALIZAR!$C$7:$C$18,MATCH(A71,ACTUALIZAR!$A$7:$A$18,0))/SUMIF($A$7:$A$200,A71,$E$7:$E$200)),"") -> 4819110.4 | J71: =IFERROR(IF(E71="","",E71*INDEX(PPK!$F$7:$F$18,MATCH(A71,PPK!$A$7:$A$18,0))/SUMIF($A$7:$A$200,A71,$E$7:$E$200)),"") -> 7374081.6 | K71: =IF(AND(I71="",J71=""),"",SUM(I71:J71)) -> 12193192 | L71: =IFERROR(K71/E71,"") -> 46896.892 | M71: 2026-158 | N71: 88096 | P71: =IF($A71='VISTA MES'!$B$4,COUNTIF($A$7:$A71,'VISTA MES'!$B$4),"")
... A79: Agosto | B79: 8423 | C79: MSC | D79: MSC QINGDAO | E79: 1 | F79: 1 | G79: 4.75 | H79: Disponible | I79: =IFERROR(IF(E79="","",E79*INDEX(ACTUALIZAR!$C$7:$C$18,MATCH(A79,ACTUALIZAR!$A$7:$A$18,0))/SUMIF($A$7:$A$200,A79,$E$7:$E$200)),"") -> 18535.04 | J79: =IFERROR(IF(E79="","",E79*INDEX(PPK!$F$7:$F$18,MATCH(A79,PPK!$A$7:$A$18,0))/SUMIF($A$7:$A$200,A79,$E$7:$E$200)),"") -> 28361.852 | K79: =IF(AND(I79="",J79=""),"",SUM(I79:J79)) -> 46896.892 | L79: =IFERROR(K79/E79,"") -> 46896.892 | M79: 2026-179 | N79: 984 | P79: =IF($A79='VISTA MES'!$B$4,COUNTIF($A$7:$A79,'VISTA MES'!$B$4),"")
A80: Agosto | B80: 8410 | C80: Por confirmar | D80: CAPE BRUNO 1 | E80: 6 | F80: 6 | G80: 1.39 | H80: Disponible | I80: =IFERROR(IF(E80="","",E80*INDEX(ACTUALIZAR!$C$7:$C$18,MATCH(A80,ACTUALIZAR!$A$7:$A$18,0))/SUMIF($A$7:$A$200,A80,$E$7:$E$200)),"") -> 111210.24 | J80: =IFERROR(IF(E80="","",E80*INDEX(PPK!$F$7:$F$18,MATCH(A80,PPK!$A$7:$A$18,0))/SUMIF($A$7:$A$200,A80,$E$7:$E$200)),"") -> 170171.11 | K80: =IF(AND(I80="",J80=""),"",SUM(I80:J80)) -> 281381.35 | L80: =IFERROR(K80/E80,"") -> 46896.892 | N80: 0 | P80: =IF($A80='VISTA MES'!$B$4,COUNTIF($A$7:$A80,'VISTA MES'!$B$4),"")
A81: Agosto | B81: 8418 | C81: Por confirmar | D81: CAPE BRUNO 2 | E81: 18 | F81: 18 | G81: 5.2 | H81: Disponible | I81: =IFERROR(IF(E81="","",E81*INDEX(ACTUALIZAR!$C$7:$C$18,MATCH(A81,ACTUALIZAR!$A$7:$A$18,0))/SUMIF($A$7:$A$200,A81,$E$7:$E$200)),"") -> 333630.72 | J81: =IFERROR(IF(E81="","",E81*INDEX(PPK!$F$7:$F$18,MATCH(A81,PPK!$A$7:$A$18,0))/SUMIF($A$7:$A$200,A81,$E$7:$E$200)),"") -> 510513.34 | K81: =IF(AND(I81="",J81=""),"",SUM(I81:J81)) -> 844144.06 | L81: =IFERROR(K81/E81,"") -> 46896.892 | N81: 0 | P81: =IF($A81='VISTA MES'!$B$4,COUNTIF($A$7:$A81,'VISTA MES'!$B$4),"")
A82: Septiembre | B82: 8426 | C82: Por confirmar | D82: ALIOTH 1 | E82: 1 | F82: 1 | G82: 6.04 | H82: Disponible | I82: =IFERROR(IF(E82="","",E82*INDEX(ACTUALIZAR!$C$7:$C$18,MATCH(A82,ACTUALIZAR!$A$7:$A$18,0))/SUMIF($A$7:$A$200,A82,$E$7:$E$200)),"") -> 12383.722 | J82: =IFERROR(IF(E82="","",E82*INDEX(PPK!$F$7:$F$18,MATCH(A82,PPK!$A$7:$A$18,0))/SUMIF($A$7:$A$200,A82,$E$7:$E$200)),"") -> 22315.252 | K82: =IF(AND(I82="",J82=""),"",SUM(I82:J82)) -> 34698.974 | L82: =IFERROR(K82/E82,"") -> 34698.974 | M82: 2026-182 | N82: 656 | P82: =IF($A82='VISTA MES'!$B$4,COUNTIF($A$7:$A82,'VISTA MES'!$B$4),"") -> 1
A83: Septiembre | B83: 8427 | C83: MSC | D83: MSC ABUJA VI | E83: 4 | F83: 4 | G83: 5.44 | H83: Disponible | I83: =IFERROR(IF(E83="","",E83*INDEX(ACTUALIZAR!$C$7:$C$18,MATCH(A83,ACTUALIZAR!$A$7:$A$18,0))/SUMIF($A$7:$A$200,A83,$E$7:$E$200)),"") -> 49534.887 | J83: =IFERROR(IF(E83="","",E83*INDEX(PPK!$F$7:$F$18,MATCH(A83,PPK!$A$7:$A$18,0))/SUMIF($A$7:$A$200,A83,$E$7:$E$200)),"") -> 89261.008 | K83: =IF(AND(I83="",J83=""),"",SUM(I83:J83)) -> 138795.9 | L83: =IFERROR(K83/E83,"") -> 34698.974 | M83: 2026-181 | N83: 3200 | P83: =IF($A83='VISTA MES'!$B$4,COUNTIF($A$7:$A83,'VISTA MES'!$B$4),"") -> 2
A84: Septiembre | B84: 8428 | C84: Por confirmar | D84: CAPE BRUNO 1 | E84: 2 | F84: 2 | G84: 4.6 | H84: Disponible | I84: =IFERROR(IF(E84="","",E84*INDEX(ACTUALIZAR!$C$7:$C$18,MATCH(A84,ACTUALIZAR!$A$7:$A$18,0))/SUMIF($A$7:$A$200,A84,$E$7:$E$200)),"") -> 24767.444 | J84: =IFERROR(IF(E84="","",E84*INDEX(PPK!$F$7:$F$18,MATCH(A84,PPK!$A$7:$A$18,0))/SUMIF($A$7:$A$200,A84,$E$7:$E$200)),"") -> 44630.504 | K84: =IF(AND(I84="",J84=""),"",SUM(I84:J84)) -> 69397.948 | L84: =IFERROR(K84/E84,"") -> 34698.974 | M84: 2026-185 | N84: 512 | P84: =IF($A84='VISTA MES'!$B$4,COUNTIF($A$7:$A84,'VISTA MES'!$B$4),"") -> 3
A85: Septiembre | B85: 8429 | C85: Por confirmar | D85: LITTLE ATHINA | E85: 1 | F85: 0 | H85: Parcial | I85: =IFERROR(IF(E85="","",E85*INDEX(ACTUALIZAR!$C$7:$C$18,MATCH(A85,ACTUALIZAR!$A$7:$A$18,0))/SUMIF($A$7:$A$200,A85,$E$7:$E$200)),"") -> 12383.722 | J85: =IFERROR(IF(E85="","",E85*INDEX(PPK!$F$7:$F$18,MATCH(A85,PPK!$A$7:$A$18,0))/SUMIF($A$7:$A$200,A85,$E$7:$E$200)),"") -> 22315.252 | K85: =IF(AND(I85="",J85=""),"",SUM(I85:J85)) -> 34698.974 | L85: =IFERROR(K85/E85,"") -> 34698.974 | N85: 0 | P85: =IF($A85='VISTA MES'!$B$4,COUNTIF($A$7:$A85,'VISTA MES'!$B$4),"") -> 4
A86: Septiembre | B86: 8430 | C86: MAERSK | D86: POLAR CHILE | E86: 268 | F86: 267 | G86: 2.69 | H86: Parcial | I86: =IFERROR(IF(E86="","",E86*INDEX(ACTUALIZAR!$C$7:$C$18,MATCH(A86,ACTUALIZAR!$A$7:$A$18,0))/SUMIF($A$7:$A$200,A86,$E$7:$E$200)),"") -> 3318837.5 | J86: =IFERROR(IF(E86="","",E86*INDEX(PPK!$F$7:$F$18,MATCH(A86,PPK!$A$7:$A$18,0))/SUMIF($A$7:$A$200,A86,$E$7:$E$200)),"") -> 5980487.5 | K86: =IF(AND(I86="",J86=""),"",SUM(I86:J86)) -> 9299325 | L86: =IFERROR(K86/E86,"") -> 34698.974 | M86: 2026-186 | N86: 145144 | P86: =IF($A86='VISTA MES'!$B$4,COUNTIF($A$7:$A86,'VISTA MES'!$B$4),"") -> 5
A87: Septiembre | B87: 8431 | C87: HAPAG LLOYD / ON | D87: HUMBOLDT EXPRESS | E87: 17 | F87: 17 | G87: 8.62 | H87: Disponible | I87: =IFERROR(IF(E87="","",E87*INDEX(ACTUALIZAR!$C$7:$C$18,MATCH(A87,ACTUALIZAR!$A$7:$A$18,0))/SUMIF($A$7:$A$200,A87,$E$7:$E$200)),"") -> 210523.27 | J87: =IFERROR(IF(E87="","",E87*INDEX(PPK!$F$7:$F$18,MATCH(A87,PPK!$A$7:$A$18,0))/SUMIF($A$7:$A$200,A87,$E$7:$E$200)),"") -> 379359.28 | K87: =IF(AND(I87="",J87=""),"",SUM(I87:J87)) -> 589882.55 | L87: =IFERROR(K87/E87,"") -> 34698.974 | M87: 2026-177 | N87: 16440 | P87: =IF($A87='VISTA MES'!$B$4,COUNTIF($A$7:$A87,'VISTA MES'!$B$4),"") -> 6
A88: Septiembre | B88: 8432 | C88: SEABOARD | D88: MOLLY SCHULTE 1 | E88: 9 | F88: 9 | G88: 9.29 | H88: Disponible | I88: =IFERROR(IF(E88="","",E88*INDEX(ACTUALIZAR!$C$7:$C$18,MATCH(A88,ACTUALIZAR!$A$7:$A$18,0))/SUMIF($A$7:$A$200,A88,$E$7:$E$200)),"") -> 111453.5 | J88: =IFERROR(IF(E88="","",E88*INDEX(PPK!$F$7:$F$18,MATCH(A88,PPK!$A$7:$A$18,0))/SUMIF($A$7:$A$200,A88,$E$7:$E$200)),"") -> 200837.27 | K88: =IF(AND(I88="",J88=""),"",SUM(I88:J88)) -> 312290.76 | L88: =IFERROR(K88/E88,"") -> 34698.974 | M88: 2026-192 | N88: 7560 | P88: =IF($A88='VISTA MES'!$B$4,COUNTIF($A$7:$A88,'VISTA MES'!$B$4),"") -> 7
A89: Septiembre | B89: 8433 | C89: MSC | D89: MSC YOKOHAMA | E89: 12 | F89: 12 | G89: 6.06 | H89: Disponible | I89: =IFERROR(IF(E89="","",E89*INDEX(ACTUALIZAR!$C$7:$C$18,MATCH(A89,ACTUALIZAR!$A$7:$A$18,0))/SUMIF($A$7:$A$200,A89,$E$7:$E$200)),"") -> 148604.66 | J89: =IFERROR(IF(E89="","",E89*INDEX(PPK!$F$7:$F$18,MATCH(A89,PPK!$A$7:$A$18,0))/SUMIF($A$7:$A$200,A89,$E$7:$E$200)),"") -> 267783.02 | K89: =IF(AND(I89="",J89=""),"",SUM(I89:J89)) -> 416387.69 | L89: =IFERROR(K89/E89,"") -> 34698.974 | M89: 2026-188 | N89: 12000 | P89: =IF($A89='VISTA MES'!$B$4,COUNTIF($A$7:$A89,'VISTA MES'!$B$4),"") -> 8
A90: Septiembre | B90: 8434 | C90: MAERSK | D90: POLAR ARGENTINA | E90: 210 | F90: 210 | G90: 2.91 | H90: Disponible | I90: =IFERROR(IF(E90="","",E90*INDEX(ACTUALIZAR!$C$7:$C$18,MATCH(A90,ACTUALIZAR!$A$7:$A$18,0))/SUMIF($A$7:$A$200,A90,$E$7:$E$200)),"") -> 2600581.6 | J90: =IFERROR(IF(E90="","",E90*INDEX(PPK!$F$7:$F$18,MATCH(A90,PPK!$A$7:$A$18,0))/SUMIF($A$7:$A$200,A90,$E$7:$E$200)),"") -> 4686202.9 | K90: =IF(AND(I90="",J90=""),"",SUM(I90:J90)) -> 7286784.5 | L90: =IFERROR(K90/E90,"") -> 34698.974 | M90: 2026-187 | N90: 147896 | P90: =IF($A90='VISTA MES'!$B$4,COUNTIF($A$7:$A90,'VISTA MES'!$B$4),"") -> 9
A91: Septiembre | B91: 8436 | C91: Por confirmar | D91: ALIOTH 2 | E91: 1 | F91: 1 | G91: 6.52 | H91: Disponible | I91: =IFERROR(IF(E91="","",E91*INDEX(ACTUALIZAR!$C$7:$C$18,MATCH(A91,ACTUALIZAR!$A$7:$A$18,0))/SUMIF($A$7:$A$200,A91,$E$7:$E$200)),"") -> 12383.722 | J91: =IFERROR(IF(E91="","",E91*INDEX(PPK!$F$7:$F$18,MATCH(A91,PPK!$A$7:$A$18,0))/SUMIF($A$7:$A$200,A91,$E$7:$E$200)),"") -> 22315.252 | K91: =IF(AND(I91="",J91=""),"",SUM(I91:J91)) -> 34698.974 | L91: =IFERROR(K91/E91,"") -> 34698.974 | M91: 2026-196 | N91: 616 | P91: =IF($A91='VISTA MES'!$B$4,COUNTIF($A$7:$A91,'VISTA MES'!$B$4),"") -> 10
A92: Septiembre | B92: 8437 | C92: Por confirmar | D92: CAPE BRUNO 2 | E92: 1 | F92: 1 | G92: 2.34 | H92: Disponible | I92: =IFERROR(IF(E92="","",E92*INDEX(ACTUALIZAR!$C$7:$C$18,MATCH(A92,ACTUALIZAR!$A$7:$A$18,0))/SUMIF($A$7:$A$200,A92,$E$7:$E$200)),"") -> 12383.722 | J92: =IFERROR(IF(E92="","",E92*INDEX(PPK!$F$7:$F$18,MATCH(A92,PPK!$A$7:$A$18,0))/SUMIF($A$7:$A$200,A92,$E$7:$E$200)),"") -> 22315.252 | K92: =IF(AND(I92="",J92=""),"",SUM(I92:J92)) -> 34698.974 | L92: =IFERROR(K92/E92,"") -> 34698.974 | N92: 0 | P92: =IF($A92='VISTA MES'!$B$4,COUNTIF($A$7:$A92,'VISTA MES'!$B$4),"") -> 11
A93: Septiembre | B93: 8438 | C93: HAPAG LLOYD / ON | D93: ONE SINCERITY | E93: 37 | F93: 37 | G93: 7.17 | H93: Disponible | I93: =IFERROR(IF(E93="","",E93*INDEX(ACTUALIZAR!$C$7:$C$18,MATCH(A93,ACTUALIZAR!$A$7:$A$18,0))/SUMIF($A$7:$A$200,A93,$E$7:$E$200)),"") -> 458197.71 | J93: =IFERROR(IF(E93="","",E93*INDEX(PPK!$F$7:$F$18,MATCH(A93,PPK!$A$7:$A$18,0))/SUMIF($A$7:$A$200,A93,$E$7:$E$200)),"") -> 825664.32 | K93: =IF(AND(I93="",J93=""),"",SUM(I93:J93)) -> 1283862 | L93: =IFERROR(K93/E93,"") -> 34698.974 | M93: 2026-190 | N93: 27608 | P93: =IF($A93='VISTA MES'!$B$4,COUNTIF($A$7:$A93,'VISTA MES'!$B$4),"") -> 12
A94: Septiembre | B94: 8439 | C94: MAERSK | D94: POLAR PERU | E94: 166 | F94: 166 | G94: 2 | H94: Disponible | I94: =IFERROR(IF(E94="","",E94*INDEX(ACTUALIZAR!$C$7:$C$18,MATCH(A94,ACTUALIZAR!$A$7:$A$18,0))/SUMIF($A$7:$A$200,A94,$E$7:$E$200)),"") -> 2055697.8 | J94: =IFERROR(IF(E94="","",E94*INDEX(PPK!$F$7:$F$18,MATCH(A94,PPK!$A$7:$A$18,0))/SUMIF($A$7:$A$200,A94,$E$7:$E$200)),"") -> 3704331.8 | K94: =IF(AND(I94="",J94=""),"",SUM(I94:J94)) -> 5760029.7 | L94: =IFERROR(K94/E94,"") -> 34698.974 | M94: 2026-200 | N94: 69784 | P94: =IF($A94='VISTA MES'!$B$4,COUNTIF($A$7:$A94,'VISTA MES'!$B$4),"") -> 13
A95: Septiembre | B95: 8440 | C95: MSC | D95: MSC FLORIANA VI | E95: 2 | F95: 2 | G95: 12.09 | H95: Disponible | I95: =IFERROR(IF(E95="","",E95*INDEX(ACTUALIZAR!$C$7:$C$18,MATCH(A95,ACTUALIZAR!$A$7:$A$18,0))/SUMIF($A$7:$A$200,A95,$E$7:$E$200)),"") -> 24767.444 | J95: =IFERROR(IF(E95="","",E95*INDEX(PPK!$F$7:$F$18,MATCH(A95,PPK!$A$7:$A$18,0))/SUMIF($A$7:$A$200,A95,$E$7:$E$200)),"") -> 44630.504 | K95: =IF(AND(I95="",J95=""),"",SUM(I95:J95)) -> 69397.948 | L95: =IFERROR(K95/E95,"") -> 34698.974 | M95: 2026-199 | N95: 4704 | P95: =IF($A95='VISTA MES'!$B$4,COUNTIF($A$7:$A95,'VISTA MES'!$B$4),"") -> 14
A96: Septiembre | B96: 8442 | C96: HAPAG LLOYD / ON | D96: ONE SAPHIRE | E96: 29 | F96: 29 | G96: 5.51 | H96: Disponible | I96: =IFERROR(IF(E96="","",E96*INDEX(ACTUALIZAR!$C$7:$C$18,MATCH(A96,ACTUALIZAR!$A$7:$A$18,0))/SUMIF($A$7:$A$200,A96,$E$7:$E$200)),"") -> 359127.93 | J96: =IFERROR(IF(E96="","",E96*INDEX(PPK!$F$7:$F$18,MATCH(A96,PPK!$A$7:$A$18,0))/SUMIF($A$7:$A$200,A96,$E$7:$E$200)),"") -> 647142.31 | K96: =IF(AND(I96="",J96=""),"",SUM(I96:J96)) -> 1006270.2 | L96: =IFERROR(K96/E96,"") -> 34698.974 | M96: 2026-191 | N96: 26856 | P96: =IF($A96='VISTA MES'!$B$4,COUNTIF($A$7:$A96,'VISTA MES'!$B$4),"") -> 15
A97: Septiembre | B97: 8443 | C97: MAERSK | D97: POLAR COLOMBIA | E97: 387 | F97: 385 | G97: 2.02 | H97: Parcial | I97: =IFERROR(IF(E97="","",E97*INDEX(ACTUALIZAR!$C$7:$C$18,MATCH(A97,ACTUALIZAR!$A$7:$A$18,0))/SUMIF($A$7:$A$200,A97,$E$7:$E$200)),"") -> 4792500.4 | J97: =IFERROR(IF(E97="","",E97*INDEX(PPK!$F$7:$F$18,MATCH(A97,PPK!$A$7:$A$18,0))/SUMIF($A$7:$A$200,A97,$E$7:$E$200)),"") -> 8636002.5 | K97: =IF(AND(I97="",J97=""),"",SUM(I97:J97)) -> 13428503 | L97: =IFERROR(K97/E97,"") -> 34698.974 | M97: 2026-204 | N97: 166640 | P97: =IF($A97='VISTA MES'!$B$4,COUNTIF($A$7:$A97,'VISTA MES'!$B$4),"") -> 16
A98: Septiembre | B98: 8444 | C98: Por confirmar | D98: ALIOTH 3 | E98: 1 | F98: 1 | G98: 4.01 | H98: Disponible | I98: =IFERROR(IF(E98="","",E98*INDEX(ACTUALIZAR!$C$7:$C$18,MATCH(A98,ACTUALIZAR!$A$7:$A$18,0))/SUMIF($A$7:$A$200,A98,$E$7:$E$200)),"") -> 12383.722 | J98: =IFERROR(IF(E98="","",E98*INDEX(PPK!$F$7:$F$18,MATCH(A98,PPK!$A$7:$A$18,0))/SUMIF($A$7:$A$200,A98,$E$7:$E$200)),"") -> 22315.252 | K98: =IF(AND(I98="",J98=""),"",SUM(I98:J98)) -> 34698.974 | L98: =IFERROR(K98/E98,"") -> 34698.974 | M98: 2026-198 | N98: 656 | P98: =IF($A98='VISTA MES'!$B$4,COUNTIF($A$7:$A98,'VISTA MES'!$B$4),"") -> 17
A99: Septiembre | B99: 8445 | C99: Por confirmar | D99: CAPE BRUNO 3 | E99: 3 | F99: 1 | G99: 2.42 | H99: Parcial | I99: =IFERROR(IF(E99="","",E99*INDEX(ACTUALIZAR!$C$7:$C$18,MATCH(A99,ACTUALIZAR!$A$7:$A$18,0))/SUMIF($A$7:$A$200,A99,$E$7:$E$200)),"") -> 37151.166 | J99: =IFERROR(IF(E99="","",E99*INDEX(PPK!$F$7:$F$18,MATCH(A99,PPK!$A$7:$A$18,0))/SUMIF($A$7:$A$200,A99,$E$7:$E$200)),"") -> 66945.756 | K99: =IF(AND(I99="",J99=""),"",SUM(I99:J99)) -> 104096.92 | L99: =IFERROR(K99/E99,"") -> 34698.974 | M99: 2026-202 | N99: 552 | P99: =IF($A99='VISTA MES'!$B$4,COUNTIF($A$7:$A99,'VISTA MES'!$B$4),"") -> 18

Sheet PPK
A1: PPK — EQUIPOS, DÍAS Y COSTO REAL 2026
A2: Resumen mensual y detalle por equipo. Una fila por PPK y mes; los periodos múltiples quedan consolidados.
A4: RESUMEN MENSUAL
A6: Mes | B6: PPK únicos | C6: Días-PPK | D6: Arriendo CLP | E6: Camioneta CLP | F6: PPK total CLP
A7: Enero | B7: =IF(COUNTIF($A$23:$A$150,A7)>0,COUNTIF($A$23:$A$150,A7),"") -> 2 | C7: =IF(B7="","",SUMIF($A$23:$A$150,A7,$E$23:$E$150)) -> 31 | D7: 8496139 | E7: =IF(ACTUALIZAR!D7="","",ACTUALIZAR!D7) -> 1018645 | F7: =IF(AND(D7="",E7=""),"",SUM(D7:E7)) -> 9514784
A8: Febrero | B8: =IF(COUNTIF($A$23:$A$150,A8)>0,COUNTIF($A$23:$A$150,A8),"") -> 2 | C8: =IF(B8="","",SUMIF($A$23:$A$150,A8,$E$23:$E$150)) -> 34 | D8: 9318346 | E8: =IF(ACTUALIZAR!D8="","",ACTUALIZAR!D8) -> 1018645 | F8: =IF(AND(D8="",E8=""),"",SUM(D8:E8)) -> 10336991
A9: Marzo | B9: =IF(COUNTIF($A$23:$A$150,A9)>0,COUNTIF($A$23:$A$150,A9),"") -> 2 | C9: =IF(B9="","",SUMIF($A$23:$A$150,A9,$E$23:$E$150)) -> 31 | D9: 8496139 | E9: =IF(ACTUALIZAR!D9="","",ACTUALIZAR!D9) -> 1018645 | F9: =IF(AND(D9="",E9=""),"",SUM(D9:E9)) -> 9514784
A10: Abril | B10: =IF(COUNTIF($A$23:$A$150,A10)>0,COUNTIF($A$23:$A$150,A10),"") -> 1 | C10: =IF(B10="","",SUMIF($A$23:$A$150,A10,$E$23:$E$150)) -> 30 | D10: 8222070 | E10: =IF(ACTUALIZAR!D10="","",ACTUALIZAR!D10) -> 1018645 | F10: =IF(AND(D10="",E10=""),"",SUM(D10:E10)) -> 9240715
A11: Mayo | B11: =IF(COUNTIF($A$23:$A$150,A11)>0,COUNTIF($A$23:$A$150,A11),"") -> 2 | C11: =IF(B11="","",SUMIF($A$23:$A$150,A11,$E$23:$E$150)) -> 31 | D11: 8496139 | E11: =IF(ACTUALIZAR!D11="","",ACTUALIZAR!D11) -> 1018645 | F11: =IF(AND(D11="",E11=""),"",SUM(D11:E11)) -> 9514784
A12: Junio | B12: =IF(COUNTIF($A$23:$A$150,A12)>0,COUNTIF($A$23:$A$150,A12),"") -> 3 | C12: =IF(B12="","",SUMIF($A$23:$A$150,A12,$E$23:$E$150)) -> 32 | D12: 8770208 | E12: =IF(ACTUALIZAR!D12="","",ACTUALIZAR!D12) -> 1018645 | F12: =IF(AND(D12="",E12=""),"",SUM(D12:E12)) -> 9788853
A13: Julio | B13: =IF(COUNTIF($A$23:$A$150,A13)>0,COUNTIF($A$23:$A$150,A13),"") -> 4 | C13: =IF(B13="","",SUMIF($A$23:$A$150,A13,$E$23:$E$150)) -> 35 | D13: 9592417 | E13: =IF(ACTUALIZAR!D13="","",ACTUALIZAR!D13) -> 1018645 | F13: =IF(AND(D13="",E13=""),"",SUM(D13:E13)) -> 10611062
A14: Agosto | B14: =IF(COUNTIF($A$23:$A$150,A14)>0,COUNTIF($A$23:$A$150,A14),"") -> 9 | C14: =IF(B14="","",SUMIF($A$23:$A$150,A14,$E$23:$E$150)) -> 74 | D14: 20281106 | E14: =IF(ACTUALIZAR!D14="","",ACTUALIZAR!D14) -> 1018645 | F14: =IF(AND(D14="",E14=""),"",SUM(D14:E14)) -> 21299751
A15: Septiembre | B15: =IF(COUNTIF($A$23:$A$150,A15)>0,COUNTIF($A$23:$A$150,A15),"") -> 9 | C15: =IF(B15="","",SUMIF($A$23:$A$150,A15,$E$23:$E$150)) -> 90 | D15: 24666210 | E15: =IF(ACTUALIZAR!D15="","",ACTUALIZAR!D15) -> 1018645 | F15: =IF(AND(D15="",E15=""),"",SUM(D15:E15)) -> 25684855
A16: Octubre | B16: =IF(COUNTIF($A$23:$A$150,A16)>0,COUNTIF($A$23:$A$150,A16),"") | C16: =IF(B16="","",SUMIF($A$23:$A$150,A16,$E$23:$E$150)) | E16: =IF(ACTUALIZAR!D16="","",ACTUALIZAR!D16) | F16: =IF(AND(D16="",E16=""),"",SUM(D16:E16))
A17: Noviembre | B17: =IF(COUNTIF($A$23:$A$150,A17)>0,COUNTIF($A$23:$A$150,A17),"") | C17: =IF(B17="","",SUMIF($A$23:$A$150,A17,$E$23:$E$150)) | E17: =IF(ACTUALIZAR!D17="","",ACTUALIZAR!D17) | F17: =IF(AND(D17="",E17=""),"",SUM(D17:E17))
A18: Diciembre | B18: =IF(COUNTIF($A$23:$A$150,A18)>0,COUNTIF($A$23:$A$150,A18),"") | C18: =IF(B18="","",SUMIF($A$23:$A$150,A18,$E$23:$E$150)) | E18: =IF(ACTUALIZAR!D18="","",ACTUALIZAR!D18) | F18: =IF(AND(D18="",E18=""),"",SUM(D18:E18))
A20: DETALLE POR PPK — agrega los meses nuevos en la primera fila libre debajo de la tabla
A22: Mes | B22: PPK | C22: Tipo | D22: Períodos utilizados | E22: Días | F22: Costo arriendo CLP
A23: Enero | B23: PPK 16 | C23: Principal | D23: 01–05 ene | E23: 5 | F23: 1370345
A24: Enero | B24: PPK 99 | C24: Principal | D24: 06–31 ene | E24: 26 | F24: 7125794
A25: Febrero | B25: PPK 16 | C25: Backup | D25: 31 ene–05 feb | E25: 6 | F25: 1644414
A26: Febrero | B26: PPK 99 | C26: Principal | D26: 01–28 feb | E26: 28 | F26: 7673932
A27: Marzo | B27: PPK 16 | C27: Backup | D27: 01–16 mar | E27: 16 | F27: 4385104
A28: Marzo | B28: PPK 96 | C28: Principal | D28: 17–31 mar | E28: 15 | F28: 4111035
A29: Abril | B29: PPK 96 | C29: Principal | D29: 01–30 abr | E29: 30 | F29: 8222070
A30: Mayo | B30: PPK 16 | C30: Backup | D30: 01–03 may | E30: 3 | F30: 822207
A31: Mayo | B31: PPK 96 | C31: Principal | D31: 04–31 may | E31: 28 | F31: 7673932
A32: Junio | B32: PPK 16 | C32: Principal | D32: 26–30 jun | E32: 5 | F32: 1370345
A33: Junio | B33: PPK 79 | C33: Principal | D33: 19–20 jun | E33: 2 | F33: 548138
A34: Junio | B34: PPK 99 | C34: Principal | D34: 01–25 jun | E34: 25 | F34: 6851725
... A56: Septiembre | B56: PPK 90 | C56: Principal | D56: 10–13 sep; 17–19 sep | E56: 7 | F56: 1918483

Sheet ACTUALIZAR
A1: ACTUALIZAR MESES — COSTOS REALES REEFER 2026
A2: Completa las celdas amarillas para octubre–diciembre; después agrega los PPK y las naves en sus tablas.
A4: Combustible: total mensual en litros y USD. Se mantiene separado y no se distribuye por nave.
